Workbook

Sheet BankPresentation BS
A1: Bravado Spice LLC
A2: Comparative Balance Sheets
C4: December 31,
C5: 2022 | D5: 2021
A6: Assets
A7: Current Assets
B8: Cash | C8: ='Balance Sheet'!B15 -> 49122.45 | D8: ='Balance Sheet'!C15 -> 97922.05
B9: Accounts receivable | C9: ='Balance Sheet'!B18 -> 176485.4 | D9: ='Balance Sheet'!C18 -> 158704.13
B10: Inventory | C10: ='Balance Sheet'!B27 -> 390898.41 | D10: ='Balance Sheet'!C27 -> 313525.6
B11: Other | C11: ='Balance Sheet'!B20+'Balance Sheet'!B29+'Balance Sheet'!B30+'Balance Sheet'!B31 -> 40490.52 | D11: ='Balance Sheet'!C29+'Balance Sheet'!C31 -> 27482.35
B12: Total current assets | C12: =SUM(C8:C11) -> 656996.78 | D12: =SUM(D8:D11) -> 597634.13
A14: Property & Equipment
B15: Machinery | C15: ='Balance Sheet'!B35 -> 14069.56 | D15: ='Balance Sheet'!C35 -> 14069.56
B16: Vehicles | C16: ='Balance Sheet'!B36+'Balance Sheet'!B37+'Balance Sheet'!B38 -> 85655.92 | D16: ='Balance Sheet'!C36+'Balance Sheet'!C37+'Balance Sheet'!C38 -> 85655.92
B17: Accumulated depreciation | C17: ='Balance Sheet'!B39 -> -99725.48 | D17: ='Balance Sheet'!C39 -> -99725.48
B18: Total property & equipment | C18: =SUM(C15:C17) -> 0
A20: Other Assets | C20: ='Balance Sheet'!B43 -> 8799.4 | D20: ='Balance Sheet'!C42 -> 8799.4
B21: Total assets | C21: =C12+C18+C20 -> 665796.18 | D21: =D12+D18+D20 -> 606433.53
A23: Liabilities and Equity
A24: Current Liabilities
B25: Accounts payable | C25: ='Balance Sheet'!B50 -> 109115.57 | D25: ='Balance Sheet'!C50 -> 190713.27
B26: Credit cards | C26: ='Balance Sheet'!B62 -> 115930.39 | D26: ='Balance Sheet'!C62 -> 66219.9
B27: LOC | C27: ='Balance Sheet'!B69 -> 113361.74 | D27: ='Balance Sheet'!C69 -> 0
B28: Other | C28: ='Balance Sheet'!B71+'Balance Sheet'!B73 -> 9714 | D28: ='Balance Sheet'!C71+'Balance Sheet'!C73 -> 15330.8
B29: Total current liabilities | C29: =SUM(C25:C28) -> 348121.7 | D29: =SUM(D25:D28) -> 272263.97
A31: Long-Term Debt | C31: ='Balance Sheet'!B85 -> 152599.61 | D31: ='Balance Sheet'!C85 -> 105749.99
A33: Equity
B34: Members interests | C34: ='Balance Sheet'!B88+'Balance Sheet'!B90+'Balance Sheet'!B91 -> -57246.07 | D34: ='Balance Sheet'!C88+'Balance Sheet'!C90+'Balance Sheet'!C91 -> -14443.04
B35: Retained earnings | C35: ='Balance Sheet'!B89+'Balance Sheet'!B92 -> 222320.94 | D35: ='Balance Sheet'!C89+'Balance Sheet'!C92 -> 242862.61
B36: Total equity | C36: =SUM(C34:C35) -> 165074.87 | D36: =SUM(D34:D35) -> 228419.57
B37: Total liabilities and equity | C37: =C29+C31+C36 -> 665796.18 | D37: =D29+D31+D36 -> 606433.53

Sheet Bank Presentation IS
A1: Bravado Spice LLC
A2: Comparative Balance Sheets
C4: ACTUAL | G4: PRE_CLOSING | I4: FORECAST
C5: Year Ended December 31,
C6: 2020 | E6: 2021 | G6: 2022 | I6: 2023
A8: Sales | C8: ='2024 Monthly'!E14 -> 2169255.1 | D8: =C8/C$8 -> 1 | E8: ='2024 Monthly'!G14 -> 2201897 | F8: =E8/E$8 -> 1 | G8: ='2024 Monthly'!M14 -> 2325993.4 | H8: =G8/G$8 -> 1 | I8: ='2024 Monthly'!T14 -> 3130981.5 | J8: =I8/I$8 -> 1
A10: Cost of Goods Sold | C10: ='2024 Monthly'!E23 -> 1214762.6 | D10: =C10/C$8 -> 0.55999065 | E10: ='2024 Monthly'!G23 -> 1468052.7 | F10: =E10/E$8 -> 0.66672179 | G10: ='2024 Monthly'!M23 -> 1311764.4 | H10: =G10/G$8 -> 0.56395879 | I10: ='2024 Monthly'!T23 -> 1732402.9 | J10: =I10/I$8 -> 0.55330987
A11: Gross Margin | C11: =C8-C10 -> 954492.55 | D11: =C11/C$8 -> 0.44000935 | E11: =E8-E10 -> 733844.3 | F11: =E11/E$8 -> 0.33327821 | G11: =G8-G10 -> 1014229 | H11: =G11/G$8 -> 0.43604121 | I11: =I8-I10 -> 1398578.5 | J11: =I11/I$8 -> 0.44669013
A12: Selling, General & Administrative Expenses
B13: Compensation | C13: ='2024 Monthly'!E42 -> 302985.14 | D13: =C13/C$8 -> 0.13967243 | E13: ='2024 Monthly'!G42 -> 444817.26 | F13: =E13/E$8 -> 0.20201547 | G13: ='2024 Monthly'!M42 -> 550362.48 | H13: =G13/G$8 -> 0.23661395 | I13: ='2024 Monthly'!T42 -> 653489.76 | J13: =I13/I$8 -> 0.20871722
B14: Marketing & advertising | C14: ='2024 Monthly'!E43 -> 126166.54 | D14: =C14/C$8 -> 0.058161227 | E14: ='2024 Monthly'!G43 -> 153428.37 | F14: =E14/E$8 -> 0.069680085 | G14: ='2024 Monthly'!M43 -> 182977.57 | H14: =G14/G$8 -> 0.07866642 | I14: ='2024 Monthly'!T43 -> 215700 | J14: =I14/I$8 -> 0.068892135
B15: Rent | C15: ='2024 Monthly'!E51 -> 32084.48 | D15: =C15/C$8 -> 0.014790552 | E15: ='2024 Monthly'!G51 -> 84207.42 | F15: =E15/E$8 -> 0.038243124 | G15: ='2024 Monthly'!M51 -> 109405.43 | H15: =G15/G$8 -> 0.047036003 | I15: ='2024 Monthly'!T51 -> 114000 | J15: =I15/I$8 -> 0.036410308
B16: Office expenses | C16: ='2024 Monthly'!E52 -> 28881.79 | D16: =C16/C$8 -> 0.013314151 | E16: ='2024 Monthly'!G52 -> 62978.55 | F16: =E16/E$8 -> 0.028601951 | G16: ='2024 Monthly'!M52 -> 65098.44 | H16: =G16/G$8 -> 0.027987371 | I16: ='2024 Monthly'!T52 -> 60000 | J16: =I16/I$8 -> 0.01916332
B17: Professional fees | C17: ='2024 Monthly'!E59 -> 14641.91 | D17: =C17/C$8 -> 0.0067497408 | E17: ='2024 Monthly'!G59 -> 25989.68 | F17: =E17/E$8 -> 0.011803313 | G17: ='2024 Monthly'!M59 -> 19266.98 | H17: =G17/G$8 -> 0.0082833341 | I17: ='2024 Monthly'!T59 -> 41766.98 | J17: =I17/I$8 -> 0.0133399
B18: Travel | C18: ='2024 Monthly'!E53 -> 6913.83 | D18: =C18/C$8 -> 0.0031871908 | E18: ='2024 Monthly'!G53 -> 9268.26 | F18: =E18/E$8 -> 0.0042092159 | G18: ='2024 Monthly'!M53 -> 23883.94 | H18: =G18/G$8 -> 0.010268275 | I18: ='2024 Monthly'!T53 -> 23883.94 | J18: =I18/I$8 -> 0.0076282598
B19: Software dues & subscriptions | C19: ='2024 Monthly'!E54 -> 9832.89 | D19: =C19/C$8 -> 0.0045328416 | E19: ='2024 Monthly'!G54 -> 13230.97 | F19: =E19/E$8 -> 0.0060088959 | G19: ='2024 Monthly'!M54 -> 20485.7 | H19: =G19/G$8 -> 0.0088072908 | I19: ='2024 Monthly'!T54 -> 20485.7 | J19: =I19/I$8 -> 0.0065429004
B20: Insurance | C20: ='2024 Monthly'!E55 -> 9618.2 | D20: =C20/C$8 -> 0.0044338722 | E20: ='2024 Monthly'!G55 -> 19428.15 | F20: =E20/E$8 -> 0.0088233691 | G20: ='2024 Monthly'!M55 -> 16312.52 | H20: =G20/G$8 -> 0.0070131413 | I20: ='2024 Monthly'!T55 -> 17128.146 | J20: =I20/I$8 -> 0.0054705357
B21: Utilities | C21: ='2024 Monthly'!E56 -> 4766.11 | D21: =C21/C$8 -> 0.0021971182 | E21: ='2024 Monthly'!G56 -> 12331.72 | F21: =E21/E$8 -> 0.0056004981 | G21: ='2024 Monthly'!M56 -> 13550.21 | H21: =G21/G$8 -> 0.0058255583 | I21: ='2024 Monthly'!T56 -> 13550.21 | J21: =I21/I$8 -> 0.0043277835
B22: Repairs & maintenance | C22: ='2024 Monthly'!E60 -> 3200.57 | D22: =C22/C$8 -> 0.0014754235 | E22: ='2024 Monthly'!G60 -> 8234.48 | F22: =E22/E$8 -> 0.0037397208 | G22: ='2024 Monthly'!M60 -> 11019.92 | H22: =G22/G$8 -> 0.0047377263 | I22: ='2024 Monthly'!T60 -> 11019.92 | J22: =I22/I$8 -> 0.0035196376
B23: Taxes & licenses | C23: ='2024 Monthly'!E61 -> 3042.38 | D23: =C23/C$8 -> 0.0014024998 | E23: ='2024 Monthly'!G61 -> 22007.56 | F23: =E23/E$8 -> 0.0099948181 | G23: ='2024 Monthly'!M61 -> 9261.62 | H23: =G23/G$8 -> 0.0039817912 | I23: ='2024 Monthly'!T61 -> 9901.794 | J23: =I23/I$8 -> 0.0031625208
B24: Reimbursements | C24: ='2024 Monthly'!E62 -> 0 | D24: =C24/C$8 -> 0 | E24: ='2024 Monthly'!G62 -> 32.44 | F24: =E24/E$8 -> 1.4732751e-05 | G24: ='2024 Monthly'!M62 -> 3653.13 | H24: =G24/G$8 -> 0.0015705677 | I24: ='2024 Monthly'!T62 -> 3653.13 | J24: =I24/I$8 -> 0.0011667683
B25: Bad debts | C25: ='2024 Monthly'!E67 -> 6737.83 | D25: =C25/C$8 -> 0.0031060569 | E25: ='2024 Monthly'!G67 -> 0 | F25: =E25/E$8 -> 0 | G25: ='2024 Monthly'!M67 -> 0 | H25: =G25/G$8 -> 0 | I25: ='2024 Monthly'!T67 -> 2000 | J25: =I25/I$8 -> 0.00063877733
B26: Miscellaneous | C26: ='2024 Monthly'!E68 -> 4773.89 | D26: =C26/C$8 -> 0.0022007047 | E26: ='2024 Monthly'!G68 -> 1597.54 | F26: =E26/E$8 -> 0.00072552894 | G26: ='2024 Monthly'!M68 -> 1085.26 | H26: =G26/G$8 -> 0.00046657915 | I26: ='2024 Monthly'!T68 -> 10000 | J26: =I26/I$8 -> 0.0031938867
B27: Total S, G & A expenses | C27: =SUM(C13:C26) -> 553645.56 | D27: =C27/C$8 -> 0.25522381 | E27: =SUM(E13:E26) -> 857552.4 | F27: =E27/E$8 -> 0.38946072 | G27: =SUM(G13:G26) -> 1026363.2 | H27: =G27/G$8 -> 0.44125801 | I27: =SUM(I13:I26) -> 1196579.6 | J27: =I27/I$8 -> 0.38217396
A28: EBITDA | C28: =C11-C27 -> 400846.99 | D28: =C28/C$8 -> 0.18478554 | E28: =E11-E27 -> -123708.1 | F28: =E28/E$8 -> -0.05618251 | G28: =G11-G27 -> -12134.23 | H28: =G28/G$8 -> -0.0052167948 | I28: =I11-I27 -> 201998.95 | J28: =I28/I$8 -> 0.064516175
A30: Other Income/Expenses
B31: Non-operating | C31: ='2024 Monthly'!#REF! -> #REF! | D31: =C31/C$8 -> #REF! | E31: ='2024 Monthly'!#REF! -> #REF! | F31: =E31/E$8 -> #REF! | G31: ='2024 Monthly'!#REF! -> #REF! | H31: =G31/G$8 -> #REF! | I31: ='2024 Monthly'!#REF! -> #REF! | J31: =I31/I$8 -> #REF!
B32: Interest & fees | C32: ='2024 Monthly'!E82 -> 2481.65 | D32: =C32/C$8 -> 0.0011440102 | E32: ='2024 Monthly'!G82 -> 8155.74 | F32: =E32/E$8 -> 0.0037039607 | G32: ='2024 Monthly'!M82 -> 33783.04 | H32: =G32/G$8 -> 0.014524134 | I32: ='2024 Monthly'!T82 -> 30404.736 | J32: =I32/I$8 -> 0.0097109281
B33: Depreciation | C33: ='2024 Monthly'!E86 -> 0 | D33: =C33/C$8 -> 0 | E33: ='2024 Monthly'!G86 -> 0 | F33: =E33/E$8 -> 0 | G33: ='2024 Monthly'!M86 -> 0 | H33: =G33/G$8 -> 0 | I33: ='2024 Monthly'!T86 -> 0 | J33: =I33/I$8 -> 0
A34: Net Income(Loss) | C34: =C28-C31-C32-C33 -> #REF! | D34: =C34/C$8 -> #REF! | E34: =E28-E31-E32-E33 -> #REF! | F34: =E34/E$8 -> #REF! | G34: =G28-G31-G32-G33 -> #REF! | H34: =G34/G$8 -> #REF! | I34: =I28-I31-I32-I33 -> #REF! | J34: =I34/I$8 -> #REF!

Sheet IS v PY
A1: Bravado Spice
A2: Income Statement
C3: Four Months Ended April 30,
C4: 2023 | E4: 2022
A5: Sales
B6: Retail | C6: 72718 | D6: =C6/C$10 -> 0.1043872 | E6: 92509 | F6: =E6/E$10 -> 0.12327433
B7: Online/Amazon | C7: =65107+46128 -> 111235 | D7: =C7/C$10 -> 0.15967862 | E7: =62366+75286 -> 137652 | F7: =E7/E$10 -> 0.18343034
B8: Distributor | C8: 204747 | D8: =C8/C$10 -> 0.29391575 | E8: 169379 | F8: =E8/E$10 -> 0.22570866
B9: Franchise | C9: 307918 | D9: =C9/C$10 -> 0.44201844 | E9: 350892 | F9: =E9/E$10 -> 0.46758667
B10: Total sales | C10: =SUM(C6:C9) -> 696618 | D10: =C10/C$10 -> 1 | E10: =SUM(E6:E9) -> 750432 | F10: =E10/E$10 -> 1
A11: Cost of Sales | C11: 372326 | D11: =C11/C$10 -> 0.53447657 | E11: 439232 | F11: =E11/E$10 -> 0.58530553
A12: Gross Margin | C12: =C10-C11 -> 324292 | D12: =C12/C$10 -> 0.46552343 | E12: =E10-E11 -> 311200 | F12: =E12/E$10 -> 0.41469447
A14: Selling, General & Administrative
B15: Compensation
B16: Salaries & wages | C16: 129607 | D16: =C16/C$10 -> 0.18605175 | E16: 115382 | F16: =E16/E$10 -> 0.1537541
B17: Contract labor | C17: 34626 | D17: =C17/C$10 -> 0.049705865 | E17: 21259 | F17: =E17/E$10 -> 0.028329016
B18: Payroll taxes | C18: 10032 | D18: =C18/C$10 -> 0.014401006 | E18: 9035 | F18: =E18/E$10 -> 0.012039732
B19: Employee benefits | C19: 4147 | D19: =C19/C$10 -> 0.0059530474 | E19: 6169 | F19: =E19/E$10 -> 0.0082205983
B20: Total compensation | C20: =SUM(C16:C19) -> 178412 | D20: =C20/C$10 -> 0.25611167 | E20: =SUM(E16:E19) -> 151845 | F20: =E20/E$10 -> 0.20234345
B21: Marketing & advertising | C21: 58892 | D21: =C21/C$10 -> 0.084539877 | E21: 46619 | F21: =E21/E$10 -> 0.062122884
B22: Rent | C22: 46647 | D22: =C22/C$10 -> 0.066962094 | E22: 34822 | F22: =E22/E$10 -> 0.046402605
B23: Other G&A | C23: =SUM(C24:C35) -> 81756 | D23: =C23/C$10 -> 0.11736131 | E23: =SUM(E24:E35) -> 56628 | F23: =E23/E$10 -> 0.075460535
B24: Office expenses | C24: 17745 | D24: =C24/C$10 -> 0.025473071 | E24: 14657 | F24: =E24/E$10 -> 0.019531417
B25: Travel | C25: 11836 | D25: =C25/C$10 -> 0.016990661 | E25: 9654 | F25: =E25/E$10 -> 0.01286459
B26: Dues & subscriptions | C26: 10026 | D26: =C26/C$10 -> 0.014392393 | E26: 5512 | F26: =E26/E$10 -> 0.0073451026
B27: Insurance | C27: 7765 | D27: =C27/C$10 -> 0.011146712 | E27: 6891 | F27: =E27/E$10 -> 0.0091827108
B28: Utilities | C28: 5418 | D28: =C28/C$10 -> 0.0077775768 | E28: 4528 | F28: =E28/E$10 -> 0.0060338578
B29: Professional fees | C29: 13153 | D29: =C29/C$10 -> 0.018881223 | E29: 2789 | F29: =E29/E$10 -> 0.0037165259
B30: Repairs & maintenance | C30: 4291 | D30: =C30/C$10 -> 0.0061597604 | E30: 6105 | F30: =E30/E$10 -> 0.0081353141
B31: Taxes & licenses | C31: 849 | D31: =C31/C$10 -> 0.0012187454 | E31: 2320 | F31: =E31/E$10 -> 0.0030915526
B32: Reimbursements | C32: 1453 | D32: =C32/C$10 -> 0.0020857916 | E32: 1029 | F32: =E32/E$10 -> 0.0013712102
B33: Bank fees | C33: 9042 | D33: =C33/C$10 -> 0.012979854 | E33: 2959 | F33: =E33/E$10 -> 0.0039430621
B34: Bad debts | C34: 0 | D34: =C34/C$10 -> 0 | E34: 0 | F34: =E34/E$10 -> 0
B35: Miscellaneous | C35: 178 | D35: =C35/C$10 -> 0.00025552024 | E35: 184 | F35: =E35/E$10 -> 0.0002451921
B36: Total SG&A | C36: =SUM(C20:C35)-C23 -> 365707 | D36: =C36/C$10 -> 0.52497495 | E36: =SUM(E20:E35)-E23 -> 289914 | F36: =E36/E$10 -> 0.38632947
A37: EBITDA | C37: =C12-C36 -> -41415 | D37: =C37/C$10 -> -0.059451521 | E37: =E12-E36 -> 21286 | F37: =E37/E$10 -> 0.028364995
A38: Other Income/Expenses
B39: Nonoperating income/expenses | D39: =C39/C$10 -> 0 | F39: =E39/E$10 -> 0
B40: Interest & CC fees | C40: 22470 | D40: =C40/C$10 -> 0.032255842 | E40: 2092 | F40: =E40/E$10 -> 0.0027877276
B41: Depreciation | C41: =QB!F131 -> 0 | D41: =C41/C$10 -> 0 | F41: =E41/E$10 -> 0
A42: Net Income | C42: =C37-C39-C40-C41 -> -63885 | D42: =C42/C$10 -> -0.091707363 | E42: =E37-E39-E40-E41 -> 19194 | F42: =E42/E$10 -> 0.025577267

Sheet Financial Trend.Budget
A1: Bravado Spice
A2: Forecast 2024-2025 | AJ2: 2024 by Month | AZ2: 2025 by Month
K3: 2023 Forecast (Original) | R3: 2023 Forecast (Original)
A4: (assuming Investment November, 2024) | K4: 2023 | R4: 2024 | Z4: 2025 | AJ4: Actual | AR4: Budget | AZ4: Budget
C5: 2019 | E5: 2020 | G5: 2021 | I5: 2022 | K5: Q1 | L5: Q2 | M5: Q3 | N5: Q4 | O5: 2023 | R5: Q1 | S5: Q2 | T5: Q3 | U5: Q4 | V5: 2024 | X5: Notes | Z5: Q1 | AA5: Q2 | AB5: Q3 | AC5: Q4 | AD5: 2025 | AF5: Q3 Actual | AG5: Oct | AH5: Nov | AI5: Dec | AJ5: Jan | AK5: Feb | AL5: Mar | AM5: Apr | AN5: May | AO5: June | AP5: July | AQ5: Aug | AR5: Sept | AS5: Oct | AT5: Nov | AU5: Dec | AV5: 2024 Total | AX5: Assumptions | AZ5: Jan | BA5: Feb | BB5: Mar | BC5: Apr | BD5: May | BE5: June | BF5: July | BG5: Aug | BH5: Sept | BI5: Oct | BJ5: Nov | BK5: Dec | BL5: 2025 Total
A6: Sales
B7: Retail | AV7: =SUM(AJ7:AU7) -> 0 | AW7: =AV7/AV$15 -> 0 | BL7: =SUM(AZ7:BK7) -> 0
B8: Online/Amazon | AV8: =SUM(AJ8:AU8) -> 0 | AW8: =AV8/AV$15 -> 0 | BL8: =SUM(AZ8:BK8) -> 0
B9: Less Amazon netting | AV9: =SUM(AJ9:AU9) -> 0 | AW9: =AV9/AV$15 -> 0 | BL9: =SUM(AZ9:BK9) -> 0
B10: Distributor | AV10: =SUM(AJ10:AU10) -> 0 | AW10: =AV10/AV$15 -> 0 | BL10: =SUM(AZ10:BK10) -> 0
B11: Franchise | AV11: =SUM(AJ11:AU11) -> 0 | AW11: =AV11/AV$15 -> 0 | BL11: =SUM(AZ11:BK11) -> 0
B12: Total hot sauce | C12: =QB!F20+QB!F30+QB!F33+QB!F34+QB!F40 -> 1176162.1 | E12: =QB!K20+QB!K30+QB!K33+QB!K34+QB!K40 -> 1985300.7 | G12: =QB!P20+QB!P30+QB!P33+QB!P34+QB!P40 -> 1946199.2
B13: Mixers & seasonings | C13: =QB!F24+QB!F29 -> 98761.52 | E13: =QB!K24+QB!K29 -> 182871.54 | G13: =QB!P24+QB!P29 -> 249354.5
B14: Other | C14: =QB!F42+QB!F43+QB!F44 -> 5945.28 | E14: =QB!K42+QB!K43+QB!K44 -> 1082.89 | G14: =QB!P42+QB!P43+QB!P44 -> 6343.26
A15: Sales | C15: =SUM(C12:C14) -> 1280868.9 | D15: =C15/C$15 -> 1 | E15: =SUM(E12:E14) -> 2169255.1 | F15: =E15/E$15 -> 1 | G15: =SUM(G12:G14) -> 2201897 | H15: =G15/G$15 -> 1 | I15: 2321440 | J15: =I15/I$15 -> 1 | K15: 570041 | L15: 405174 | M15: 347143 | N15: 432361 | O15: =SUM(K15:N15) -> 1754719 | P15: =O15/O$15 -> 1 | R15: =SUM(AJ15:AL15) -> 232955 | S15: =SUM(AM15:AO15) -> 218307 | T15: =SUM(AP15:AR15) -> 177640 | U15: =SUM(AS15:AU15) -> 320000 | V15: =SUM(R15:U15) -> 948902 | W15: =V15/V$15 -> 1 | Z15: =SUM(AZ15:BB15) -> 270000 | AA15: =SUM(BC15:BE15) -> 350000 | AB15: =SUM(BF15:BH15) -> 390000 | AC15: =SUM(BI15:BK15) -> 485000 | AD15: =SUM(Z15:AC15) -> 1495000 | AF15: 347143 | AG15: 155912 | AH15: 147384 | AI15: 129065 | AJ15: 97342 | AK15: 69706 | AL15: 65907 | AM15: 58908 | AN15: 77566 | AO15: 81833 | AP15: 64514 | AQ15: 34126 | AR15: 79000 | AS15: 120000 | AT15: 100000 | AU15: 100000 | AV15: =SUM(AJ15:AU15) -> 948902 | AW15: =AV15/AV$15 -> 1 | AX15: Per Jer | AZ15: 100000 | BA15: 80000 | BB15: 90000 | BC15: 110000 | BD15: 120000 | BE15: 120000 | BF15: 120000 | BG15: 130000 | BH15: 140000 | BI15: 180000 | BJ15: 180000 | BK15: 125000 | BL15: =SUM(AZ15:BK15) -> 1495000 | BM15: =BL15/BL$15 -> 1
A16: Cost of Sales
B17: Co-Packer & ingredients | C17: =QB!F47+QB!F48+QB!F50+QB!F51 -> 497738.93 | D17: =C17/C$15 -> 0.38859476 | E17: 725353 | F17: =E17/E$15 -> 0.33437883 | G17: =QB!P47+QB!P48+QB!P50+QB!P51 -> 943998.9 | H17: =G17/G$15 -> 0.42872073 | I17: 1012654 | J17: =I17/I$15 -> 0.43621804 | K17: 342783 | L17: 213990 | M17: 225540 | N17: 184128 | O17: =SUM(K17:N17) -> 966441 | P17: =O17/O$15 -> 0.55076682 | R17: =SUM(AJ17:AL17) -> 101494 | S17: =SUM(AM17:AO17) -> 125394 | T17: =SUM(AP17:AR17) -> 63093 | U17: =SUM(AS17:AU17) -> 134400 | V17: =SUM(R17:U17) -> 424381 | W17: =V17/V$15 -> 0.44723375 | Z17: =SUM(AZ17:BB17) -> 113400 | AA17: =SUM(BC17:BE17) -> 147000 | AB17: =SUM(BF17:BH17) -> 163800 | AC17: =SUM(BI17:BK17) -> 203700 | AD17: =SUM(Z17:AC17) -> 627900 | AF17: 199547 | AG17: 51354 | AH17: 56556 | AI17: 54070 | AJ17: 40909 | AK17: 27875 | AL17: 32710 | AM17: 44532 | AN17: 47512 | AO17: 33350 | AP17: 21398 | AQ17: 11321 | AR17: 30374 | AS17: =AS15*0.42 -> 50400 | AT17: =AT15*0.42 -> 42000 | AU17: =AU15*0.42 -> 42000 | AV17: =SUM(AJ17:AU17) -> 424381 | AW17: =AV17/AV$15 -> 0.44723375 | AX17: 45% of sales starting June | AZ17: =AZ15*0.42 -> 42000 | BA17: =BA15*0.42 -> 33600 | BB17: =BB15*0.42 -> 37800 | BC17: =BC15*0.42 -> 46200 | BD17: =BD15*0.42 -> 50400 | BE17: =BE15*0.42 -> 50400 | BF17: =BF15*0.42 -> 50400 | BG17: =BG15*0.42 -> 54600 | ... BK17: =BK15*0.42 -> 52500 | BL17: =SUM(AZ17:BK17) -> 627900 | BM17: =BL17/BL$15 -> 0.42
B18: Shipping & delivery | C18: =QB!F49 -> 115308.88 | D18: =C18/C$15 -> 0.090023954 | E18: =QB!K49 -> 198278.67 | F18: =E18/E$15 -> 0.091404034 | G18: =QB!P49 -> 268052.97 | H18: =G18/G$15 -> 0.12173729 | I18: 214975 | J18: =I18/I$15 -> 0.092604159 | K18: 46962 | L18: 32407 | M18: 27976 | N18: 27158 | O18: =SUM(K18:N18) -> 134503 | P18: =O18/O$15 -> 0.076652159 | R18: =SUM(AJ18:AL18) -> 18015 | S18: =SUM(AM18:AO18) -> 12763 | T18: =SUM(AP18:AR18) -> 11467 | U18: =SUM(AS18:AU18) -> 19200 | V18: =SUM(R18:U18) -> 61445 | W18: =V18/V$15 -> 0.064753789 | Z18: =SUM(AZ18:BB18) -> 16200 | AA18: =SUM(BC18:BE18) -> 21000 | AB18: =SUM(BF18:BH18) -> 23400 | AC18: =SUM(BI18:BK18) -> 29100 | AD18: =SUM(Z18:AC18) -> 89700 | AF18: 27976 | AG18: 8573 | AH18: 10446 | AI18: 8139 | AJ18: 8646 | AK18: 5159 | AL18: 4210 | AM18: 4062 | AN18: 5030 | AO18: 3671 | AP18: 4688 | AQ18: 3279 | AR18: 3500 | AS18: =0.06*AS15 -> 7200 | AT18: =0.06*AT15 -> 6000 | AU18: =0.06*AU15 -> 6000 | AV18: =SUM(AJ18:AU18) -> 61445 | AW18: =AV18/AV$15 -> 0.064753789 | AX18: 7% of sales | AZ18: =0.06*AZ15 -> 6000 | BA18: =0.06*BA15 -> 4800 | BB18: =0.06*BB15 -> 5400 | BC18: =0.06*BC15 -> 6600 | BD18: =0.06*BD15 -> 7200 | BE18: =0.06*BE15 -> 7200 | BF18: =0.06*BF15 -> 7200 | BG18: =0.06*BG15 -> 7800 | ... BK18: =0.06*BK15 -> 7500 | BL18: =SUM(AZ18:BK18) -> 89700 | BM18: =BL18/BL$15 -> 0.06
B19: Inventory adjustment | I19: -100 | J19: =I19/I$15 -> -4.3076711e-05 | O19: =SUM(K19:N19) -> 0 | R19: =SUM(AJ19:AL19) -> 6240 | S19: =SUM(AM19:AO19) -> 3848 | T19: =SUM(AP19:AR19) -> 2171 | U19: =SUM(AS19:AU19) -> 0 | V19: =SUM(R19:U19) -> 12259 | W19: =V19/V$15 -> 0.012919142 | Z19: =SUM(AZ19:BB19) -> 0 | AA19: =SUM(BC19:BE19) -> 0 | AB19: =SUM(BF19:BH19) -> 0 | AC19: =SUM(BI19:BK19) -> 0 | AD19: =SUM(Z19:AC19) -> 0 | AJ19: 6900 | AK19: -2315 | AL19: 1655 | AM19: 2783 | AN19: 696 | AO19: 369 | AP19: 1326 | AQ19: 845 | AV19: =SUM(AJ19:AU19) -> 12259 | AW19: =AV19/AV$15 -> 0.012919142 | BL19: =SUM(AZ19:BK19) -> 0 | BM19: =BL19/BL$15 -> 0
B20: Materials | C20: =QB!F52 -> 128054.04 | D20: =C20/C$15 -> 0.099974356 | E20: =QB!K52 -> 194413.35 | F20: =E20/E$15 -> 0.089622169 | G20: =QB!P52 -> 179567.31 | H20: =G20/G$15 -> 0.081551185 | J20: =I20/I$15 -> 0 | K20: =SUM(I20:J20) -> 0 | L20: =SUM(I20:K20) -> 0 | M20: =SUM(J20:L20) -> 0 | N20: =SUM(K20:M20) -> 0 | O20: =SUM(K20:N20) -> 0 | P20: =O20/O$15 -> 0 | R20: =SUM(AJ20:AL20) -> 0 | S20: =SUM(AM20:AO20) -> 0 | T20: =SUM(AP20:AR20) -> 0 | U20: =SUM(AS20:AU20) -> 0 | V20: =SUM(R20:U20) -> 0 | W20: =V20/V$15 -> 0 | Z20: =SUM(AZ20:BB20) -> 0 | AA20: =SUM(BC20:BE20) -> 0 | AB20: =SUM(BF20:BH20) -> 0 | AC20: =SUM(BI20:BK20) -> 0 | AD20: =SUM(Z20:AC20) -> 0 | AV20: =SUM(AJ20:AU20) -> 0 | AW20: =AV20/AV$15 -> 0 | BL20: =SUM(AZ20:BK20) -> 0 | BM20: =BL20/BL$15 -> 0
B21: KeHe slotting fees | O21: =SUM(K21:N21) -> 0 | R21: =SUM(AJ21:AL21) -> 0 | S21: =SUM(AM21:AO21) -> 0 | T21: =SUM(AP21:AR21) -> 0 | U21: =SUM(AS21:AU21) -> 0 | V21: =SUM(R21:U21) -> 0 | W21: =V21/V$15 -> 0 | Z21: =SUM(AZ21:BB21) -> 0 | AA21: =SUM(BC21:BE21) -> 0 | AB21: =SUM(BF21:BH21) -> 0 | AC21: =SUM(BI21:BK21) -> 0 | AD21: =SUM(Z21:AC21) -> 0 | AV21: =SUM(AJ21:AU21) -> 0 | AW21: =AV21/AV$15 -> 0 | BL21: =SUM(AZ21:BK21) -> 0 | BM21: =BL21/BL$15 -> 0
B22: Swell/other discounts | C22: 25822 | D22: =C22/C$15 -> 0.020159753 | E22: 62660 | F22: =E22/E$15 -> 0.028885491 | I22: 82476 | J22: =I22/I$15 -> 0.035527948 | K22: 18624 | L22: 15910 | M22: 46676 | N22: 34766 | O22: =SUM(K22:N22) -> 115976 | P22: =O22/O$15 -> 0.066093773 | R22: =SUM(AJ22:AL22) -> 42841 | S22: =SUM(AM22:AO22) -> 11937 | T22: =SUM(AP22:AR22) -> 13016 | U22: =SUM(AS22:AU22) -> 19200 | V22: =SUM(R22:U22) -> 86994 | W22: =V22/V$15 -> 0.091678593 | Z22: =SUM(AZ22:BB22) -> 16200 | AA22: =SUM(BC22:BE22) -> 17500 | AB22: =SUM(BF22:BH22) -> 19500 | AC22: =SUM(BI22:BK22) -> 24250 | AD22: =SUM(Z22:AC22) -> 77450 | AF22: 52288 | AG22: 20454 | AH22: 12986 | AI22: 2493 | AJ22: 19221 | AK22: 18623 | AL22: 4997 | AM22: 7371 | AN22: 2440 | AO22: 2126 | AP22: 5444 | AQ22: 3298 | AR22: 4274 | AS22: =AS15*0.06 -> 7200 | AT22: =AT15*0.06 -> 6000 | AU22: =AU15*0.06 -> 6000 | AV22: =SUM(AJ22:AU22) -> 86994 | AW22: =AV22/AV$15 -> 0.091678593 | AX22: 8% of sales, bump in June promo, 6% last few mos | AZ22: =AZ15*0.06 -> 6000 | BA22: =BA15*0.06 -> 4800 | BB22: =BB15*0.06 -> 5400 | BC22: =BC15*0.05 -> 5500 | BD22: =BD15*0.05 -> 6000 | BE22: =BE15*0.05 -> 6000 | BF22: =BF15*0.05 -> 6000 | BG22: =BG15*0.05 -> 6500 | BH22: =BH15*0.05 -> 7000 | BI22: =BI15*0.05 -> 9000 | BJ22: =BJ15*0.05 -> 9000 | BK22: =BK15*0.05 -> 6250 | BL22: =SUM(AZ22:BK22) -> 77450 | BM22: =BL22/BL$15 -> 0.05180602
B23: Other | D23: =C23/C$15 -> 0 | E23: 33331 | F23: =E23/E$15 -> 0.015365182 | G23: =QB!P53+QB!P54+QB!P55+QB!P56+QB!P57+QB!P58+QB!P59+QB!P60+QB!P61+QB!P62+QB!P64 -> 76433.53 | H23: =G23/G$15 -> 0.034712582 | I23: 1566 | J23: =I23/I$15 -> 0.00067458129 | K23: 7237 | L23: 1331 | M23: 9057 | N23: 4257 | O23: =SUM(K23:N23) -> 21882 | P23: =O23/O$15 -> 0.012470373 | R23: =SUM(AJ23:AL23) -> 7098 | S23: =SUM(AM23:AO23) -> 6573 | T23: =SUM(AP23:AR23) -> 9959 | U23: =SUM(AS23:AU23) -> 9600 | V23: =SUM(R23:U23) -> 33230 | W23: =V23/V$15 -> 0.035019422 | Z23: =SUM(AZ23:BB23) -> 8100 | AA23: =SUM(BC23:BE23) -> 10500 | AB23: =SUM(BF23:BH23) -> 11700 | AC23: =SUM(BI23:BK23) -> 14550 | AD23: =SUM(Z23:AC23) -> 44850 | AF23: 29434 | AG23: 10167 | AH23: 6575 | AI23: 9120 | AJ23: 1408 | AK23: 97 | AL23: 5593 | AM23: 5783 | AN23: 484 | AO23: 306 | AP23: 2519 | AQ23: 440 | AR23: 7000 | AS23: =AS15*0.03 -> 3600 | AT23: =AT15*0.03 -> 3000 | AU23: =AU15*0.03 -> 3000 | AV23: =SUM(AJ23:AU23) -> 33230 | AW23: =AV23/AV$15 -> 0.035019422 | AX23: 3% of sales | AZ23: =AZ15*0.03 -> 3000 | BA23: =BA15*0.03 -> 2400 | BB23: =BB15*0.03 -> 2700 | BC23: =BC15*0.03 -> 3300 | BD23: =BD15*0.03 -> 3600 | BE23: =BE15*0.03 -> 3600 | BF23: =BF15*0.03 -> 3600 | BG23: =BG15*0.03 -> 3900 | ... BK23: =BK15*0.03 -> 3750 | BL23: =SUM(AZ23:BK23) -> 44850 | BM23: =BL23/BL$15 -> 0.03
B24: Total CGS | C24: =SUM(C17:C23) -> 766923.85 | D24: =C24/C$15 -> 0.59875282 | E24: =SUM(E17:E23) -> 1214036 | F24: =E24/E$15 -> 0.55965571 | G24: =SUM(G17:G23) -> 1468052.7 | H24: =G24/G$15 -> 0.66672179 | I24: =SUM(I17:I23) -> 1311571 | J24: =I24/I$15 -> 0.56498165 | K24: =SUM(K17:K23) -> 415606 | L24: =SUM(L17:L23) -> 263638 | M24: =SUM(M17:M23) -> 309249 | N24: =SUM(N17:N23) -> 250309 | O24: =SUM(O17:O23) -> 1238802 | P24: =O24/O$15 -> 0.70598312 | R24: =SUM(R17:R23) -> 175688 | S24: =SUM(S17:S23) -> 160515 | T24: =SUM(T17:T23) -> 99706 | U24: =SUM(U17:U23) -> 182400 | V24: =SUM(V17:V23) -> 618309 | W24: =V24/V$15 -> 0.6516047 | Z24: =SUM(Z17:Z23) -> 153900 | AA24: =SUM(AA17:AA23) -> 196000 | AB24: =SUM(AB17:AB23) -> 218400 | AC24: =SUM(AC17:AC23) -> 271600 | AD24: =SUM(AD17:AD23) -> 839900 | AF24: =SUM(AF17:AF23) -> 309245 | AG24: =SUM(AG17:AG23) -> 90548 | AH24: =SUM(AH17:AH23) -> 86563 | AI24: =SUM(AI17:AI23) -> 73822 | AJ24: =SUM(AJ17:AJ23) -> 77084 | AK24: =SUM(AK17:AK23) -> 49439 | AL24: =SUM(AL17:AL23) -> 49165 | AM24: =SUM(AM17:AM23) -> 64531 | ... AV24: =SUM(AV17:AV23) -> 618309 | AW24: =AV24/AV$15 -> 0.6516047 | AZ24: =SUM(AZ17:AZ23) -> 57000 | BA24: =SUM(BA17:BA23) -> 45600 | BB24: =SUM(BB17:BB23) -> 51300 | BC24: =SUM(BC17:BC23) -> 61600 | BD24: =SUM(BD17:BD23) -> 67200 | BE24: =SUM(BE17:BE23) -> 67200 | BF24: =SUM(BF17:BF23) -> 67200 | BG24: =SUM(BG17:BG23) -> 72800 | ... BL24: =SUM(BL17:BL23) -> 839900 | BM24: =BL24/BL$15 -> 0.56180602
A25: Gross Margin | C25: =C15-C24 -> 513945.02 | D25: =C25/C$15 -> 0.40124718 | E25: =E15-E24 -> 955219.12 | F25: =E25/E$15 -> 0.44034429 | G25: =G15-G24 -> 733844.3 | H25: =G25/G$15 -> 0.33327821 | I25: =I15-I24 -> 1009869 | J25: =I25/I$15 -> 0.43501835 | K25: =K15-K24 -> 154435 | L25: =L15-L24 -> 141536 | M25: =M15-M24 -> 37894 | N25: =N15-N24 -> 182052 | O25: =O15-O24 -> 515917 | P25: =O25/O$15 -> 0.29401688 | R25: =R15-R24 -> 57267 | S25: =S15-S24 -> 57792 | T25: =T15-T24 -> 77934 | U25: =U15-U24 -> 137600 | V25: =V15-V24 -> 330593 | W25: =V25/V$15 -> 0.3483953 | Z25: =Z15-Z24 -> 116100 | AA25: =AA15-AA24 -> 154000 | AB25: =AB15-AB24 -> 171600 | AC25: =AC15-AC24 -> 213400 | AD25: =AD15-AD24 -> 655100 | AF25: =AF15-AF24 -> 37898 | AG25: =AG15-AG24 -> 65364 | AH25: =AH15-AH24 -> 60821 | AI25: =AI15-AI24 -> 55243 | AJ25: =AJ15-AJ24 -> 20258 | AK25: =AK15-AK24 -> 20267 | AL25: =AL15-AL24 -> 16742 | AM25: =AM15-AM24 -> -5623 | ... AV25: =AV15-AV24 -> 330593 | AW25: =AV25/AV$15 -> 0.3483953 | AZ25: =AZ15-AZ24 -> 43000 | BA25: =BA15-BA24 -> 34400 | BB25: =BB15-BB24 -> 38700 | BC25: =BC15-BC24 -> 48400 | BD25: =BD15-BD24 -> 52800 | BE25: =BE15-BE24 -> 52800 | BF25: =BF15-BF24 -> 52800 | BG25: =BG15-BG24 -> 57200 | ... BL25: =BL15-BL24 -> 655100 | BM25: =BL25/BL$15 -> 0.43819398
K26: =K25/K15 -> 0.27091911 | L26: =L25/L15 -> 0.34932153 | M26: =M25/M15 -> 0.10915963 | N26: =N25/N15 -> 0.4210648 | R26: =R25/R15 -> 0.24582859 | S26: =S25/S15 -> 0.26472811 | T26: =T25/T15 -> 0.43871876 | U26: =U25/U15 -> 0.43 | Z26: =Z25/Z15 -> 0.43 | AA26: =AA25/AA15 -> 0.44 | AB26: =AB25/AB15 -> 0.44 | AC26: =AC25/AC15 -> 0.44 | AF26: =AF25/AF15 -> 0.10917115 | AG26: =AG25/AG15 -> 0.41923649 | AH26: =AH25/AH15 -> 0.4126703 | AI26: =AI25/AI15 -> 0.42802464 | AJ26: =AJ25/AJ15 -> 0.20811161 | AK26: =AK25/AK15 -> 0.29074972 | AL26: =AL25/AL15 -> 0.25402461 | AM26: =AM25/AM15 -> -0.095453928 | ... AU26: =AU25/AU15 -> 0.43 | AX26: hange to 43 | AZ26: =AZ25/AZ15 -> 0.43 | BA26: =BA25/BA15 -> 0.43 | BB26: =BB25/BB15 -> 0.43 | BC26: =BC25/BC15 -> 0.44 | BD26: =BD25/BD15 -> 0.44 | BE26: =BE25/BE15 -> 0.44 | BF26: =BF25/BF15 -> 0.44 | BG26: =BG25/BG15 -> 0.44 | ... BK26: =BK25/BK15 -> 0.44
A27: Selling, General & Administrative
B28: Compensation
B29: Salaries & wages | C29: =QB!F110 -> 0 | D29: =C29/C$15 -> 0 | E29: =QB!K110 -> 216764.24 | F29: =E29/E$15 -> 0.099925655 | G29: =QB!P110 -> 391277.16 | H29: =G29/G$15 -> 0.17770003 | I29: 410305 | J29: =I29/I$15 -> 0.1767459 | K29: 113695 | L29: 113361 | M29: 88012 | N29: 79844 | O29: =SUM(K29:N29) -> 394912 | P29: =O29/O$15 -> 0.22505712 | R29: =SUM(AJ29:AL29) -> 74406 | S29: =SUM(AM29:AO29) -> 40476 | T29: =SUM(AP29:AR29) -> 12500 | U29: =SUM(AS29:AU29) -> 36828 | V29: =SUM(R29:U29) -> 164210 | W29: =V29/V$15 -> 0.17305264 | Z29: =SUM(AZ29:BB29) -> 41828 | AA29: =SUM(BC29:BE29) -> 56424 | AB29: =SUM(BF29:BH29) -> 58722 | AC29: =SUM(BI29:BK29) -> 58722 | AD29: =SUM(Z29:AC29) -> 215696 | AF29: 88012 | AG29: 32685 | AH29: 24892 | AI29: 22267 | AJ29: 29409 | AK29: 22407 | AL29: 22590 | AM29: 17255 | AN29: 14039 | AO29: 9182 | AP29: 5000 | AQ29: 2500 | AR29: 5000 | AS29: =SUM(AS30:AS35) -> 12276 | AT29: =SUM(AT30:AT35) -> 12276 | AU29: =SUM(AU30:AU35) -> 12276 | AV29: =SUM(AJ29:AU29) -> 164210 | AW29: =AV29/AV$15 -> 0.17305264 | AZ29: =SUM(AZ30:AZ35) -> 12276 | BA29: =SUM(BA30:BA35) -> 12276 | BB29: =SUM(BB30:BB35) -> 17276 | BC29: =SUM(BC30:BC35) -> 17276 | BD29: =SUM(BD30:BD35) -> 19574 | BE29: =SUM(BE30:BE35) -> 19574 | BF29: =SUM(BF30:BF35) -> 19574 | BG29: =SUM(BG30:BG35) -> 19574 | ... BK29: =SUM(BK30:BK35) -> 19574 | BL29: =SUM(AZ29:BK29) -> 215696 | BM29: =BL29/BL$15 -> 0.14427826
B30: Spencer | Z30: =SUM(AZ30:BB30) -> 0 | AA30: =SUM(BC30:BE30) -> 0 | AB30: =SUM(BF30:BH30) -> 0 | AC30: =SUM(BI30:BK30) -> 0 | AH30: =$AX30*2 -> 4744 | AI30: =$AX30*2 -> 4744 | AJ30: =$AX30*2 -> 4744 | AK30: 1313 | AX30: 2372
B31: Ryan (Kristopher)/NEW REP | Z31: =SUM(AZ31:BB31) -> 5000 | AA31: =SUM(BC31:BE31) -> 15000 | AB31: =SUM(BF31:BH31) -> 15000 | AC31: =SUM(BI31:BK31) -> 15000 | AH31: =$AX31*2 -> 5000 | AI31: =$AX31*2 -> 5000 | AJ31: =$AX31*2 -> 5000 | AK31: =$AX31*2 -> 5000 | AX31: 2500 | BB31: 5000 | BC31: 5000 | BD31: 5000 | BE31: 5000 | BF31: 5000 | BG31: 5000 | BH31: 5000 | BI31: 5000 | BJ31: 5000 | BK31: 5000
B32: Levi | Z32: =SUM(AZ32:BB32) -> 11328 | AA32: =SUM(BC32:BE32) -> 12924 | AB32: =SUM(BF32:BH32) -> 13722 | AC32: =SUM(BI32:BK32) -> 13722 | AH32: =$AX32*2 -> 4574 | AI32: =$AX32*2 -> 4574 | AJ32: 4416 | AK32: 4468 | AL32: =$AX32*2 -> 4574 | AM32: =$AX32*2 -> 4574 | AN32: =$AX32*2 -> 4574 | AO32: =$AX32*2 -> 4574 | AP32: 3776 | AQ32: 3776 | AR32: 3776 | AS32: 3776 | AT32: 3776 | AU32: 3776 | AX32: 2287 | AZ32: 3776 | BA32: 3776 | BB32: 3776 | BC32: 3776 | BD32: 4574 | BE32: 4574 | BF32: 4574 | BG32: 4574 | BH32: 4574 | BI32: 4574 | BJ32: 4574 | BK32: 4574
B33: McKenna | Z33: =SUM(AZ33:BB33) -> 0 | AA33: =SUM(BC33:BE33) -> 0 | AB33: =SUM(BF33:BH33) -> 0 | AC33: =SUM(BI33:BK33) -> 0 | AH33: =$AX33*2 -> 1834 | AI33: =$AX33*2 -> 1834 | AJ33: 1834 | AK33: 1834 | AX33: 917
B34: Marisa | Z34: =SUM(AZ34:BB34) -> 15000 | AA34: =SUM(BC34:BE34) -> 15000 | AB34: =SUM(BF34:BH34) -> 15000 | AC34: =SUM(BI34:BK34) -> 15000 | AH34: =$AX34*2 -> 2490 | AI34: =$AX34*AI$144 -> 2490 | AJ34: 6666 | AK34: 6667 | AL34: 5000 | AM34: 5000 | AN34: 5000 | AO34: 5000 | AP34: 5000 | AQ34: 5000 | AR34: 5000 | AS34: 5000 | AT34: 5000 | AU34: 5000 | AX34: 1245 | AZ34: 5000 | BA34: 5000 | BB34: 5000 | BC34: 5000 | BD34: 5000 | BE34: 5000 | BF34: 5000 | BG34: 5000 | BH34: 5000 | BI34: 5000 | BJ34: 5000 | BK34: 5000
B35: Jeremiah | Z35: =SUM(AZ35:BB35) -> 10500 | AA35: =SUM(BC35:BE35) -> 13500 | AB35: =SUM(BF35:BH35) -> 15000 | AC35: =SUM(BI35:BK35) -> 15000 | AH35: =$AX35*2 -> 7000 | AI35: =$AX35*2 -> 7000 | AJ35: 3625 | AK35: 0 | AL35: 3000 | AM35: 3000 | AN35: 3000 | AO35: 3500 | AP35: 3500 | AQ35: 3500 | AR35: 3500 | AS35: 3500 | AT35: 3500 | AU35: 3500 | AX35: 3500 | AZ35: 3500 | BA35: 3500 | BB35: 3500 | BC35: 3500 | BD35: 5000 | BE35: 5000 | BF35: 5000 | BG35: 5000 | BH35: 5000 | BI35: 5000 | BJ35: 5000 | BK35: 5000
B36: Contract labor | C36: =QB!F108 -> 142452.45 | D36: =C36/C$15 -> 0.11121548 | E36: =QB!K108 -> 57528.86 | F36: =E36/E$15 -> 0.026520099 | G36: =QB!P108 -> 18232.21 | H36: =G36/G$15 -> 0.0082802283 | I36: 84566 | J36: =I36/I$15 -> 0.036428251 | K36: 30320 | L36: 9582 | M36: 9031 | N36: 16319 | O36: =SUM(K36:N36) -> 65252 | P36: =O36/O$15 -> 0.037186581 | R36: =SUM(AJ36:AL36) -> 18540 | S36: =SUM(AM36:AO36) -> 19428 | T36: =SUM(AP36:AR36) -> 20710 | U36: =SUM(AS36:AU36) -> 17160 | V36: =SUM(R36:U36) -> 75838 | W36: =V36/V$15 -> 0.079921847 | Z36: =SUM(AZ36:BB36) -> 18671 | AA36: =SUM(BC36:BE36) -> 19428 | AB36: =SUM(BF36:BH36) -> 19200 | AC36: =SUM(BI36:BK36) -> 19200 | AD36: =SUM(Z36:AC36) -> 76499 | AF36: 9030 | AG36: 4939 | AH36: 6242 | AI36: 5138 | AJ36: =SUM(AJ37:AJ40) -> 7721 | AK36: =SUM(AK37:AK40) -> 3588 | AL36: 7231 | AM36: 6049 | AN36: 6115 | AO36: 7264 | AP36: 8034 | AQ36: 6695 | AR36: 5981 | AS36: =SUM(AS37:AS40) -> 5720 | AT36: =SUM(AT37:AT40) -> 5720 | AU36: =SUM(AU37:AU40) -> 5720 | AV36: =SUM(AJ36:AU36) -> 75838 | AW36: =AV36/AV$15 -> 0.079921847 | AZ36: =SUM(AZ37:AZ40) -> 5720 | BA36: =SUM(BA37:BA40) -> 5720 | BB36: 7231 | BC36: 6049 | BD36: 6115 | BE36: 7264 | BF36: =SUM(BF37:BF40) -> 6400 | BG36: =SUM(BG37:BG40) -> 6400 | BH36: =SUM(BH37:BH40) -> 6400 | BI36: =SUM(BI37:BI40) -> 6400 | BJ36: =SUM(BJ37:BJ40) -> 6400 | BK36: =SUM(BK37:BK40) -> 6400 | BL36: =SUM(AZ36:BK36) -> 76499 | BM36: =BL36/BL$15 -> 0.0511699
B37: Miguel | Z37: =SUM(AZ37:BB37) -> 8580 | AA37: =SUM(BC37:BE37) -> 9260 | AB37: =SUM(BF37:BH37) -> 9600 | AC37: =SUM(BI37:BK37) -> 9600 | AH37: 2860 | AI37: 2860 | AJ37: 4767 | AK37: 1428 | AL37: 2860 | AM37: 2860 | AN37: 2860 | AO37: 2860 | AP37: 2860 | AQ37: 2860 | AR37: 2860 | AS37: 2860 | AT37: 2860 | AU37: 2860 | AX37: 1430 fulfillment | AZ37: 2860 | BA37: 2860 | BB37: 2860 | BC37: 2860 | BD37: 3200 | BE37: 3200 | BF37: 3200 | BG37: 3200 | BH37: 3200 | BI37: 3200 | BJ37: 3200 | BK37: 3200
B38: Robert | Z38: =SUM(AZ38:BB38) -> 8580 | AA38: =SUM(BC38:BE38) -> 9260 | AB38: =SUM(BF38:BH38) -> 9600 | AC38: =SUM(BI38:BK38) -> 9600 | AH38: 2860 | AI38: 2860 | AJ38: 2954 | AK38: 2160 | AL38: 2860 | AM38: 2860 | AN38: 2860 | AO38: 2860 | AP38: 2860 | AQ38: 2000 | AR38: 2000 | AS38: 2860 | AT38: 2860 | AU38: 2860 | AX38: 1430 sales admin | AZ38: 2860 | BA38: 2860 | BB38: 2860 | BC38: 2860 | BD38: 3200 | BE38: 3200 | BF38: 3200 | BG38: 3200 | BH38: 3200 | BI38: 3200 | BJ38: 3200 | BK38: 3200
Z39: =SUM(AZ39:BB39) -> 0 | AA39: =SUM(BC39:BE39) -> 0 | AB39: =SUM(BF39:BH39) -> 0 | AC39: =SUM(BI39:BK39) -> 0
Z40: =SUM(AZ40:BB40) -> 0 | AA40: =SUM(BC40:BE40) -> 0 | AB40: =SUM(BF40:BH40) -> 0 | AC40: =SUM(BI40:BK40) -> 0
B41: Payroll taxes | C41: =QB!F109 -> 0 | D41: =C41/C$15 -> 0 | E41: =QB!K109 -> 18516.46 | F41: =E41/E$15 -> 0.0085358608 | G41: =QB!P109 -> 32796.35 | H41: =G41/G$15 -> 0.014894589 | I41: 31028 | J41: =I41/I$15 -> 0.013365842 | K41: 7707 | L41: 6925 | M41: 5184 | N41: 4472 | O41: =SUM(K41:N41) -> 24288 | P41: =O41/O$15 -> 0.013841532 | R41: =SUM(AJ41:AL41) -> 4724 | S41: =SUM(AM41:AO41) -> 2011 | T41: =SUM(AP41:AR41) -> 684 | U41: =SUM(AS41:AU41) -> 2946.24 | V41: =SUM(R41:U41) -> 10365.24 | W41: =V41/V$15 -> 0.010923404 | Z41: =SUM(AZ41:BB41) -> 3346.24 | AA41: =SUM(BC41:BE41) -> 4513.92 | AB41: =SUM(BF41:BH41) -> 4697.76 | AC41: =SUM(BI41:BK41) -> 4697.76 | AD41: =SUM(Z41:AC41) -> 17255.68 | AF41: 5184 | AG41: 1439 | AH41: 1363 | AI41: 1670 | AJ41: 2184 | AK41: 1545 | AL41: 995 | AM41: 683 | AN41: 804 | AO41: 524 | AP41: 350 | AR41: 334 | AS41: =AS29*0.08 -> 982.08 | AT41: =AT29*0.08 -> 982.08 | AU41: =AU29*0.08 -> 982.08 | AV41: =SUM(AJ41:AU41) -> 10365.24 | AW41: =AV41/AV$15 -> 0.010923404 | AX41: 8% of payroll | AZ41: =AZ29*0.08 -> 982.08 | BA41: =BA29*0.08 -> 982.08 | BB41: =BB29*0.08 -> 1382.08 | BC41: =BC29*0.08 -> 1382.08 | BD41: =BD29*0.08 -> 1565.92 | BE41: =BE29*0.08 -> 1565.92 | BF41: =BF29*0.08 -> 1565.92 | BG41: =BG29*0.08 -> 1565.92 | ... BK41: =BK29*0.08 -> 1565.92 | BL41: =SUM(AZ41:BK41) -> 17255.68 | BM41: =BL41/BL$15 -> 0.011542261
B42: Employee benefits | C42: =QB!F104 -> 6974.56 | D42: =C42/C$15 -> 0.0054451788 | E42: =QB!K104 -> 10175.58 | F42: =E42/E$15 -> 0.0046908175 | G42: =QB!P104 -> 2511.54 | H42: =G42/G$15 -> 0.0011406256 | I42: 18506 | J42: =I42/I$15 -> 0.0079717761 | K42: 3190 | L42: 3417 | M42: 3692 | N42: 4817 | O42: =SUM(K42:N42) -> 15116 | P42: =O42/O$15 -> 0.0086144847 | R42: =SUM(AJ42:AL42) -> 690 | S42: =SUM(AM42:AO42) -> 5594 | T42: =SUM(AP42:AR42) -> 2856 | U42: =SUM(AS42:AU42) -> 3300 | V42: =SUM(R42:U42) -> 12440 | W42: =V42/V$15 -> 0.013109889 | Z42: =SUM(AZ42:BB42) -> 1050 | AA42: =SUM(BC42:BE42) -> 1050 | AB42: =SUM(BF42:BH42) -> 1050 | AC42: =SUM(BI42:BK42) -> 1050 | AD42: =SUM(Z42:AC42) -> 4200 | AF42: 3692 | AI42: 4817 | AJ42: 345 | AK42: 138 | AL42: 207 | AM42: 3311 | AN42: 138 | AO42: 2145 | AP42: 1756 | AR42: 1100 | AS42: 1100 | AT42: 1100 | AU42: 1100 | AV42: =SUM(AJ42:AU42) -> 12440 | AW42: =AV42/AV$15 -> 0.013109889 | AX42: Actual - Jer & Mar only | AZ42: 350 | BA42: 350 | BB42: 350 | BC42: 350 | BD42: 350 | BE42: 350 | BF42: 350 | BG42: 350 | BH42: 350 | BI42: 350 | BJ42: 350 | BK42: 350 | BL42: =SUM(AZ42:BK42) -> 4200 | BM42: =BL42/BL$15 -> 0.0028093645
B43: Total compensation | C43: =SUM(C29:C42) -> 149427.01 | D43: =C43/C$15 -> 0.11666066 | E43: =SUM(E29:E42) -> 302985.14 | F43: =E43/E$15 -> 0.13967243 | G43: =SUM(G29:G42) -> 444817.26 | H43: =G43/G$15 -> 0.20201547 | I43: =SUM(I29:I42) -> 544405 | J43: =I43/I$15 -> 0.23451177 | K43: =SUM(K29:K42) -> 154912 | L43: =SUM(L29:L42) -> 133285 | M43: =SUM(M29:M42) -> 105919 | N43: =SUM(N29:N42) -> 105452 | O43: =SUM(O29:O42) -> 499568 | P43: =O43/O$15 -> 0.28469972 | R43: =SUM(R29:R42) -> 98360 | S43: =SUM(S29:S42) -> 67509 | T43: =SUM(T29:T42) -> 36750 | U43: =SUM(U29:U42) -> 60234.24 | V43: =SUM(V29:V42) -> 262853.24 | W43: =V43/V$15 -> 0.27700778 | Z43: =Z29+Z36+Z41+Z42 -> 64895.24 | AA43: =AA29+AA36+AA41+AA42 -> 81415.92 | AB43: =AB29+AB36+AB41+AB42 -> 83669.76 | AC43: =AC29+AC36+AC41+AC42 -> 83669.76 | AD43: =AD29+AD36+AD41+AD42 -> 313650.68 | AF43: =SUM(AF29:AF42) -> 105918 | AG43: =SUM(AG29:AG42) -> 39063 | AH43: =AH29+AH36+AH41+AH42 -> 32497 | AI43: =AI29+AI36+AI41+AI42 -> 33892 | AJ43: =AJ29+AJ36+AJ41+AJ42 -> 39659 | AK43: =AK29+AK36+AK41+AK42 -> 27678 | AL43: =AL29+AL36+AL41+AL42 -> 31023 | AM43: =AM29+AM36+AM41+AM42 -> 27298 | AN43: =AN29+AN36+AN41+AN42 -> 21096 | AO43: =AO29+AO36+AO41+AO42 -> 19115 | ... AU43: =AU29+AU36+AU41+AU42 -> 20078.08 | AV43: =SUM(AV29:AV42) -> 262853.24 | AW43: =AV43/AV$15 -> 0.27700778 | AZ43: =AZ29+AZ36+AZ41+AZ42 -> 19328.08 | BA43: =BA29+BA36+BA41+BA42 -> 19328.08 | BB43: =BB29+BB36+BB41+BB42 -> 26239.08 | BC43: =BC29+BC36+BC41+BC42 -> 25057.08 | BD43: =BD29+BD36+BD41+BD42 -> 27604.92 | BE43: =BE29+BE36+BE41+BE42 -> 28753.92 | BF43: =BF29+BF36+BF41+BF42 -> 27889.92 | BG43: =BG29+BG36+BG41+BG42 -> 27889.92 | ... BK43: =BK29+BK36+BK41+BK42 -> 27889.92 | BL43: =SUM(BL29:BL42) -> 313650.68 | BM43: =BL43/BL$15 -> 0.20979979
B44: Marketing & advertising | C44: =QB!F80 -> 120088.93 | D44: =C44/C$15 -> 0.093755835 | E44: =QB!K80 -> 126166.54 | F44: =E44/E$15 -> 0.058161227 | G44: =QB!P80 -> 153428.37 | H44: =G44/G$15 -> 0.069680085 | I44: 182458 | J44: =I44/I$15 -> 0.078596905 | K44: 47826 | L44: 43028 | M44: 32671 | N44: 13368 | O44: =SUM(K44:N44) -> 136893 | P44: =O44/O$15 -> 0.078014201 | R44: =SUM(AJ44:AL44) -> 15741 | S44: =SUM(AM44:AO44) -> 13643 | T44: =SUM(AP44:AR44) -> 9525 | U44: =SUM(AS44:AU44) -> 6000 | V44: =SUM(R44:U44) -> 44909 | W44: =V44/V$15 -> 0.047327332 | Z44: =SUM(AZ44:BB44) -> 6000 | AA44: =SUM(BC44:BE44) -> 6000 | AB44: =SUM(BF44:BH44) -> 6000 | AC44: =SUM(BI44:BK44) -> 6000 | AD44: =SUM(Z44:AC44) -> 24000 | AF44: 35371 | AG44: -277 | AH44: =SUM(AH45:AH51) -> 37351 | AI44: =SUM(AI45:AI51) -> 11703 | AJ44: =SUM(AJ45:AJ51) -> 4931 | AK44: =SUM(AK45:AK51) -> 8652 | AL44: 2158 | AM44: =SUM(AM45:AM51) -> 3074 | AN44: 7656 | AO44: 2913 | AP44: 2482 | AQ44: 1815 | AR44: 5228 | AS44: =SUM(AS45:AS51) -> 2000 | AT44: =SUM(AT45:AT51) -> 2000 | AU44: =SUM(AU45:AU51) -> 2000 | AV44: =SUM(AJ44:AU44) -> 44909 | AW44: =AV44/AV$15 -> 0.047327332 | AX44: Per Jer | AZ44: 2000 | BA44: 2000 | BB44: 2000 | BC44: 2000 | BD44: 2000 | BE44: 2000 | BF44: 2000 | BG44: =SUM(BG45:BG51) -> 2000 | BH44: =SUM(BH45:BH51) -> 2000 | BI44: =SUM(BI45:BI51) -> 2000 | BJ44: =SUM(BJ45:BJ51) -> 2000 | BK44: =SUM(BK45:BK51) -> 2000 | BL44: =SUM(AZ44:BK44) -> 24000 | BM44: =BL44/BL$15 -> 0.016053512
B45: Events & shows | Z45: =SUM(AZ45:BB45) -> 4011 | AA45: =SUM(BC45:BE45) -> 75 | AB45: =SUM(BF45:BH45) -> 3000 | AC45: =SUM(BI45:BK45) -> 0 | AH45: 5091 | AJ45: 15 | AK45: 3991 | AL45: 5 | AM45: 75 | AP45: 3000 | AZ45: 15 | BA45: 3991 | BB45: 5 | BC45: 75 | BF45: 3000
B46: Travel | Z46: =SUM(AZ46:BB46) -> 4428 | AA46: =SUM(BC46:BE46) -> 362 | AB46: =SUM(BF46:BH46) -> 0 | AC46: =SUM(BI46:BK46) -> 0 | AJ46: 3487 | AK46: 209 | AL46: 732 | AM46: 362 | AZ46: 3487 | BA46: 209 | BB46: 732 | BC46: 362
B47: Social Media | Z47: =SUM(AZ47:BB47) -> 741 | AA47: =SUM(BC47:BE47) -> 600 | AB47: =SUM(BF47:BH47) -> 900 | AC47: =SUM(BI47:BK47) -> 900 | AJ47: 741 | AN47: 300 | AO47: 300 | AP47: 300 | AQ47: 300 | AR47: 300 | AS47: 300 | AT47: 300 | AU47: 300 | AZ47: 741 | BD47: 300 | BE47: 300 | BF47: 300 | BG47: 300 | BH47: 300 | BI47: 300 | BJ47: 300 | BK47: 300
B48: In store | Z48: =SUM(AZ48:BB48) -> 328 | AA48: =SUM(BC48:BE48) -> 741 | AB48: =SUM(BF48:BH48) -> 900 | AC48: =SUM(BI48:BK48) -> 900 | AJ48: 192 | AK48: 30 | AL48: 106 | AM48: 141 | AN48: 300 | AO48: 300 | AP48: 300 | AQ48: 300 | AR48: 300 | AS48: 300 | AT48: 300 | AU48: 300 | AZ48: 192 | BA48: 30 | BB48: 106 | BC48: 141 | BD48: 300 | BE48: 300 | BF48: 300 | BG48: 300 | BH48: 300 | BI48: 300 | BJ48: 300 | BK48: 300
B49: Website | Z49: =SUM(AZ49:BB49) -> 0 | AA49: =SUM(BC49:BE49) -> 0 | AB49: =SUM(BF49:BH49) -> 0 | AC49: =SUM(BI49:BK49) -> 0
A50: a | B50: Slotting fees | M50: 2700 | N50: 35410 | O50: =SUM(K50:N50) -> 38110 | P50: =O50/O$15 -> 0.021718577 | T50: =SUM(AP50:AR50) -> 0 | U50: =SUM(AS50:AU50) -> 0 | V50: =SUM(R50:U50) -> 0 | W50: =V50/V$15 -> 0 | Z50: =SUM(AZ50:BB50) -> 0 | AA50: =SUM(BC50:BE50) -> 0 | AB50: =SUM(BF50:BH50) -> 0 | AC50: =SUM(BI50:BK50) -> 0 | AD50: =SUM(Z50:AC50) -> 0 | AH50: 30280 | AI50: 5130
B51: Other | Z51: =SUM(AZ51:BB51) -> 6232 | AA51: =SUM(BC51:BE51) -> 5296 | AB51: =SUM(BF51:BH51) -> 4200 | AC51: =SUM(BI51:BK51) -> 4200 | AH51: 1980 | AI51: 6573 | AJ51: 496 | AK51: 4422 | AL51: 1314 | AM51: 2496 | AN51: 1400 | AO51: 1400 | AP51: 1400 | AQ51: 1400 | AR51: 1400 | AS51: 1400 | AT51: 1400 | AU51: 1400 | AZ51: 496 | BA51: 4422 | BB51: 1314 | BC51: 2496 | BD51: 1400 | BE51: 1400 | BF51: 1400 | BG51: 1400 | BH51: 1400 | BI51: 1400 | BJ51: 1400 | BK51: 1400
B52: Rent | C52: =QB!F85 -> 38000.7 | D52: =C52/C$15 -> 0.029667908 | E52: =QB!K85 -> 32084.48 | F52: =E52/E$15 -> 0.014790552 | G52: =QB!P85 -> 84207.42 | H52: =G52/G$15 -> 0.038243124 | I52: 109406 | J52: =I52/I$15 -> 0.047128506 | K52: 37316 | L52: 28264 | M52: 28321 | N52: 28907 | O52: =SUM(K52:N52) -> 122808 | P52: =O52/O$15 -> 0.069987274 | R52: =SUM(AJ52:AL52) -> 9705 | S52: =SUM(AM52:AO52) -> 13399 | T52: =SUM(AP52:AR52) -> 7634 | U52: =SUM(AS52:AU52) -> 7644 | V52: =SUM(R52:U52) -> 38382 | W52: =V52/V$15 -> 0.040448856 | Z52: =SUM(AZ52:BB52) -> 6990 | AA52: =SUM(BC52:BE52) -> 6990 | AB52: =SUM(BF52:BH52) -> 6990 | AC52: =SUM(BI52:BK52) -> 6990 | AD52: =SUM(Z52:AC52) -> 27960 | AF52: 29360 | AG52: 9440 | AH52: 9372 | AI52: 10026 | AJ52: =9560-4500 -> 5060 | AK52: 9559 | AL52: -4914 | AM52: 4653 | AN52: 6034 | AO52: 2712 | AP52: 2548 | AQ52: 2538 | AR52: 2548 | AS52: 2548 | AT52: 2548 | AU52: 2548 | AV52: =SUM(AJ52:AU52) -> 38382 | AW52: =AV52/AV$15 -> 0.040448856 | AX52: In June start $1425 + (pallets x $15)/mo | AZ52: 2330 | BA52: 2330 | BB52: 2330 | BC52: 2330 | BD52: 2330 | BE52: 2330 | BF52: 2330 | BG52: 2330 | BH52: 2330 | BI52: 2330 | BJ52: 2330 | BK52: 2330 | BL52: =SUM(AZ52:BK52) -> 27960 | BM52: =BL52/BL$15 -> 0.018702341
B53: Office/food expenses | C53: 20867 | D53: =C53/C$15 -> 0.016291285 | E53: =QB!K89 -> 28881.79 | F53: =E53/E$15 -> 0.013314151 | G53: =QB!P89 -> 62978.55 | H53: =G53/G$15 -> 0.028601951 | I53: 65098 | J53: =I53/I$15 -> 0.028042077 | K53: 11546 | L53: 6569 | M53: 1645 | N53: 3394 | O53: =SUM(K53:N53) -> 23154 | P53: =O53/O$15 -> 0.013195275 | R53: =SUM(AJ53:AL53) -> 3695 | S53: =SUM(AM53:AO53) -> 3293 | T53: =SUM(AP53:AR53) -> 4374 | U53: =SUM(AS53:AU53) -> 3600 | V53: =SUM(R53:U53) -> 14962 | W53: =V53/V$15 -> 0.015767698 | Z53: =SUM(AZ53:BB53) -> 3600 | AA53: =SUM(BC53:BE53) -> 3600 | AB53: =SUM(BF53:BH53) -> 3600 | AC53: =SUM(BI53:BK53) -> 3600 | AD53: =SUM(Z53:AC53) -> 14400 | AF53: 1644 | AG53: 1798 | AH53: 1032 | AI53: 564 | AJ53: 251 | AK53: 1029 | AL53: 2415 | AM53: 1007 | AN53: 1318 | AO53: 968 | AP53: 1746 | AQ53: 217 | AR53: 2411 | AS53: 1200 | AT53: 1200 | AU53: 1200 | AV53: =SUM(AJ53:AU53) -> 14962 | AW53: =AV53/AV$15 -> 0.015767698 | AX53: Per discussion 11/20 | AZ53: 1200 | BA53: 1200 | BB53: 1200 | BC53: 1200 | BD53: 1200 | BE53: 1200 | BF53: 1200 | BG53: =BF53 -> 1200 | BH53: =BG53 -> 1200 | BI53: =BH53 -> 1200 | BJ53: =BI53 -> 1200 | BK53: =BJ53 -> 1200 | BL53: =SUM(AZ53:BK53) -> 14400 | BM53: =BL53/BL$15 -> 0.009632107
B54: Travel | C54: 10236 | D54: =C54/C$15 -> 0.0079914504 | E54: =QB!K113 -> 6913.83 | F54: =E54/E$15 -> 0.0031871908 | G54: =QB!P113 -> 9268.26 | H54: =G54/G$15 -> 0.0042092159 | I54: 23884 | J54: =I54/I$15 -> 0.010288442 | K54: 10230 | L54: 17117 | M54: 9398 | N54: 2277 | O54: =SUM(K54:N54) -> 39022 | P54: =O54/O$15 -> 0.022238318 | R54: =SUM(AJ54:AL54) -> 18 | S54: =SUM(AM54:AO54) -> 95 | T54: =SUM(AP54:AR54) -> 591 | U54: =SUM(AS54:AU54) -> 1500 | V54: =SUM(R54:U54) -> 2204 | W54: =V54/V$15 -> 0.0023226845 | Z54: =SUM(AZ54:BB54) -> 1500 | AA54: =SUM(BC54:BE54) -> 1500 | AB54: =SUM(BF54:BH54) -> 1500 | AC54: =SUM(BI54:BK54) -> 1500 | AD54: =SUM(Z54:AC54) -> 6000 | AF54: 9398 | AG54: 1514 | AH54: 571 | AI54: 192 | AL54: 18 | AO54: 95 | AP54: 13 | AQ54: 78 | AR54: 500 | AS54: 500 | AT54: 500 | AU54: 500 | AV54: =SUM(AJ54:AU54) -> 2204 | AW54: =AV54/AV$15 -> 0.0023226845 | AX54: Per Jer | AZ54: 500 | BA54: 500 | BB54: 500 | BC54: 500 | BD54: 500 | BE54: 500 | BF54: 500 | BG54: 500 | BH54: 500 | BI54: 500 | BJ54: 500 | BK54: 500 | BL54: =SUM(AZ54:BK54) -> 6000 | BM54: =BL54/BL$15 -> 0.0040133779
B55: Dues & subscriptions | C55: =QB!F100 -> 9066.62 | D55: =C55/C$15 -> 0.007078492 | E55: =QB!K100 -> 9832.89 | F55: =E55/E$15 -> 0.0045328416 | G55: =QB!P100 -> 13230.97 | H55: =G55/G$15 -> 0.0060088959 | I55: 20486 | J55: =I55/I$15 -> 0.008824695 | K55: 12949 | L55: 10819 | M55: 17922 | N55: 10655 | O55: =SUM(K55:N55) -> 52345 | P55: =O55/O$15 -> 0.029830987 | R55: =SUM(AJ55:AL55) -> 7703 | S55: =SUM(AM55:AO55) -> 5633 | T55: =SUM(AP55:AR55) -> 8129 | U55: =SUM(AS55:AU55) -> 6600 | V55: =SUM(R55:U55) -> 28065 | W55: =V55/V$15 -> 0.029576289 | Z55: =SUM(AZ55:BB55) -> 6600 | AA55: =SUM(BC55:BE55) -> 6600 | AB55: =SUM(BF55:BH55) -> 6600 | AC55: =SUM(BI55:BK55) -> 6600 | AD55: =SUM(Z55:AC55) -> 26400 | AF55: 17922 | AG55: 3465 | AH55: 5065 | AI55: 2125 | AJ55: 2088 | AK55: 1427 | AL55: 4188 | AM55: 649 | AN55: 2517 | AO55: 2467 | AP55: 3594 | AQ55: 2964 | AR55: 1571 | AS55: 2200 | AT55: 2200 | AU55: 2200 | AV55: =SUM(AJ55:AU55) -> 28065 | AW55: =AV55/AV$15 -> 0.029576289 | AX55: Per analysis, software subscriptions | AZ55: 2200 | BA55: 2200 | BB55: 2200 | BC55: 2200 | BD55: 2200 | BE55: 2200 | BF55: 2200 | BG55: 2200 | BH55: 2200 | BI55: 2200 | BJ55: 2200 | BK55: 2200 | BL55: =SUM(AZ55:BK55) -> 26400 | BM55: =BL55/BL$15 -> 0.017658863
B56: Insurance | C56: =QB!F101+QB!F102+QB!F103 -> 7786.98 | D56: =C56/C$15 -> 0.0060794514 | E56: =QB!K101+QB!K102+QB!K103 -> 9618.2 | F56: =E56/E$15 -> 0.0044338722 | G56: =QB!P101+QB!P102+QB!P103 -> 19428.15 | H56: =G56/G$15 -> 0.0088233691 | I56: 16312 | J56: =I56/I$15 -> 0.0070266731 | K56: 8122 | L56: 4876 | M56: 3609 | N56: 2133 | O56: =SUM(K56:N56) -> 18740 | P56: =O56/O$15 -> 0.010679773 | R56: =SUM(AJ56:AL56) -> 6382 | S56: =SUM(AM56:AO56) -> 825 | T56: =SUM(AP56:AR56) -> 879 | U56: =SUM(AS56:AU56) -> 3000 | V56: =SUM(R56:U56) -> 11086 | W56: =V56/V$15 -> 0.011682977 | Z56: =SUM(AZ56:BB56) -> 2508 | AA56: =SUM(BC56:BE56) -> 2508 | AB56: =SUM(BF56:BH56) -> 2508 | AC56: =SUM(BI56:BK56) -> 2508 | AD56: =SUM(Z56:AC56) -> 10032 | AF56: 3610 | AG56: 1394 | AH56: 364 | AI56: 375 | AJ56: 3015 | AK56: =201+94+1809 -> 2104 | AL56: 1263 | AM56: 1316 | AN56: 1236 | AO56: -1727 | AP56: 297 | AQ56: 297 | AR56: 285 | AS56: 1000 | AT56: 1000 | AU56: 1000 | AV56: =SUM(AJ56:AU56) -> 11086 | AW56: =AV56/AV$15 -> 0.011682977 | AX56: Beam(dental), SF(auto), SF(liab/WC) | AZ56: 836 | BA56: 836 | BB56: 836 | BC56: 836 | BD56: 836 | BE56: 836 | BF56: 836 | BG56: 836 | BH56: 836 | BI56: 836 | BJ56: 836 | BK56: 836 | BL56: =SUM(AZ56:BK56) -> 10032 | BM56: =BL56/BL$15 -> 0.0067103679
B57: Utilities | C57: =QB!F90 -> 3827.54 | D57: =C57/C$15 -> 0.0029882372 | E57: =QB!K90 -> 4766.11 | F57: =E57/E$15 -> 0.0021971182 | G57: =QB!P90 -> 12331.72 | H57: =G57/G$15 -> 0.0056004981 | I57: 13550 | J57: =I57/I$15 -> 0.0058368943 | K57: 6236 | L57: 5636 | M57: 5354 | N57: 5161 | O57: =SUM(K57:N57) -> 22387 | P57: =O57/O$15 -> 0.012758168 | AG57: 3400
B58: - Phone | O58: =SUM(K58:N58) -> 0 | R58: =SUM(AJ58:AL58) -> 2356 | S58: =SUM(AM58:AO58) -> 2611 | T58: =SUM(AP58:AR58) -> 1089 | U58: =SUM(AS58:AU58) -> 714 | V58: =SUM(R58:U58) -> 6770 | W58: =V58/V$15 -> 0.0071345618 | Z58: =SUM(AZ58:BB58) -> 714 | AA58: =SUM(BC58:BE58) -> 714 | AB58: =SUM(BF58:BH58) -> 714 | AC58: =SUM(BI58:BK58) -> 714 | AD58: =SUM(Z58:AC58) -> 2856 | AF58: 2189 | AI58: 650 | AJ58: 792 | AK58: 782 | AL58: 782 | AM58: 610 | AN58: 610 | AO58: 1391 | AP58: 580 | AQ58: 238 | AR58: 271 | AS58: 238 | AT58: 238 | AU58: 238 | AV58: =SUM(AJ58:AU58) -> 6770 | AW58: =AV58/AV$15 -> 0.0071345618 | AX58: Verizon(phone), AT&T (internet) | AZ58: 238 | BA58: 238 | BB58: 238 | BC58: 238 | BD58: 238 | BE58: 238 | BF58: 238 | BG58: 238 | BH58: 238 | BI58: 238 | BJ58: 238 | BK58: 238 | BL58: =SUM(AZ58:BK58) -> 2856 | BM58: =BL58/BL$15 -> 0.0019103679
B59: - Electric | O59: =SUM(K59:N59) -> 0 | R59: =SUM(AJ59:AL59) -> 3231 | S59: =SUM(AM59:AO59) -> 1347 | T59: =SUM(AP59:AR59) -> 0 | U59: =SUM(AS59:AU59) -> 0 | V59: =SUM(R59:U59) -> 4578 | W59: =V59/V$15 -> 0.0048245235 | Z59: =SUM(AZ59:BB59) -> 0 | AA59: =SUM(BC59:BE59) -> 0 | AB59: =SUM(BF59:BH59) -> 0 | AC59: =SUM(BI59:BK59) -> 0 | AD59: =SUM(Z59:AC59) -> 0 | AF59: 3165 | AH59: 252 | AI59: 858 | AJ59: 1298 | AK59: 0 | AL59: 1933 | AM59: 683 | AO59: 664 | AV59: =SUM(AJ59:AU59) -> 4578 | AW59: =AV59/AV$15 -> 0.0048245235 | AX59: Trend | BL59: =SUM(AZ59:BK59) -> 0 | BM59: =BL59/BL$15 -> 0
B60: Professional fees | C60: =QB!F106 -> 8793.32 | D60: =C60/C$15 -> 0.0068651212 | E60: =QB!K106 -> 14641.91 | F60: =E60/E$15 -> 0.0067497408 | G60: =QB!P106 -> 25989.68 | H60: =G60/G$15 -> 0.011803313 | I60: 19267 | J60: =I60/I$15 -> 0.0082995899 | K60: 12052 | L60: 9564 | M60: 9537 | N60: 12881 | O60: =SUM(K60:N60) -> 44034 | P60: =O60/O$15 -> 0.025094616 | R60: =SUM(AJ60:AL60) -> 7487 | S60: =SUM(AM60:AO60) -> 17322 | T60: =SUM(AP60:AR60) -> 12441 | U60: =SUM(AS60:AU60) -> 12402 | V60: =SUM(R60:U60) -> 49652 | W60: =V60/V$15 -> 0.052325741 | Z60: =SUM(AZ60:BB60) -> 12402 | AA60: =SUM(BC60:BE60) -> 12402 | AB60: =SUM(BF60:BH60) -> 12402 | AC60: =SUM(BI60:BK60) -> 12402 | AD60: =SUM(Z60:AC60) -> 49608 | AF60: 9537 | AG60: 2194 | AH60: 1594 | AI60: 9094 | AJ60: 5893 | AK60: 0 | AL60: 1594 | AM60: 9094 | AN60: 4094 | AO60: 4134 | AP60: =AO60 -> 4134 | AQ60: 4173 | AR60: 4134 | AS60: 4134 | AT60: 4134 | AU60: 4134 | AV60: =SUM(AJ60:AU60) -> 49652 | AW60: =AV60/AV$15 -> 0.052325741 | AX60: $1594/mo bookies, $2500/mo Mark | AZ60: 4134 | BA60: 4134 | BB60: 4134 | BC60: 4134 | BD60: 4134 | BE60: 4134 | BF60: 4134 | BG60: 4134 | BH60: =BG60 -> 4134 | BI60: =BH60 -> 4134 | BJ60: =BI60 -> 4134 | BK60: =BJ60 -> 4134 | BL60: =SUM(AZ60:BK60) -> 49608 | BM60: =BL60/BL$15 -> 0.033182609
B61: Repairs & maintenance | C61: =QB!F115 -> 5276.76 | D61: =C61/C$15 -> 0.0041196723 | E61: =QB!K115 -> 3200.57 | F61: =E61/E$15 -> 0.0014754235 | G61: =QB!P115 -> 8234.48 | H61: =G61/G$15 -> 0.0037397208 | I61: 11020 | J61: =I61/I$15 -> 0.0047470536 | K61: 1010 | L61: 2214 | M61: 1118 | N61: 738 | O61: =SUM(K61:N61) -> 5080 | P61: =O61/O$15 -> 0.0028950504 | R61: =SUM(AJ61:AL61) -> 361 | S61: =SUM(AM61:AO61) -> 777 | T61: =SUM(AP61:AR61) -> 268 | U61: =SUM(AS61:AU61) -> 600 | V61: =SUM(R61:U61) -> 2006 | W61: =V61/V$15 -> 0.0021140223 | Z61: =SUM(AZ61:BB61) -> 600 | AA61: =SUM(BC61:BE61) -> 600 | AB61: =SUM(BF61:BH61) -> 600 | AC61: =SUM(BI61:BK61) -> 600 | AD61: =SUM(Z61:AC61) -> 2400 | AF61: 1118 | AG61: 534 | AI61: 204 | AJ61: 0 | AK61: 0 | AL61: 361 | AM61: 259 | AN61: 354 | AO61: 164 | AP61: 0 | AQ61: 0 | AR61: 268 | AS61: 200 | AT61: 200 | AU61: 200 | AV61: =SUM(AJ61:AU61) -> 2006 | AW61: =AV61/AV$15 -> 0.0021140223 | AX61: Average | AZ61: 200 | BA61: 200 | BB61: 200 | BC61: 200 | BD61: 200 | BE61: 200 | BF61: 200 | BG61: 200 | BH61: 200 | BI61: 200 | BJ61: 200 | BK61: 200 | BL61: =SUM(AZ61:BK61) -> 2400 | BM61: =BL61/BL$15 -> 0.0016053512
B62: Taxes & licenses | C62: =QB!F107 -> 2966.05 | D62: =C62/C$15 -> 0.0023156547 | E62: =QB!K107 -> 3042.38 | F62: =E62/E$15 -> 0.0014024998 | G62: =QB!P107 -> 22007.56 | H62: =G62/G$15 -> 0.0099948181 | I62: 9262 | J62: =I62/I$15 -> 0.003989765 | K62: 849 | L62: 7574 | M62: 150 | N62: 0 | O62: =SUM(K62:N62) -> 8573 | P62: =O62/O$15 -> 0.0048856826 | R62: =SUM(AJ62:AL62) -> 0 | S62: =SUM(AM62:AO62) -> 0 | T62: =SUM(AP62:AR62) -> 1 | U62: =SUM(AS62:AU62) -> 0 | V62: =SUM(R62:U62) -> 1 | W62: =V62/V$15 -> 1.0538496e-06 | Z62: =SUM(AZ62:BB62) -> 0 | AA62: =SUM(BC62:BE62) -> 0 | AB62: =SUM(BF62:BH62) -> 0 | AC62: =SUM(BI62:BK62) -> 0 | AD62: =SUM(Z62:AC62) -> 0 | AF62: 150 | AH62: 0 | AI62: 0 | AJ62: 0 | AK62: 0 | AL62: 0 | AM62: 0 | AN62: 0 | AO62: 0 | AP62: 0 | AQ62: 1 | AR62: 0 | AS62: 0 | AT62: 0 | AU62: 0 | AV62: =SUM(AJ62:AU62) -> 1 | AW62: =AV62/AV$15 -> 1.0538496e-06 | AX62: Franchise tax in April | AZ62: 0 | BA62: 0 | BB62: 0 | BC62: 0 | BD62: 0 | BE62: 0 | BF62: 0 | BG62: 0 | BH62: 0 | BI62: 0 | BJ62: 0 | BK62: 0 | BL62: =SUM(AZ62:BK62) -> 0 | BM62: =BL62/BL$15 -> 0
B63: Reimbursements | C63: =QB!F114 -> 0 | D63: =C63/C$15 -> 0 | E63: =QB!K114 -> 0 | F63: =E63/E$15 -> 0 | G63: =QB!P114 -> 32.44 | H63: =G63/G$15 -> 1.4732751e-05 | I63: 3653 | J63: =I63/I$15 -> 0.0015735923 | K63: 1267 | L63: 917 | M63: 794 | N63: 1092 | O63: =SUM(K63:N63) -> 4070 | P63: =O63/O$15 -> 0.0023194597 | R63: =SUM(AJ63:AL63) -> 423 | S63: =SUM(AM63:AO63) -> 55 | T63: =SUM(AP63:AR63) -> 100 | U63: =SUM(AS63:AU63) -> 300 | V63: =SUM(R63:U63) -> 878 | W63: =V63/V$15 -> 0.00092527996 | Z63: =SUM(AZ63:BB63) -> 300 | AA63: =SUM(BC63:BE63) -> 300 | AB63: =SUM(BF63:BH63) -> 300 | AC63: =SUM(BI63:BK63) -> 300 | AD63: =SUM(Z63:AC63) -> 1200 | AF63: 794 | AG63: 650 | AI63: 442 | AJ63: 79 | AK63: 240 | AL63: 104 | AN63: 55 | AP63: 0 | AQ63: 0 | AR63: 100 | AS63: 100 | AT63: 100 | AU63: 100 | AV63: =SUM(AJ63:AU63) -> 878 | AW63: =AV63/AV$15 -> 0.00092527996 | AX63: Average | AZ63: 100 | BA63: 100 | BB63: 100 | BC63: 100 | BD63: 100 | BE63: 100 | BF63: 100 | BG63: 100 | BH63: 100 | BI63: 100 | BJ63: 100 | BK63: 100 | BL63: =SUM(AZ63:BK63) -> 1200 | BM63: =BL63/BL$15 -> 0.00080267559
B64: Bank/Faire/CC charges
B65: - Bank/cc | C65: 4055 | D65: =C65/C$15 -> 0.0031658198 | E65: 1905 | F65: =E65/E$15 -> 0.00087818162 | G65: 4660 | H65: =G65/G$15 -> 0.0021163569 | I65: 11808 | J65: =I65/I$15 -> 0.005086498 | K65: 5812 | L65: 6586 | M65: 3830 | N65: 1598 | O65: =SUM(K65:N65) -> 17826 | R65: =SUM(AJ65:AL65) -> 4247 | S65: =SUM(AM65:AO65) -> 7163 | T65: =SUM(AP65:AR65) -> 5572 | U65: =SUM(AS65:AU65) -> 2200 | V65: =SUM(R65:U65) -> 19182 | W65: =V65/V$15 -> 0.020214943 | Z65: =SUM(AZ65:BB65) -> 300 | AA65: =SUM(BC65:BE65) -> 300 | AB65: =SUM(BF65:BH65) -> 300 | AC65: =SUM(BI65:BK65) -> 300 | AD65: =SUM(Z65:AC65) -> 1200 | AF65: 3831 | AG65: 252 | AH65: 533 | AI65: 813 | AJ65: 1441 | AK65: 640 | AL65: 2166 | AM65: 3759 | AN65: 2176 | AO65: 1228 | AP65: 1444 | AQ65: 2945 | AR65: 1183 | AS65: 1000 | AT65: 1000 | AU65: 200 | AV65: =SUM(AJ65:AU65) -> 19182 | AZ65: 100 | BA65: 100 | BB65: 100 | BC65: 100 | BD65: 100 | BE65: 100 | BF65: 100 | BG65: 100 | BH65: 100 | BI65: 100 | BJ65: 100 | BK65: 100 | BL65: =SUM(AZ65:BK65) -> 1200
B66: - Faire | O66: =SUM(K66:N66) -> 0 | R66: =SUM(AJ66:AL66) -> 616 | S66: =SUM(AM66:AO66) -> 446 | T66: =SUM(AP66:AR66) -> 713 | U66: =SUM(AS66:AU66) -> 525 | V66: =SUM(R66:U66) -> 2300 | W66: =V66/V$15 -> 0.0024238541 | Z66: =SUM(AZ66:BB66) -> 525 | AA66: =SUM(BC66:BE66) -> 525 | AB66: =SUM(BF66:BH66) -> 525 | AC66: =SUM(BI66:BK66) -> 525 | AD66: =SUM(Z66:AC66) -> 2100 | AJ66: 366 | AK66: 102 | AL66: 148 | AM66: 76 | AN66: 172 | AO66: 198 | AP66: 354 | AQ66: 183 | AR66: 176 | AS66: 175 | AT66: 175 | AU66: 175 | AV66: =SUM(AJ66:AU66) -> 2300 | AZ66: 175 | BA66: 175 | BB66: 175 | BC66: 175 | BD66: 175 | BE66: 175 | BF66: 175 | BG66: 175 | BH66: 175 | BI66: 175 | BJ66: 175 | BK66: 175 | BL66: =SUM(AZ66:BK66) -> 2100
B67: - Interest | C67: 6092 | D67: =C67/C$15 -> 0.0047561465 | E67: 577 | F67: =E67/E$15 -> 0.00026598992 | G67: 3496 | H67: =G67/G$15 -> 0.0015877219 | I67: 21775 | J67: =I67/I$15 -> 0.0093799538 | K67: 16981 | L67: 23222 | M67: 15052 | N67: 9081 | O67: =SUM(K67:N67) -> 64336 | R67: =SUM(AJ67:AL67) -> 10080 | S67: =SUM(AM67:AO67) -> 8271 | T67: =SUM(AP67:AR67) -> 6287 | U67: =SUM(AS67:AU67) -> 4500 | V67: =SUM(R67:U67) -> 29138 | W67: =V67/V$15 -> 0.03070707 | Z67: =SUM(AZ67:BB67) -> 3000 | AA67: =SUM(BC67:BE67) -> 1500 | AB67: =SUM(BF67:BH67) -> 1500 | AC67: =SUM(BI67:BK67) -> 1500 | AD67: =SUM(Z67:AC67) -> 7500 | AG67: 5025 | AH67: 6435 | AI67: -2378 | AJ67: 3799 | AK67: 3609 | AL67: 2672 | AM67: 5113 | AN67: 2317 | AO67: 841 | AP67: 1310 | AQ67: 3505 | AR67: 1472 | AS67: 1500 | AT67: 1500 | AU67: 1500 | AV67: =SUM(AJ67:AU67) -> 29138 | AX67: Approx $1200/mo CC/misc, see below | AZ67: 1000 | BA67: 1000 | BB67: 1000 | BC67: 500 | BD67: 500 | BE67: 500 | BF67: 500 | BG67: 500 | BH67: 500 | BI67: 500 | BJ67: 500 | BK67: 500 | BL67: =SUM(AZ67:BK67) -> 7500
B68: Bad debts | C68: =QB!F112 -> 652.42 | D68: =C68/C$15 -> 0.00050935737 | E68: =QB!K112 -> 6737.83 | F68: =E68/E$15 -> 0.0031060569 | G68: =QB!P112 -> 0 | H68: =G68/G$15 -> 0 | I68: 12743 | J68: =I68/I$15 -> 0.0054892653 | K68: -144 | L68: 0 | M68: 477 | N68: 0 | O68: =SUM(K68:N68) -> 333 | P68: =O68/O$15 -> 0.00018977398 | R68: =SUM(AJ68:AL68) -> 1949 | S68: =SUM(AM68:AO68) -> 0 | T68: =SUM(AP68:AR68) -> 0 | U68: =SUM(AS68:AU68) -> 0 | V68: =SUM(R68:U68) -> 1949 | W68: =V68/V$15 -> 0.0020539529 | Z68: =SUM(AZ68:BB68) -> 0 | AA68: =SUM(BC68:BE68) -> 0 | AB68: =SUM(BF68:BH68) -> 0 | AC68: =SUM(BI68:BK68) -> 0 | AD68: =SUM(Z68:AC68) -> 0 | AF68: 477 | AH68: 0 | AI68: 0 | AJ68: 0 | AK68: 0 | AL68: 1949 | AM68: 0 | AN68: 0 | AO68: 0 | AP68: 0 | AQ68: 0 | AR68: 0 | AS68: 0 | AT68: 0 | AU68: 0 | AV68: =SUM(AJ68:AU68) -> 1949 | AW68: =AV68/AV$15 -> 0.0020539529 | AZ68: 0 | BA68: 0 | BB68: 0 | BC68: 0 | BD68: 0 | BE68: 0 | BF68: 0 | BG68: 0 | BH68: 0 | BI68: 0 | BJ68: 0 | BK68: 0 | BL68: =SUM(AZ68:BK68) -> 0 | BM68: =BL68/BL$15 -> 0
B69: Miscellaneous | C69: -8262 | D69: =C69/C$15 -> -0.006450309 | E69: =QB!K132+QB!K116+QB!K117+QB!K118+QB!K119+QB!K120+QB!K121 -> 4773.89 | F69: =E69/E$15 -> 0.0022007047 | G69: 1625 | H69: =G69/G$15 -> 0.000738 | I69: 1085 | J69: =I69/I$15 -> 0.00046738231 | K69: 87 | L69: -101 | M69: 1156 | N69: -335 | O69: =SUM(K69:N69) -> 807 | P69: =O69/O$15 -> 0.0004599027 | R69: =SUM(AJ69:AL69) -> 171 | S69: =SUM(AM69:AO69) -> -23898 | T69: =SUM(AP69:AR69) -> 7058 | U69: =SUM(AS69:AU69) -> 750 | V69: =SUM(R69:U69) -> -15919 | W69: =V69/V$15 -> -0.016776232 | Z69: =SUM(AZ69:BB69) -> 750 | AA69: =SUM(BC69:BE69) -> 750 | AB69: =SUM(BF69:BH69) -> 750 | AC69: =SUM(BI69:BK69) -> 750 | AD69: =SUM(Z69:AC69) -> 3000 | AF69: -16379 | AG69: 21 | AH69: =-319+83 -> -236 | AI69: 31 | AJ69: 7 | AK69: 5 | AL69: 159 | AM69: -15 | AN69: -693 | AO69: -23190 | AP69: -2096 | AQ69: 4289 | AR69: 4865 | AS69: 250 | AT69: 250 | AU69: 250 | AV69: =SUM(AJ69:AU69) -> -15919 | AW69: =AV69/AV$15 -> -0.016776232 | AX69: Cushion | AZ69: 250 | BA69: 250 | BB69: 250 | BC69: 250 | BD69: 250 | BE69: 250 | BF69: 250 | BG69: 250 | BH69: 250 | BI69: 250 | BJ69: 250 | BK69: 250 | BL69: =SUM(AZ69:BK69) -> 3000 | BM69: =BL69/BL$15 -> 0.002006689
B70: Total SG&A | C70: =SUM(C43:C69) -> 378874.33 | D70: =C70/C$15 -> 0.29579478 | E70: =SUM(E43:E69) -> 556127.56 | F70: =E70/E$15 -> 0.25636798 | G70: =SUM(G43:G69) -> 865735.86 | H70: =G70/G$15 -> 0.39317727 | I70: =SUM(I43:I69) -> 1066212 | J70: =I70/I$15 -> 0.45928906 | K70: =SUM(K43:K69) -> 327051 | L70: =SUM(L43:L69) -> 299570 | M70: =SUM(M43:M69) -> 239653 | N70: =SUM(N43:N69) -> 231812 | O70: =SUM(O43:O69) -> 1098086 | P70: =O70/O$15 -> 0.62579023 | R70: =SUM(R43:R69) -> 172525 | S70: =SUM(S43:S69) -> 118491 | T70: =SUM(T43:T69) -> 101411 | U70: =SUM(U43:U69) -> 110569.24 | V70: =SUM(V43:V69) -> 502996.24 | W70: =V70/V$15 -> 0.53008239 | Z70: =SUM(Z52:Z69)+Z44+Z43 -> 110684.24 | AA70: =SUM(AA52:AA69)+AA44+AA43 -> 125704.92 | AB70: =SUM(AB52:AB69)+AB44+AB43 -> 127958.76 | AC70: =SUM(AC52:AC69)+AC44+AC43 -> 127958.76 | AD70: =SUM(AD52:AD69)+AD44+AD43 -> 492306.68 | AF70: =SUM(AF43:AF69) -> 208105 | AG70: =SUM(AG43:AG69) -> 68473 | AH70: =SUM(AH43:AH69)-AH45-AH47-AH48-AH49-AH50-AH51 -> 94830 | AI70: =SUM(AI43:AI69)-AI45-AI47-AI48-AI49-AI50-AI51 -> 68591 | AJ70: =SUM(AJ43:AJ69)-AJ45-AJ46-AJ47-AJ48-AJ49-AJ50-AJ51 -> 68679 | AK70: =SUM(AK52:AK69)+AK44+AK43 -> 55827 | AL70: =SUM(AL52:AL69)+AL44+AL43 -> 48019 | AM70: =SUM(AM52:AM69)+AM44+AM43 -> 57576 | AN70: =SUM(AN52:AN69)+AN44+AN43 -> 48942 | AO70: =SUM(AO52:AO69)+AO44+AO43 -> 11973 | AP70: =SUM(AP52:AP69)+AP44+AP43 -> 31546 | AQ70: =SUM(AQ52:AQ69)+AQ44+AQ43 -> 32438 | AR70: =SUM(AR52:AR69)+AR44+AR43 -> 37427 | ... AV70: =SUM(AV52:AV69)+AV44+AV43 -> 502996.24 | AW70: =AV70/AV$15 -> 0.53008239 | AZ70: =SUM(AZ43:AZ69)-AZ45-AZ46-AZ47-AZ48-AZ49-AZ50-AZ51 -> 34591.08 | BA70: =SUM(BA52:BA69)+BA44+BA43 -> 34591.08 | BB70: =SUM(BB52:BB69)+BB44+BB43 -> 41502.08 | BC70: =SUM(BC52:BC69)+BC44+BC43 -> 39820.08 | BD70: =SUM(BD52:BD69)+BD44+BD43 -> 42367.92 | BE70: =SUM(BE52:BE69)+BE44+BE43 -> 43516.92 | BF70: =SUM(BF52:BF69)+BF44+BF43 -> 42652.92 | BG70: =SUM(BG52:BG69)+BG44+BG43 -> 42652.92 | BH70: =SUM(BH52:BH69)+BH44+BH43 -> 42652.92 | ... BL70: =SUM(BL52:BL69)+BL44+BL43 -> 492306.68 | BM70: =BL70/BL$15 -> 0.32930213
A71: Cash from Operations | C71: =C25-C70 -> 135070.69 | D71: =C71/C$15 -> 0.10545239 | E71: =E25-E70 -> 399091.56 | F71: =E71/E$15 -> 0.18397631 | G71: =G25-G70 -> -131891.56 | H71: =G71/G$15 -> -0.059899059 | I71: =I25-I70 -> -56343 | J71: =I71/I$15 -> -0.024270711 | K71: =K25-K70 -> -172616 | L71: =L25-L70 -> -158034 | M71: =M25-M70 -> -201759 | N71: =N25-N70 -> -49760 | O71: =O25-O70 -> -582169 | P71: =O71/O$15 -> -0.33177335 | R71: =R25-R70 -> -115258 | S71: =S25-S70 -> -60699 | T71: =T25-T70 -> -23477 | U71: =U25-U70 -> 27030.76 | V71: =V25-V70 -> -172403.24 | W71: =V71/V$15 -> -0.18168709 | Z71: =Z25-Z70 -> 5415.76 | AA71: =AA25-AA70 -> 28295.08 | AB71: =AB25-AB70 -> 43641.24 | AC71: =AC25-AC70 -> 85441.24 | AD71: =AD25-AD70 -> 162793.32 | AF71: =AF25-AF70 -> -170207 | AG71: =AG25-AG70 -> -3109 | AH71: =AH25-AH70 -> -34009 | AI71: =AI25-AI70 -> -13348 | AJ71: =AJ25-AJ70 -> -48421 | AK71: =AK25-AK70 -> -35560 | AL71: =AL25-AL70 -> -31277 | AM71: =AM25-AM70 -> -63199 | ... AV71: =AV25-AV70 -> -172403.24 | AW71: =AV71/AV$15 -> -0.18168709 | AZ71: =AZ25-AZ70 -> 8408.92 | BA71: =BA25-BA70 -> -191.08 | BB71: =BB25-BB70 -> -2802.08 | BC71: =BC25-BC70 -> 8579.92 | BD71: =BD25-BD70 -> 10432.08 | BE71: =BE25-BE70 -> 9283.08 | BF71: =BF25-BF70 -> 10147.08 | BG71: =BG25-BG70 -> 14547.08 | ... BL71: =BL25-BL70 -> 162793.32 | BM71: =BL71/BL$15 -> 0.10889185
A72: Debt Service
B73: CC payments, net of charges | N73: 18747 | R73: =SUM(AJ73:AL73) -> 28470 | S73: =SUM(AM73:AO73) -> 24256 | T73: =SUM(AP73:AR73) -> 4866 | U73: =SUM(AS73:AU73) -> 19995 | V73: =SUM(R73:U73) -> 77587 | Z73: =SUM(AZ73:BB73) -> 10665 | AA73: =SUM(BC73:BE73) -> 6000 | AB73: =SUM(BF73:BH73) -> 6000 | AC73: =SUM(BI73:BK73) -> 6000 | AD73: =SUM(Z73:AC73) -> 28665 | AG73: =AF128-AG128 -> 15451 | AH73: =AG128-AH128 -> 1827.3 | AI73: =AH128-AI128 -> 1468.7 | AJ73: =AI128-AJ128 -> 27408 | AK73: =AJ128-AK128 -> -1419 | AL73: =AK128-AL128 -> 2481 | AM73: =AL128-AM128 -> 1009 | AN73: =AM128-AN128 -> -168 | ... AQ73: =AP128-AQ128 -> -5551 | AR73: 6665 | AS73: 6665 | AT73: 6665 | AU73: 6665 | AV73: =SUM(AJ73:AU73) -> 77587 | AZ73: 6665 | BA73: 2000 | BB73: 2000 | BC73: 2000 | BD73: 2000 | BE73: 2000 | BF73: 2000 | BG73: 2000 | BH73: 2000 | BI73: 2000 | BJ73: 2000 | BK73: 2000 | BL73: =SUM(AZ73:BK73) -> 28665
B74: Anthony Tallerine | R74: =SUM(AJ74:AL74) -> 0 | S74: =SUM(AM74:AO74) -> 0 | T74: =SUM(AP74:AR74) -> 0 | U74: =SUM(AS74:AU74) -> 0 | V74: =SUM(R74:U74) -> 0 | Z74: =SUM(AZ74:BB74) -> 0 | AA74: =SUM(BC74:BE74) -> 0 | AB74: =SUM(BF74:BH74) -> 0 | AC74: =SUM(BI74:BK74) -> 0 | AD74: =SUM(Z74:AC74) -> 0 | AV74: =SUM(AJ74:AU74) -> 0 | BL74: =SUM(AZ74:BK74) -> 0
B75: Bluevine | N75: 69541 | R75: =SUM(AJ75:AL75) -> 29552 | S75: =SUM(AM75:AO75) -> 9448 | T75: =SUM(AP75:AR75) -> 0 | U75: =SUM(AS75:AU75) -> 0 | V75: =SUM(R75:U75) -> 39000 | Z75: =SUM(AZ75:BB75) -> 0 | AA75: =SUM(BC75:BE75) -> 0 | AB75: =SUM(BF75:BH75) -> 0 | AC75: =SUM(BI75:BK75) -> 0 | AD75: =SUM(Z75:AC75) -> 0 | AG75: 28007 | AH75: 23286 | AI75: 18248 | AJ75: 15342 | AK75: 10668 | AL75: 3542 | AM75: =1181*4 -> 4724 | AN75: =1181*4 -> 4724 | AV75: =SUM(AJ75:AU75) -> 39000 | BL75: =SUM(AZ75:BK75) -> 0
B76: Jeremiah reimbursements | N76: 25252 | R76: =SUM(AJ76:AL76) -> 11131 | S76: =SUM(AM76:AO76) -> -22942 | T76: =SUM(AP76:AR76) -> 3616 | U76: =SUM(AS76:AU76) -> 0 | V76: =SUM(R76:U76) -> -8195 | Z76: =SUM(AZ76:BB76) -> 0 | AA76: =SUM(BC76:BE76) -> 0 | AB76: =SUM(BF76:BH76) -> 0 | AC76: =SUM(BI76:BK76) -> 0 | AD76: =SUM(Z76:AC76) -> 0 | AG76: 2834 | AI76: 22418 | AJ76: 14150 | AK76: =AJ130-AK130 -> -261 | AL76: =AK130-AL130 -> -2758 | AM76: =AL130-AM130 -> -19492 | AN76: =AM130-AN130 -> -8100 | AO76: =AN130-AO130 -> 4650 | AP76: =AO130-AP130 -> 2376 | AQ76: =AP130-AQ130 -> 1240 | AV76: =SUM(AJ76:AU76) -> -8195 | BL76: =SUM(AZ76:BK76) -> 0
B77: Forward Financing | R77: =SUM(AJ77:AL77) -> 1512 | S77: =SUM(AM77:AO77) -> 23436 | T77: =SUM(AP77:AR77) -> 22193 | U77: =SUM(AS77:AU77) -> 13238 | V77: =SUM(R77:U77) -> 60379 | Z77: =SUM(AZ77:BB77) -> 0 | AA77: =SUM(BC77:BE77) -> 0 | AB77: =SUM(BF77:BH77) -> 0 | AC77: =SUM(BI77:BK77) -> 0 | AD77: =SUM(Z77:AC77) -> 0 | AK77: =AJ131-AK131 -> 0 | AL77: 1512 | AM77: 8316 | AN77: 7938 | AO77: 7182 | AP77: 5939 | AQ77: 8316 | AR77: 7938 | AS77: 7938 | AT77: 5300 | AV77: =SUM(AJ77:AU77) -> 60379 | BL77: =SUM(AZ77:BK77) -> 0
B78: Everest | T78: =SUM(AP78:AR78) -> 15323 | U78: =SUM(AS78:AU78) -> 9912 | V78: =SUM(R78:U78) -> 25235 | Z78: =SUM(AZ78:BB78) -> 0 | AA78: =SUM(BC78:BE78) -> 0 | AB78: =SUM(BF78:BH78) -> 0 | AC78: =SUM(BI78:BK78) -> 0 | AD78: =SUM(Z78:AC78) -> 0 | AP78: 4712 | AQ78: 5655 | AR78: 4956 | AS78: 4956 | AT78: 4956 | AV78: =SUM(AJ78:AU78) -> 25235
B79: Fundbox | N79: 6921 | R79: =SUM(AJ79:AL79) -> 13228 | S79: =SUM(AM79:AO79) -> 7605 | T79: =SUM(AP79:AR79) -> 0 | U79: =SUM(AS79:AU79) -> 0 | V79: =SUM(R79:U79) -> 20833 | Z79: =SUM(AZ79:BB79) -> 0 | AA79: =SUM(BC79:BE79) -> 0 | AB79: =SUM(BF79:BH79) -> 0 | AC79: =SUM(BI79:BK79) -> 0 | AD79: =SUM(Z79:AC79) -> 0 | AH79: 2273 | AI79: 4648 | AJ79: 5689 | AK79: 5783 | AL79: 1756 | AM79: =585*4 -> 2340 | AN79: 2925 | AO79: =585*4 -> 2340 | AV79: =SUM(AJ79:AU79) -> 20833 | BL79: =SUM(AZ79:BK79) -> 0
B80: Funding Circle | N80: 8924 | R80: =SUM(AJ80:AL80) -> 9262 | S80: =SUM(AM80:AO80) -> 10261 | T80: =SUM(AP80:AR80) -> 10424 | U80: =SUM(AS80:AU80) -> 11439 | V80: =SUM(R80:U80) -> 41386 | Z80: =SUM(AZ80:BB80) -> 11439 | AA80: =SUM(BC80:BE80) -> 11439 | AB80: =SUM(BF80:BH80) -> 0 | AC80: =SUM(BI80:BK80) -> 0 | AD80: =SUM(Z80:AC80) -> 22878 | AG80: 2938 | AH80: 2974 | AI80: 3012 | AJ80: 3049 | AK80: 6213 | AL80: 0 | AM80: 3813 | AN80: 3204 | AO80: 3244 | AP80: 3285 | AQ80: 3326 | AR80: 3813 | AS80: 3813 | AT80: 3813 | AU80: 3813 | AV80: =SUM(AJ80:AU80) -> 41386 | AZ80: 3813 | BA80: 3813 | BB80: 3813 | BC80: 3813 | BD80: 3813 | BE80: 3813 | BL80: =SUM(AZ80:BK80) -> 22878
B81: Parafin | N81: 11388 | R81: =SUM(AJ81:AL81) -> 8608 | S81: =SUM(AM81:AO81) -> 4806 | T81: =SUM(AP81:AR81) -> 2822 | U81: =SUM(AS81:AU81) -> 1000 | V81: =SUM(R81:U81) -> 17236 | Z81: =SUM(AZ81:BB81) -> 0 | AA81: =SUM(BC81:BE81) -> 0 | AB81: =SUM(BF81:BH81) -> 0 | AC81: =SUM(BI81:BK81) -> 0 | AD81: =SUM(Z81:AC81) -> 0 | AG81: 5486 | AH81: 3617 | AI81: 2285 | AJ81: 3580 | AK81: 1973 | AL81: 3055 | AM81: 3000 | AN81: 896 | AO81: 910 | AP81: 968 | AQ81: 854 | AR81: 1000 | AS81: 1000 | AV81: =SUM(AJ81:AU81) -> 17236 | BL81: =SUM(AZ81:BK81) -> 0
B82: QB | N82: 11585 | R82: =SUM(AJ82:AL82) -> 1680 | S82: =SUM(AM82:AO82) -> 3830 | T82: =SUM(AP82:AR82) -> 3225 | U82: =SUM(AS82:AU82) -> 1075 | V82: =SUM(R82:U82) -> 9810 | Z82: =SUM(AZ82:BB82) -> 0 | AA82: =SUM(BC82:BE82) -> 0 | AB82: =SUM(BF82:BH82) -> 0 | AC82: =SUM(BI82:BK82) -> 0 | AD82: =SUM(Z82:AC82) -> 0 | AG82: 3853 | AH82: 3888 | AI82: 3844 | AK82: 1680 | AL82: 0 | AM82: 1680 | AN82: 1075 | AO82: 1075 | AP82: 1075 | AQ82: 1075 | AR82: 1075 | AS82: 1075 | AV82: =SUM(AJ82:AU82) -> 9810 | BL82: =SUM(AZ82:BK82) -> 0
B83: Shopify | N83: 5624 | R83: =SUM(AJ83:AL83) -> 1704 | S83: =SUM(AM83:AO83) -> 1357 | T83: =SUM(AP83:AR83) -> 2484 | U83: =SUM(AS83:AU83) -> 1500 | V83: =SUM(R83:U83) -> 7045 | Z83: =SUM(AZ83:BB83) -> 0 | AA83: =SUM(BC83:BE83) -> 0 | AB83: =SUM(BF83:BH83) -> 0 | AC83: =SUM(BI83:BK83) -> 0 | AD83: =SUM(Z83:AC83) -> 0 | AG83: 954 | AH83: 2558 | AI83: 2112 | AJ83: 639 | AK83: 611 | AL83: 454 | AM83: 400 | AN83: 554 | AO83: 403 | AP83: 924 | AQ83: 1060 | AR83: 500 | AS83: 500 | AT83: 500 | AU83: 500 | AV83: =SUM(AJ83:AU83) -> 7045 | BL83: =SUM(AZ83:BK83) -> 0
B84: Amazon | N84: 17603 | R84: =SUM(AJ84:AL84) -> 17142 | S84: =SUM(AM84:AO84) -> 17388 | T84: =SUM(AP84:AR84) -> 9229 | U84: =SUM(AS84:AU84) -> 0 | V84: =SUM(R84:U84) -> 43759 | Z84: =SUM(AZ84:BB84) -> 0 | AA84: =SUM(BC84:BE84) -> 0 | AB84: =SUM(BF84:BH84) -> 0 | AC84: =SUM(BI84:BK84) -> 0 | AD84: =SUM(Z84:AC84) -> 0 | AG84: 5984 | AH84: 3433 | AI84: 8186 | AJ84: 3164 | AK84: 6111 | AL84: 7867 | AM84: 5635 | AN84: 4866 | AO84: 6887 | AP84: 6058 | AQ84: 3171 | AV84: =SUM(AJ84:AU84) -> 43759 | BL84: =SUM(AZ84:BK84) -> 0
B85: Hugh/Christy | R85: =SUM(AJ85:AL85) -> 0 | S85: =SUM(AM85:AO85) -> 0 | T85: =SUM(AP85:AR85) -> 0 | U85: =SUM(AS85:AU85) -> 0 | V85: =SUM(R85:U85) -> 0 | Z85: =SUM(AZ85:BB85) -> 0 | AA85: =SUM(BC85:BE85) -> 4707 | AB85: =SUM(BF85:BH85) -> 14121 | AC85: =SUM(BI85:BK85) -> 14121 | AD85: =SUM(Z85:AC85) -> 32949 | AV85: =SUM(AJ85:AU85) -> 0 | BE85: 4707 | BF85: 4707 | BG85: 4707 | BH85: 4707 | BI85: 4707 | BJ85: 4707 | BK85: 4707 | BL85: =SUM(AZ85:BK85) -> 32949
B86: Interest | C86: =QB!F99 -> 10146.97 | D86: =C86/C$15 -> 0.0079219429 | E86: =QB!K99 -> 2481.65 | F86: =E86/E$15 -> 0.0011440102 | G86: =QB!P99 -> 8155.74 | H86: =G86/G$15 -> 0.0037039607 | I86: =SUM(#REF!) -> #REF! | J86: =I86/I$15 -> #REF! | K86: =I86*0.9/4 -> #REF! | L86: =K86 -> #REF! | M86: =L86 -> #REF! | R86: =SUM(AJ86:AL86) -> -5480 | S86: =SUM(AM86:AO86) -> -4030 | T86: =SUM(AP86:AR86) -> -2687 | U86: =SUM(AS86:AU86) -> -900 | V86: =SUM(R86:U86) -> -13097 | Z86: =SUM(AZ86:BB86) -> -600 | AA86: =SUM(BC86:BE86) -> -300 | AB86: =SUM(BF86:BH86) -> -300 | AC86: =SUM(BI86:BK86) -> -300 | AD86: =SUM(Z86:AC86) -> -1500 | AF86: 15052 | AJ86: =1200-AJ67 -> -2599 | AK86: =1200-AK67 -> -2409 | AL86: -472 | AM86: =1200-AM67 -> -3913 | AN86: -117 | AO86: 0 | AP86: =1200-AP67 -> -110 | AQ86: =1200-AQ67 -> -2305 | AR86: =1200-AR67 -> -272 | AS86: =1200-AS67 -> -300 | AT86: =1200-AT67 -> -300 | AU86: =1200-AU67 -> -300 | AV86: =SUM(AJ86:AU86) -> -13097 | AX86: Included above | AZ86: -200 | BA86: -200 | BB86: -200 | BC86: -100 | BD86: -100 | BE86: -100 | BF86: -100 | BG86: -100 | BH86: -100 | BI86: -100 | BJ86: -100 | BK86: -100 | BL86: =SUM(AZ86:BK86) -> -1500
B87: Total debt service | N87: =SUM(N73:N86) -> 175585 | R87: =SUM(R73:R86) -> 116809 | S87: =SUM(S73:S86) -> 75415 | T87: =SUM(T73:T86) -> 71495 | U87: =SUM(U73:U86) -> 57259 | V87: =SUM(V73:V86) -> 320978 | Z87: =SUM(Z73:Z86) -> 21504 | AA87: =SUM(AA73:AA86) -> 21846 | AB87: =SUM(AB73:AB86) -> 19821 | AC87: =SUM(AC73:AC86) -> 19821 | AD87: =SUM(AD73:AD86) -> 82992 | AF87: =SUM(AF73:AF86) -> 15052 | AG87: =SUM(AG73:AG86) -> 65507 | AH87: =SUM(AH73:AH86) -> 43856.3 | AI87: =SUM(AI73:AI86) -> 66221.7 | AJ87: =SUM(AJ73:AJ86) -> 70422 | AK87: =SUM(AK73:AK86) -> 28950 | AL87: =SUM(AL73:AL86) -> 17437 | AM87: =SUM(AM73:AM86) -> 7512 | ... AV87: =SUM(AV73:AV86) -> 320978 | AZ87: =SUM(AZ73:AZ86) -> 10278 | BA87: =SUM(BA73:BA86) -> 5613 | BB87: =SUM(BB73:BB86) -> 5613 | BC87: =SUM(BC73:BC86) -> 5713 | BD87: =SUM(BD73:BD86) -> 5713 | BE87: =SUM(BE73:BE86) -> 10420 | BF87: =SUM(BF73:BF86) -> 6607 | BG87: =SUM(BG73:BG86) -> 6607 | ... BL87: =SUM(BL73:BL86) -> 82992
A88: Cash Flow after Debt Service | N88: =N71-N87 -> -225345 | R88: =R71-R87 -> -232067 | S88: =S71-S87 -> -136114 | T88: =T71-T87 -> -94972 | U88: =U71-U87 -> -30228.24 | V88: =V71-V87 -> -493381.24 | Z88: =Z71-Z87 -> -16088.24 | AA88: =AA71-AA87 -> 6449.08 | AB88: =AB71-AB87 -> 23820.24 | AC88: =AC71-AC87 -> 65620.24 | AD88: =AD71-AD87 -> 79801.32 | AG88: =AG71-AG87 -> -68616 | AH88: =AH71-AH87 -> -77865.3 | AI88: =AI71-AI87 -> -79569.7 | AJ88: =AJ71-AJ87 -> -118843 | AK88: =AK71-AK87 -> -64510 | AL88: =AL71-AL87 -> -48714 | AM88: =AM71-AM87 -> -70711 | AN88: =AN71-AN87 -> -45335 | ... AV88: =AV71-AV87 -> -493381.24 | AZ88: =AZ71-AZ87 -> -1869.08 | BA88: =BA71-BA87 -> -5804.08 | BB88: =BB71-BB87 -> -8415.08 | BC88: =BC71-BC87 -> 2866.92 | BD88: =BD71-BD87 -> 4719.08 | BE88: =BE71-BE87 -> -1136.92 | BF88: =BF71-BF87 -> 3540.08 | BG88: =BG71-BG87 -> 7940.08 | ... BL88: =BL71-BL87 -> 79801.32
A89: Working Capital Fluctuation | N89: 83009 | R89: =SUM(AJ89:AL89) -> 41293 | S89: =SUM(AM89:AO89) -> 118664 | T89: =SUM(AP89:AR89) -> 76410 | U89: =SUM(AS89:AU89) -> -29000 | V89: =SUM(R89:U89) -> 207367 | Z89: =SUM(AZ89:BB89) -> -10000 | AA89: =SUM(BC89:BE89) -> -5000 | AB89: =SUM(BF89:BH89) -> -15000 | AC89: =SUM(BI89:BK89) -> -15000 | AD89: =SUM(Z89:AC89) -> -45000 | AG89: 12964 | AH89: 22340 | AI89: 48625 | AJ89: -51185 | AK89: 65201 | AL89: 27277 | AM89: 52504 | AN89: 47114 | AO89: 19046 | AP89: 18430 | AQ89: 34980 | AR89: 23000 | AS89: 11000 | AT89: -20000 | AU89: -20000 | AV89: =SUM(AJ89:AU89) -> 207367 | AZ89: -10000 | BE89: -5000 | BF89: -5000 | BG89: -5000 | BH89: -5000 | BI89: -5000 | BJ89: -5000 | BK89: -5000 | BL89: =SUM(AZ89:BK89) -> -45000
A90: Investment/Borrowing | N90: 296440 | R90: =SUM(AJ90:AL90) -> 40950 | S90: =SUM(AM90:AO90) -> 0 | T90: =SUM(AP90:AR90) -> 20010 | U90: =SUM(AS90:AU90) -> 135000 | V90: =SUM(R90:U90) -> 195960 | Z90: =SUM(AZ90:BB90) -> 0 | AA90: =SUM(BC90:BE90) -> 0 | AB90: =SUM(AX90:AZ90) -> 0 | AC90: =SUM(BA90:BC90) -> 0 | AD90: =SUM(Z90:AC90) -> 0 | AG90: 48000 | AH90: =14000+25000 -> 39000 | AI90: 209440 | AL90: 40950 | AP90: 15010 | AQ90: 5000 | AT90: 135000 | AV90: =SUM(AJ90:AU90) -> 195960 | BL90: =SUM(AZ90:BK90) -> 0
A91: Net Cash Flow | C91: =C71-#REF!-C86-C90 -> #REF! | D91: =C91/C$15 -> #REF! | E91: =E71-#REF!-E86-E90 -> #REF! | F91: =E91/E$15 -> #REF! | G91: =G71-#REF!-G86-G90 -> #REF! | H91: =G91/G$15 -> #REF! | I91: =I71-#REF!-I86-I90 -> #REF! | J91: =I91/I$15 -> #REF! | K91: =K71-#REF!-K86-K90 -> #REF! | L91: =L71-#REF!-L86-L90 -> #REF! | M91: =M71-#REF!-M86-M90 -> #REF! | N91: =SUM(N88:N90) -> 154104 | R91: =SUM(R88:R90) -> -149824 | S91: =SUM(S88:S90) -> -17450 | T91: =SUM(T88:T90) -> 1448 | U91: =SUM(U88:U90) -> 75771.76 | V91: =SUM(V88:V90) -> -90054.24 | Z91: =SUM(Z88:Z90) -> -26088.24 | AA91: =SUM(AA88:AA90) -> 1449.08 | AB91: =SUM(AB88:AB90) -> 8820.24 | AC91: =SUM(AC88:AC90) -> 50620.24 | AD91: =SUM(AD88:AD90) -> 34801.32 | AF91: =AF71-AF87-AF90 -> -185259 | AG91: =SUM(AG88:AG90) -> -7652 | AH91: =SUM(AH88:AH90) -> -16525.3 | AI91: =SUM(AI88:AI90) -> 178495.3 | AJ91: =SUM(AJ88:AJ90) -> -170028 | AK91: =SUM(AK88:AK90) -> 691 | AL91: =SUM(AL88:AL90) -> 19513 | AM91: =SUM(AM88:AM90) -> -18207 | AN91: =SUM(AN88:AN90) -> 1779 | ... AV91: =SUM(AV88:AV90) -> -90054.24 | AZ91: =SUM(AZ88:AZ90) -> -11869.08 | BA91: =SUM(BA88:BA90) -> -5804.08 | BB91: =SUM(BB88:BB90) -> -8415.08 | BC91: =SUM(BC88:BC90) -> 2866.92 | BD91: =SUM(BD88:BD90) -> 4719.08 | BE91: =SUM(BE88:BE90) -> -6136.92 | BF91: =SUM(BF88:BF90) -> -1459.92 | BG91: =SUM(BG88:BG90) -> 2940.08 | ... BL91: =SUM(BL88:BL90) -> 34801.32
A92: Cash, Beginning of Month | N92: 12057 | R92: =AJ92 -> 166376 | S92: =R119 -> 16552 | T92: =S119 -> -898 | U92: =T119 -> 550 | V92: =R92 -> 166376 | Z92: =U119 -> 76321.76 | AA92: =Z119 -> 50233.52 | AB92: =AA119 -> 51682.6 | AC92: =AB119 -> 60502.84 | AD92: =Z92 -> 76321.76 | AG92: 12057 | AH92: 4406 | AI92: =AH119 -> -12119.3 | AJ92: 166376 | AK92: =AJ119 -> -3652 | AL92: =AK119 -> -2961 | AM92: =AL119 -> 16552 | AN92: =AM119 -> -1655 | AO92: =AN119 -> 124 | AP92: =AO119 -> -898 | AQ92: =AP119 -> 1156 | AR92: =AQ119 -> 6800 | ... AU92: =AT119 -> 100322.84 | AV92: =AJ92 -> 166376 | AZ92: =AU119 -> 76321.76 | BA92: =AZ119 -> 64452.68 | BB92: =BA119 -> 58648.6 | BC92: =BB119 -> 50233.52 | BD92: =BC119 -> 53100.44 | BE92: =BD119 -> 57819.52 | BF92: =BE119 -> 51682.6 | BG92: =BF119 -> 50222.68 | BH92: =BG119 -> 53162.76 | ... BK92: =BJ119 -> 110383 | BL92: =AZ92 -> 76321.76
A93: ASSUMPTIONS
B94: Growth
B95: Retail
B96: Online
B97: Distributor
B98: Franchise
B99: Marg/spices
B100: Cost of co-packer/ingredients
...

Sheet 2024 Budget
A1: Bravado Spice
A2: Forecast 2024 | AD2: 2024 by Month
K3: 2023 Forecast (Original) | R3: 2023 Forecast (Original)
K4: 2023 | R4: 2024 | AD4: Actual | AJ4: Budget
C5: 2019 | E5: 2020 | G5: 2021 | I5: 2022 | K5: Q1 | L5: Q2 | M5: Q3 | N5: Q4 | O5: 2023 | R5: Q1 | S5: Q2 | T5: Q3 | U5: Q4 | V5: 2024 | X5: Notes | Z5: Q3 Actual | AA5: Oct | AB5: Nov | AC5: Dec | AD5: Jan | AE5: Feb | AF5: Mar | AG5: Apr | AH5: May | AI5: June | AJ5: July | AK5: Aug | AL5: Sept | AM5: Oct | AN5: Nov | AO5: Dec | AP5: 2024 Total | AR5: Assumptions
A6: Sales
B7: Retail | AP7: =SUM(AD7:AO7) -> 0 | AQ7: =AP7/AP$15 -> 0
B8: Online/Amazon | AP8: =SUM(AD8:AO8) -> 0 | AQ8: =AP8/AP$15 -> 0
B9: Less Amazon netting | AP9: =SUM(AD9:AO9) -> 0 | AQ9: =AP9/AP$15 -> 0
B10: Distributor | AP10: =SUM(AD10:AO10) -> 0 | AQ10: =AP10/AP$15 -> 0
B11: Franchise | AP11: =SUM(AD11:AO11) -> 0 | AQ11: =AP11/AP$15 -> 0
B12: Total hot sauce | C12: =QB!F20+QB!F30+QB!F33+QB!F34+QB!F40 -> 1176162.1 | E12: =QB!K20+QB!K30+QB!K33+QB!K34+QB!K40 -> 1985300.7 | G12: =QB!P20+QB!P30+QB!P33+QB!P34+QB!P40 -> 1946199.2
B13: Mixers & seasonings | C13: =QB!F24+QB!F29 -> 98761.52 | E13: =QB!K24+QB!K29 -> 182871.54 | G13: =QB!P24+QB!P29 -> 249354.5
B14: Other | C14: =QB!F42+QB!F43+QB!F44 -> 5945.28 | E14: =QB!K42+QB!K43+QB!K44 -> 1082.89 | G14: =QB!P42+QB!P43+QB!P44 -> 6343.26
A15: Sales | C15: =SUM(C12:C14) -> 1280868.9 | D15: =C15/C$15 -> 1 | E15: =SUM(E12:E14) -> 2169255.1 | F15: =E15/E$15 -> 1 | G15: =SUM(G12:G14) -> 2201897 | H15: =G15/G$15 -> 1 | I15: 2321440 | J15: =I15/I$15 -> 1 | K15: 570041 | L15: 405174 | M15: 347143 | N15: 432361 | O15: =SUM(K15:N15) -> 1754719 | P15: =O15/O$15 -> 1 | R15: =SUM(AD15:AF15) -> 232955 | S15: =SUM(AG15:AI15) -> 218307 | T15: =SUM(AJ15:AL15) -> 154911 | U15: =SUM(AM15:AO15) -> 210000 | V15: =SUM(R15:U15) -> 816173 | W15: =V15/V$15 -> 1 | Z15: 347143 | AA15: 155912 | AB15: 147384 | AC15: 129065 | AD15: 97342 | AE15: 69706 | AF15: 65907 | AG15: 58908 | AH15: 77566 | AI15: 81833 | AJ15: 62186 | AK15: 22725 | AL15: 70000 | AM15: 70000 | AN15: 70000 | AO15: 70000 | AP15: =SUM(AD15:AO15) -> 816173 | AQ15: =AP15/AP$15 -> 1 | AR15: Per Jer
A16: Cost of Sales
B17: Co-Packer & ingredients | C17: =QB!F47+QB!F48+QB!F50+QB!F51 -> 497738.93 | D17: =C17/C$15 -> 0.38859476 | E17: 725353 | F17: =E17/E$15 -> 0.33437883 | G17: =QB!P47+QB!P48+QB!P50+QB!P51 -> 943998.9 | H17: =G17/G$15 -> 0.42872073 | I17: 1012654 | J17: =I17/I$15 -> 0.43621804 | K17: 342783 | L17: 213990 | M17: 225540 | N17: 184128 | O17: =SUM(K17:N17) -> 966441 | P17: =O17/O$15 -> 0.55076682 | R17: =SUM(AD17:AF17) -> 101494 | S17: =SUM(AG17:AI17) -> 125769 | T17: =SUM(AJ17:AL17) -> 63046 | U17: =SUM(AM17:AO17) -> 94500 | V17: =SUM(R17:U17) -> 384809 | W17: =V17/V$15 -> 0.4714797 | Z17: 199547 | AA17: 51354 | AB17: 56556 | AC17: 54070 | AD17: 40909 | AE17: 27875 | AF17: 32710 | AG17: 44532 | AH17: 47887 | AI17: 33350 | AJ17: 21398 | AK17: 10148 | AL17: =AL15*0.45 -> 31500 | AM17: =AM15*0.45 -> 31500 | AN17: =AN15*0.45 -> 31500 | AO17: =AO15*0.45 -> 31500 | AP17: =SUM(AD17:AO17) -> 384809 | AQ17: =AP17/AP$15 -> 0.4714797 | AR17: 45% of sales starting June
B18: Shipping & delivery | C18: =QB!F49 -> 115308.88 | D18: =C18/C$15 -> 0.090023954 | E18: =QB!K49 -> 198278.67 | F18: =E18/E$15 -> 0.091404034 | G18: =QB!P49 -> 268052.97 | H18: =G18/G$15 -> 0.12173729 | I18: 214975 | J18: =I18/I$15 -> 0.092604159 | K18: 46962 | L18: 32407 | M18: 27976 | N18: 27158 | O18: =SUM(K18:N18) -> 134503 | P18: =O18/O$15 -> 0.076652159 | R18: =SUM(AD18:AF18) -> 18015 | S18: =SUM(AG18:AI18) -> 12763 | T18: =SUM(AJ18:AL18) -> 12867 | U18: =SUM(AM18:AO18) -> 14700 | V18: =SUM(R18:U18) -> 58345 | W18: =V18/V$15 -> 0.07148607 | Z18: 27976 | AA18: 8573 | AB18: 10446 | AC18: 8139 | AD18: 8646 | AE18: 5159 | AF18: 4210 | AG18: 4062 | AH18: 5030 | AI18: 3671 | AJ18: 4688 | AK18: 3279 | AL18: =0.07*AL15 -> 4900 | AM18: =0.07*AM15 -> 4900 | AN18: =0.07*AN15 -> 4900 | AO18: =0.07*AO15 -> 4900 | AP18: =SUM(AD18:AO18) -> 58345 | AQ18: =AP18/AP$15 -> 0.07148607 | AR18: 7% of sales
B19: Inventory adjustment | I19: -100 | J19: =I19/I$15 -> -4.3076711e-05 | O19: =SUM(K19:N19) -> 0 | R19: =SUM(AD19:AF19) -> 6240 | S19: =SUM(AG19:AI19) -> 3848 | T19: =SUM(AJ19:AL19) -> 2171 | U19: =SUM(AM19:AO19) -> 0 | V19: =SUM(R19:U19) -> 12259 | AD19: 6900 | AE19: -2315 | AF19: 1655 | AG19: 2783 | AH19: 696 | AI19: 369 | AJ19: 1326 | AK19: 845 | AP19: =SUM(AD19:AO19) -> 12259
B20: Materials | C20: =QB!F52 -> 128054.04 | D20: =C20/C$15 -> 0.099974356 | E20: =QB!K52 -> 194413.35 | F20: =E20/E$15 -> 0.089622169 | G20: =QB!P52 -> 179567.31 | H20: =G20/G$15 -> 0.081551185 | J20: =I20/I$15 -> 0 | K20: =SUM(I20:J20) -> 0 | L20: =SUM(I20:K20) -> 0 | M20: =SUM(J20:L20) -> 0 | N20: =SUM(K20:M20) -> 0 | O20: =SUM(K20:N20) -> 0 | P20: =O20/O$15 -> 0 | R20: =SUM(AD20:AF20) -> 0 | S20: =SUM(AG20:AI20) -> 0 | T20: =SUM(AJ20:AL20) -> 0 | U20: =SUM(AM20:AO20) -> 0 | V20: =SUM(R20:U20) -> 0 | W20: =V20/V$15 -> 0 | AP20: =SUM(AD20:AO20) -> 0 | AQ20: =AP20/AP$15 -> 0
B21: KeHe slotting fees | O21: =SUM(K21:N21) -> 0 | R21: =SUM(AD21:AF21) -> 0 | S21: =SUM(AG21:AI21) -> 0 | T21: =SUM(AJ21:AL21) -> 0 | U21: =SUM(AM21:AO21) -> 0 | V21: =SUM(R21:U21) -> 0 | AP21: =SUM(AD21:AO21) -> 0
B22: Swell/other discounts | C22: 25822 | D22: =C22/C$15 -> 0.020159753 | E22: 62660 | F22: =E22/E$15 -> 0.028885491 | I22: 82476 | J22: =I22/I$15 -> 0.035527948 | K22: 18624 | L22: 15910 | M22: 46676 | N22: 34766 | O22: =SUM(K22:N22) -> 115976 | P22: =O22/O$15 -> 0.066093773 | R22: =SUM(AD22:AF22) -> 44790 | S22: =SUM(AG22:AI22) -> 11937 | T22: =SUM(AJ22:AL22) -> 12941 | U22: =SUM(AM22:AO22) -> 12600 | V22: =SUM(R22:U22) -> 82268 | Z22: 52288 | AA22: 20454 | AB22: 12986 | AC22: 2493 | AD22: 19221 | AE22: 18623 | AF22: 6946 | AG22: 7371 | AH22: 2440 | AI22: 2126 | AJ22: 5443 | AK22: 3298 | AL22: =AL15*0.06 -> 4200 | AM22: =AM15*0.06 -> 4200 | AN22: =AN15*0.06 -> 4200 | AO22: =AO15*0.06 -> 4200 | AP22: =SUM(AD22:AO22) -> 82268 | AR22: 8% of sales, bump in June promo, 6% last few mos
B23: Other | D23: =C23/C$15 -> 0 | E23: 33331 | F23: =E23/E$15 -> 0.015365182 | G23: =QB!P53+QB!P54+QB!P55+QB!P56+QB!P57+QB!P58+QB!P59+QB!P60+QB!P61+QB!P62+QB!P64 -> 76433.53 | H23: =G23/G$15 -> 0.034712582 | I23: 1566 | J23: =I23/I$15 -> 0.00067458129 | K23: 7237 | L23: 1331 | M23: 9057 | N23: 4257 | O23: =SUM(K23:N23) -> 21882 | P23: =O23/O$15 -> 0.012470373 | R23: =SUM(AD23:AF23) -> 7098 | S23: =SUM(AG23:AI23) -> 6573 | T23: =SUM(AJ23:AL23) -> 4865 | U23: =SUM(AM23:AO23) -> 6300 | V23: =SUM(R23:U23) -> 24836 | W23: =V23/V$15 -> 0.030429823 | Z23: 29434 | AA23: 10167 | AB23: 6575 | AC23: 9120 | AD23: 1408 | AE23: 97 | AF23: 5593 | AG23: 5783 | AH23: 484 | AI23: 306 | AJ23: 2519 | AK23: 246 | AL23: =AL15*0.03 -> 2100 | AM23: =AM15*0.03 -> 2100 | AN23: =AN15*0.03 -> 2100 | AO23: =AO15*0.03 -> 2100 | AP23: =SUM(AD23:AO23) -> 24836 | AQ23: =AP23/AP$15 -> 0.030429823 | AR23: 3% of sales
B24: Total CGS | C24: =SUM(C17:C23) -> 766923.85 | D24: =C24/C$15 -> 0.59875282 | E24: =SUM(E17:E23) -> 1214036 | F24: =E24/E$15 -> 0.55965571 | G24: =SUM(G17:G23) -> 1468052.7 | H24: =G24/G$15 -> 0.66672179 | I24: =SUM(I17:I23) -> 1311571 | J24: =I24/I$15 -> 0.56498165 | K24: =SUM(K17:K23) -> 415606 | L24: =SUM(L17:L23) -> 263638 | M24: =SUM(M17:M23) -> 309249 | N24: =SUM(N17:N23) -> 250309 | O24: =SUM(O17:O23) -> 1238802 | P24: =O24/O$15 -> 0.70598312 | R24: =SUM(R17:R23) -> 177637 | S24: =SUM(S17:S23) -> 160890 | T24: =SUM(T17:T23) -> 95890 | U24: =SUM(U17:U23) -> 128100 | V24: =SUM(V17:V23) -> 562517 | W24: =V24/V$15 -> 0.68921295 | Z24: =SUM(Z17:Z23) -> 309245 | AA24: =SUM(AA17:AA23) -> 90548 | AB24: =SUM(AB17:AB23) -> 86563 | AC24: =SUM(AC17:AC23) -> 73822 | AD24: =SUM(AD17:AD23) -> 77084 | AE24: =SUM(AE17:AE23) -> 49439 | AF24: =SUM(AF17:AF23) -> 51114 | AG24: =SUM(AG17:AG23) -> 64531 | ... AP24: =SUM(AP17:AP23) -> 562517 | AQ24: =AP24/AP$15 -> 0.68921295
A25: Gross Margin | C25: =C15-C24 -> 513945.02 | D25: =C25/C$15 -> 0.40124718 | E25: =E15-E24 -> 955219.12 | F25: =E25/E$15 -> 0.44034429 | G25: =G15-G24 -> 733844.3 | H25: =G25/G$15 -> 0.33327821 | I25: =I15-I24 -> 1009869 | J25: =I25/I$15 -> 0.43501835 | K25: =K15-K24 -> 154435 | L25: =L15-L24 -> 141536 | M25: =M15-M24 -> 37894 | N25: =N15-N24 -> 182052 | O25: =O15-O24 -> 515917 | P25: =O25/O$15 -> 0.29401688 | R25: =R15-R24 -> 55318 | S25: =S15-S24 -> 57417 | T25: =T15-T24 -> 59021 | U25: =U15-U24 -> 81900 | V25: =V15-V24 -> 253656 | W25: =V25/V$15 -> 0.31078705 | Z25: =Z15-Z24 -> 37898 | AA25: =AA15-AA24 -> 65364 | AB25: =AB15-AB24 -> 60821 | AC25: =AC15-AC24 -> 55243 | AD25: =AD15-AD24 -> 20258 | AE25: =AE15-AE24 -> 20267 | AF25: =AF15-AF24 -> 14793 | AG25: =AG15-AG24 -> -5623 | ... AP25: =AP15-AP24 -> 253656 | AQ25: =AP25/AP$15 -> 0.31078705
K26: =K25/K15 -> 0.27091911 | L26: =L25/L15 -> 0.34932153 | M26: =M25/M15 -> 0.10915963 | N26: =N25/N15 -> 0.4210648 | R26: =R25/R15 -> 0.23746217 | S26: =S25/S15 -> 0.26301035 | T26: =T25/T15 -> 0.38099941 | U26: =U25/U15 -> 0.39 | Z26: =Z25/Z15 -> 0.10917115 | AA26: =AA25/AA15 -> 0.41923649 | AB26: =AB25/AB15 -> 0.4126703 | AC26: =AC25/AC15 -> 0.42802464 | AD26: =AD25/AD15 -> 0.20811161 | AE26: =AE25/AE15 -> 0.29074972 | AF26: =AF25/AF15 -> 0.22445264 | AG26: =AG25/AG15 -> -0.095453928 | ... AO26: =AO25/AO15 -> 0.39
A27: Selling, General & Administrative
B28: Compensation
B29: Salaries & wages | C29: =QB!F110 -> 0 | D29: =C29/C$15 -> 0 | E29: =QB!K110 -> 216764.24 | F29: =E29/E$15 -> 0.099925655 | G29: =QB!P110 -> 391277.16 | H29: =G29/G$15 -> 0.17770003 | I29: 410305 | J29: =I29/I$15 -> 0.1767459 | K29: 113695 | L29: 113361 | M29: 88012 | N29: 79844 | O29: =SUM(K29:N29) -> 394912 | P29: =O29/O$15 -> 0.22505712 | R29: =SUM(AD29:AF29) -> 74406 | S29: =SUM(AG29:AI29) -> 40476 | T29: =SUM(AJ29:AL29) -> 22574 | U29: =SUM(AM29:AO29) -> 45222 | V29: =SUM(R29:U29) -> 182678 | W29: =V29/V$15 -> 0.22382265 | Z29: 88012 | AA29: 32685 | AB29: 24892 | AC29: 22267 | AD29: 29409 | AE29: 22407 | AF29: 22590 | AG29: 17255 | AH29: 14039 | AI29: 9182 | AJ29: 5000 | AK29: 2500 | AL29: 15074 | AM29: 15074 | AN29: 15074 | AO29: 15074 | AP29: =SUM(AD29:AO29) -> 182678 | AQ29: =AP29/AP$15 -> 0.22382265
B30: Spencer | AB30: =$AR30*2 -> 4744 | AC30: =$AR30*2 -> 4744 | AD30: =$AR30*2 -> 4744 | AE30: 1313 | AR30: 2372
B31: Ryan (Kristopher) | AB31: =$AR31*2 -> 5000 | AC31: =$AR31*2 -> 5000 | AD31: =$AR31*2 -> 5000 | AE31: =$AR31*2 -> 5000 | AR31: 2500
B32: Levi | AB32: =$AR32*2 -> 4574 | AC32: =$AR32*2 -> 4574 | AD32: 4416 | AE32: 4468 | AF32: =$AR32*2 -> 4574 | AG32: =$AR32*2 -> 4574 | AH32: =$AR32*2 -> 4574 | AI32: =$AR32*2 -> 4574 | AJ32: 3776 | AK32: 3776 | AL32: 3776 | AM32: 3776 | AN32: 3776 | AO32: 3776 | AR32: 2287
B33: McKenna | AB33: =$AR33*2 -> 1834 | AC33: =$AR33*2 -> 1834 | AD33: 1834 | AE33: 1834 | AR33: 917
B34: Marisa | AB34: =$AR34*2 -> 2490 | AC34: =$AR34*AC$143 -> 2490 | AD34: 6666 | AE34: 6667 | AF34: 5000 | AG34: 5000 | AH34: 5000 | AI34: 5000 | AJ34: 5000 | AK34: 5000 | AL34: 5000 | AM34: 5000 | AN34: 5000 | AO34: 5000 | AR34: 1245
B35: Jeremiah | AB35: =$AR35*2 -> 7000 | AC35: =$AR35*2 -> 7000 | AD35: 3625 | AE35: 0 | AF35: 3000 | AG35: 3000 | AH35: 3000 | AI35: 3500 | AJ35: 3500 | AK35: 3500 | AL35: 3500 | AM35: 3500 | AN35: 3500 | AO35: 3500 | AR35: 3500
B36: Contract labor | C36: =QB!F108 -> 142452.45 | D36: =C36/C$15 -> 0.11121548 | E36: =QB!K108 -> 57528.86 | F36: =E36/E$15 -> 0.026520099 | G36: =QB!P108 -> 18232.21 | H36: =G36/G$15 -> 0.0082802283 | I36: 84566 | J36: =I36/I$15 -> 0.036428251 | K36: 30320 | L36: 9582 | M36: 9031 | N36: 16319 | O36: =SUM(K36:N36) -> 65252 | P36: =O36/O$15 -> 0.037186581 | R36: =SUM(AD36:AF36) -> 18540 | S36: =SUM(AG36:AI36) -> 19428 | T36: =SUM(AJ36:AL36) -> 20449 | U36: =SUM(AM36:AO36) -> 17160 | V36: =SUM(R36:U36) -> 75577 | W36: =V36/V$15 -> 0.092599241 | Z36: 9030 | AA36: 4939 | AB36: 6242 | AC36: 5138 | AD36: =SUM(AD37:AD40) -> 7721 | AE36: =SUM(AE37:AE40) -> 3588 | AF36: 7231 | AG36: 6049 | AH36: 6115 | AI36: 7264 | AJ36: 8034 | AK36: 6695 | AL36: =SUM(AL37:AL40) -> 5720 | AM36: =SUM(AM37:AM40) -> 5720 | AN36: =SUM(AN37:AN40) -> 5720 | AO36: =SUM(AO37:AO40) -> 5720 | AP36: =SUM(AD36:AO36) -> 75577 | AQ36: =AP36/AP$15 -> 0.092599241
B37: Miguel | AB37: 2860 | AC37: 2860 | AD37: 4767 | AE37: 1428 | AF37: 2860 | AG37: 2860 | AH37: 2860 | AI37: 2860 | AJ37: 2860 | AK37: 2860 | AL37: 2860 | AM37: 2860 | AN37: 2860 | AO37: 2860 | AR37: 1430 fulfillment
B38: Robert | AB38: 2860 | AC38: 2860 | AD38: 2954 | AE38: 2160 | AF38: 2860 | AG38: 2860 | AH38: 2860 | AI38: 2860 | AJ38: 2860 | AK38: 2860 | AL38: 2860 | AM38: 2860 | AN38: 2860 | AO38: 2860 | AR38: 1430 sales admin
B41: Payroll taxes | C41: =QB!F109 -> 0 | D41: =C41/C$15 -> 0 | E41: =QB!K109 -> 18516.46 | F41: =E41/E$15 -> 0.0085358608 | G41: =QB!P109 -> 32796.35 | H41: =G41/G$15 -> 0.014894589 | I41: 31028 | J41: =I41/I$15 -> 0.013365842 | K41: 7707 | L41: 6925 | M41: 5184 | N41: 4472 | O41: =SUM(K41:N41) -> 24288 | P41: =O41/O$15 -> 0.013841532 | R41: =SUM(AD41:AF41) -> 4724 | S41: =SUM(AG41:AI41) -> 2011 | T41: =SUM(AJ41:AL41) -> 1555.92 | U41: =SUM(AM41:AO41) -> 3617.76 | V41: =SUM(R41:U41) -> 11908.68 | W41: =V41/V$15 -> 0.014590877 | Z41: 5184 | AA41: 1439 | AB41: 1363 | AC41: 1670 | AD41: 2184 | AE41: 1545 | AF41: 995 | AG41: 683 | AH41: 804 | AI41: 524 | AJ41: 350 | AK41: 0 | AL41: =AL29*0.08 -> 1205.92 | AM41: =AM29*0.08 -> 1205.92 | AN41: =AN29*0.08 -> 1205.92 | AO41: =AO29*0.08 -> 1205.92 | AP41: =SUM(AD41:AO41) -> 11908.68 | AQ41: =AP41/AP$15 -> 0.014590877 | AR41: 8% of payroll
B42: Employee benefits | C42: =QB!F104 -> 6974.56 | D42: =C42/C$15 -> 0.0054451788 | E42: =QB!K104 -> 10175.58 | F42: =E42/E$15 -> 0.0046908175 | G42: =QB!P104 -> 2511.54 | H42: =G42/G$15 -> 0.0011406256 | I42: 18506 | J42: =I42/I$15 -> 0.0079717761 | K42: 3190 | L42: 3417 | M42: 3692 | N42: 4817 | O42: =SUM(K42:N42) -> 15116 | P42: =O42/O$15 -> 0.0086144847 | R42: =SUM(AD42:AF42) -> 690 | S42: =SUM(AG42:AI42) -> 5594 | T42: =SUM(AJ42:AL42) -> 2856 | U42: =SUM(AM42:AO42) -> 1050 | V42: =SUM(R42:U42) -> 10190 | W42: =V42/V$15 -> 0.012485098 | Z42: 3692 | AC42: 4817 | AD42: 345 | AE42: 138 | AF42: 207 | AG42: 3311 | AH42: 138 | AI42: 2145 | AJ42: 1756 | AK42: 0 | AL42: 1100 | AM42: 350 | AN42: 350 | AO42: 350 | AP42: =SUM(AD42:AO42) -> 10190 | AQ42: =AP42/AP$15 -> 0.012485098 | AR42: Actual - Jer & Mar only
B43: Total compensation | C43: =SUM(C29:C42) -> 149427.01 | D43: =C43/C$15 -> 0.11666066 | E43: =SUM(E29:E42) -> 302985.14 | F43: =E43/E$15 -> 0.13967243 | G43: =SUM(G29:G42) -> 444817.26 | H43: =G43/G$15 -> 0.20201547 | I43: =SUM(I29:I42) -> 544405 | J43: =I43/I$15 -> 0.23451177 | K43: =SUM(K29:K42) -> 154912 | L43: =SUM(L29:L42) -> 133285 | M43: =SUM(M29:M42) -> 105919 | N43: =SUM(N29:N42) -> 105452 | O43: =SUM(O29:O42) -> 499568 | P43: =O43/O$15 -> 0.28469972 | R43: =SUM(R29:R42) -> 98360 | S43: =SUM(S29:S42) -> 67509 | T43: =SUM(T29:T42) -> 47434.92 | U43: =SUM(U29:U42) -> 67049.76 | V43: =SUM(V29:V42) -> 280353.68 | W43: =V43/V$15 -> 0.34349786 | Z43: =SUM(Z29:Z42) -> 105918 | AA43: =SUM(AA29:AA42) -> 39063 | AB43: =AB29+AB36+AB41+AB42 -> 32497 | AC43: =AC29+AC36+AC41+AC42 -> 33892 | AD43: =AD29+AD36+AD41+AD42 -> 39659 | AE43: =AE29+AE36+AE41+AE42 -> 27678 | AF43: =AF29+AF36+AF41+AF42 -> 31023 | AG43: =AG29+AG36+AG41+AG42 -> 27298 | AH43: =AH29+AH36+AH41+AH42 -> 21096 | AI43: =AI29+AI36+AI41+AI42 -> 19115 | ... AO43: =AO29+AO36+AO41+AO42 -> 22349.92 | AP43: =SUM(AP29:AP42) -> 280353.68 | AQ43: =AP43/AP$15 -> 0.34349786
B44: Marketing & advertising | C44: =QB!F80 -> 120088.93 | D44: =C44/C$15 -> 0.093755835 | E44: =QB!K80 -> 126166.54 | F44: =E44/E$15 -> 0.058161227 | G44: =QB!P80 -> 153428.37 | H44: =G44/G$15 -> 0.069680085 | I44: 182458 | J44: =I44/I$15 -> 0.078596905 | K44: 47826 | L44: 43028 | M44: 32671 | N44: 13368 | O44: =SUM(K44:N44) -> 136893 | P44: =O44/O$15 -> 0.078014201 | R44: =SUM(AD44:AF44) -> 15741 | S44: =SUM(AG44:AI44) -> 13643 | T44: =SUM(AJ44:AL44) -> 6297 | U44: =SUM(AM44:AO44) -> 6000 | V44: =SUM(R44:U44) -> 41681 | W44: =V44/V$15 -> 0.05106883 | Z44: 35371 | AA44: -277 | AB44: =SUM(AB45:AB51) -> 37351 | AC44: =SUM(AC45:AC51) -> 11703 | AD44: =SUM(AD45:AD51) -> 4931 | AE44: =SUM(AE45:AE51) -> 8652 | AF44: 2158 | AG44: =SUM(AG45:AG51) -> 3074 | AH44: 7656 | AI44: 2913 | AJ44: 2482 | AK44: 1815 | AL44: =SUM(AL45:AL51) -> 2000 | AM44: =SUM(AM45:AM51) -> 2000 | AN44: =SUM(AN45:AN51) -> 2000 | AO44: =SUM(AO45:AO51) -> 2000 | AP44: =SUM(AD44:AO44) -> 41681 | AQ44: =AP44/AP$15 -> 0.05106883 | AR44: Per Jer
B45: Events & shows | AB45: 5091 | AD45: 15 | AE45: 3991 | AF45: 5 | AG45: 75 | AJ45: 3000
B46: Travel | AD46: 3487 | AE46: 209 | AF46: 732 | AG46: 362
B47: Social Media | AD47: 741 | AH47: 300 | AI47: 300 | AJ47: 300 | AK47: 300 | AL47: 300 | AM47: 300 | AN47: 300 | AO47: 300
B48: In store | AD48: 192 | AE48: 30 | AF48: 106 | AG48: 141 | AH48: 300 | AI48: 300 | AJ48: 300 | AK48: 300 | AL48: 300 | AM48: 300 | AN48: 300 | AO48: 300
B49: Website
A50: a | B50: Slotting fees | M50: 2700 | N50: 35410 | O50: =SUM(K50:N50) -> 38110 | P50: =O50/O$15 -> 0.021718577 | T50: =SUM(AJ50:AL50) -> 0 | U50: =SUM(AM50:AO50) -> 0 | V50: =SUM(R50:U50) -> 0 | W50: =V50/V$15 -> 0 | AB50: 30280 | AC50: 5130
B51: Other | AB51: 1980 | AC51: 6573 | AD51: 496 | AE51: 4422 | AF51: 1314 | AG51: 2496 | AH51: 1400 | AI51: 1400 | AJ51: 1400 | AK51: 1400 | AL51: 1400 | AM51: 1400 | AN51: 1400 | AO51: 1400
B52: Rent | C52: =QB!F85 -> 38000.7 | D52: =C52/C$15 -> 0.029667908 | E52: =QB!K85 -> 32084.48 | F52: =E52/E$15 -> 0.014790552 | G52: =QB!P85 -> 84207.42 | H52: =G52/G$15 -> 0.038243124 | I52: 109406 | J52: =I52/I$15 -> 0.047128506 | K52: 37316 | L52: 28264 | M52: 28321 | N52: 28907 | O52: =SUM(K52:N52) -> 122808 | P52: =O52/O$15 -> 0.069987274 | R52: =SUM(AD52:AF52) -> 9705 | S52: =SUM(AG52:AI52) -> 13399 | T52: =SUM(AJ52:AL52) -> 5086 | U52: =SUM(AM52:AO52) -> 4660 | V52: =SUM(R52:U52) -> 32850 | W52: =V52/V$15 -> 0.04024882 | Z52: 29360 | AA52: 9440 | AB52: 9372 | AC52: 10026 | AD52: =9560-4500 -> 5060 | AE52: 9559 | AF52: -4914 | AG52: 4653 | AH52: 6034 | AI52: 2712 | AJ52: 2548 | AK52: 2538 | AL52: 0 | AM52: 0 | AN52: 2330 | AO52: =AN52 -> 2330 | AP52: =SUM(AD52:AO52) -> 32850 | AQ52: =AP52/AP$15 -> 0.04024882 | AR52: In June start $1425 + (pallets x $15)/mo
B53: Office/food expenses | C53: 20867 | D53: =C53/C$15 -> 0.016291285 | E53: =QB!K89 -> 28881.79 | F53: =E53/E$15 -> 0.013314151 | G53: =QB!P89 -> 62978.55 | H53: =G53/G$15 -> 0.028601951 | I53: 65098 | J53: =I53/I$15 -> 0.028042077 | K53: 11546 | L53: 6569 | M53: 1645 | N53: 3394 | O53: =SUM(K53:N53) -> 23154 | P53: =O53/O$15 -> 0.013195275 | R53: =SUM(AD53:AF53) -> 3695 | S53: =SUM(AG53:AI53) -> 3293 | T53: =SUM(AJ53:AL53) -> 3163 | U53: =SUM(AM53:AO53) -> 3600 | V53: =SUM(R53:U53) -> 13751 | W53: =V53/V$15 -> 0.016848144 | Z53: 1644 | AA53: 1798 | AB53: 1032 | AC53: 564 | AD53: 251 | AE53: 1029 | AF53: 2415 | AG53: 1007 | AH53: 1318 | AI53: 968 | AJ53: 1746 | AK53: 217 | AL53: 1200 | AM53: =AL53 -> 1200 | AN53: =AM53 -> 1200 | AO53: =AN53 -> 1200 | AP53: =SUM(AD53:AO53) -> 13751 | AQ53: =AP53/AP$15 -> 0.016848144 | AR53: Per discussion 11/20
B54: Travel | C54: 10236 | D54: =C54/C$15 -> 0.0079914504 | E54: =QB!K113 -> 6913.83 | F54: =E54/E$15 -> 0.0031871908 | G54: =QB!P113 -> 9268.26 | H54: =G54/G$15 -> 0.0042092159 | I54: 23884 | J54: =I54/I$15 -> 0.010288442 | K54: 10230 | L54: 17117 | M54: 9398 | N54: 2277 | O54: =SUM(K54:N54) -> 39022 | P54: =O54/O$15 -> 0.022238318 | R54: =SUM(AD54:AF54) -> 18 | S54: =SUM(AG54:AI54) -> 95 | T54: =SUM(AJ54:AL54) -> 591 | U54: =SUM(AM54:AO54) -> 1500 | V54: =SUM(R54:U54) -> 2204 | W54: =V54/V$15 -> 0.0027004079 | Z54: 9398 | AA54: 1514 | AB54: 571 | AC54: 192 | AF54: 18 | AI54: 95 | AJ54: 13 | AK54: 78 | AL54: 500 | AM54: 500 | AN54: 500 | AO54: 500 | AP54: =SUM(AD54:AO54) -> 2204 | AQ54: =AP54/AP$15 -> 0.0027004079 | AR54: Per Jer
B55: Dues & subscriptions | C55: =QB!F100 -> 9066.62 | D55: =C55/C$15 -> 0.007078492 | E55: =QB!K100 -> 9832.89 | F55: =E55/E$15 -> 0.0045328416 | G55: =QB!P100 -> 13230.97 | H55: =G55/G$15 -> 0.0060088959 | I55: 20486 | J55: =I55/I$15 -> 0.008824695 | K55: 12949 | L55: 10819 | M55: 17922 | N55: 10655 | O55: =SUM(K55:N55) -> 52345 | P55: =O55/O$15 -> 0.029830987 | R55: =SUM(AD55:AF55) -> 7703 | S55: =SUM(AG55:AI55) -> 5633 | T55: =SUM(AJ55:AL55) -> 8758 | U55: =SUM(AM55:AO55) -> 6600 | V55: =SUM(R55:U55) -> 28694 | W55: =V55/V$15 -> 0.035156762 | Z55: 17922 | AA55: 3465 | AB55: 5065 | AC55: 2125 | AD55: 2088 | AE55: 1427 | AF55: 4188 | AG55: 649 | AH55: 2517 | AI55: 2467 | AJ55: 3594 | AK55: 2964 | AL55: 2200 | AM55: =AL55 -> 2200 | AN55: =AM55 -> 2200 | AO55: =AN55 -> 2200 | AP55: =SUM(AD55:AO55) -> 28694 | AQ55: =AP55/AP$15 -> 0.035156762 | AR55: Per analysis, software subscriptions
B56: Insurance | C56: =QB!F101+QB!F102+QB!F103 -> 7786.98 | D56: =C56/C$15 -> 0.0060794514 | E56: =QB!K101+QB!K102+QB!K103 -> 9618.2 | F56: =E56/E$15 -> 0.0044338722 | G56: =QB!P101+QB!P102+QB!P103 -> 19428.15 | H56: =G56/G$15 -> 0.0088233691 | I56: 16312 | J56: =I56/I$15 -> 0.0070266731 | K56: 8122 | L56: 4876 | M56: 3609 | N56: 2133 | O56: =SUM(K56:N56) -> 18740 | P56: =O56/O$15 -> 0.010679773 | R56: =SUM(AD56:AF56) -> 6382 | S56: =SUM(AG56:AI56) -> 825 | T56: =SUM(AJ56:AL56) -> 1430 | U56: =SUM(AM56:AO56) -> 2508 | V56: =SUM(R56:U56) -> 11145 | W56: =V56/V$15 -> 0.013655193 | Z56: 3610 | AA56: 1394 | AB56: 364 | AC56: 375 | AD56: 3015 | AE56: =201+94+1809 -> 2104 | AF56: 1263 | AG56: 1316 | AH56: 1236 | AI56: -1727 | AJ56: 297 | AK56: 297 | AL56: 836 | AM56: 836 | AN56: 836 | AO56: 836 | AP56: =SUM(AD56:AO56) -> 11145 | AQ56: =AP56/AP$15 -> 0.013655193 | AR56: Beam(dental), SF(auto), SF(liab/WC)
B57: Utilities | C57: =QB!F90 -> 3827.54 | D57: =C57/C$15 -> 0.0029882372 | E57: =QB!K90 -> 4766.11 | F57: =E57/E$15 -> 0.0021971182 | G57: =QB!P90 -> 12331.72 | H57: =G57/G$15 -> 0.0056004981 | I57: 13550 | J57: =I57/I$15 -> 0.0058368943 | K57: 6236 | L57: 5636 | M57: 5354 | N57: 5161 | O57: =SUM(K57:N57) -> 22387 | P57: =O57/O$15 -> 0.012758168 | W57: =V57/V$15 -> 0 | AA57: 3400
B58: - Phone | O58: =SUM(K58:N58) -> 0 | R58: =SUM(AD58:AF58) -> 2356 | S58: =SUM(AG58:AI58) -> 2611 | T58: =SUM(AJ58:AL58) -> 1056 | U58: =SUM(AM58:AO58) -> 714 | V58: =SUM(R58:U58) -> 6737 | Z58: 2189 | AC58: 650 | AD58: 792 | AE58: 782 | AF58: 782 | AG58: 610 | AH58: 610 | AI58: 1391 | AJ58: 580 | AK58: 238 | AL58: 238 | AM58: 238 | AN58: 238 | AO58: 238 | AP58: =SUM(AD58:AO58) -> 6737 | AQ58: =AP58/AP$15 -> 0.0082543774 | AR58: Verizon(phone), AT&T (internet)
B59: - Electric | O59: =SUM(K59:N59) -> 0 | R59: =SUM(AD59:AF59) -> 3231 | S59: =SUM(AG59:AI59) -> 1347 | T59: =SUM(AJ59:AL59) -> 0 | U59: =SUM(AM59:AO59) -> 0 | V59: =SUM(R59:U59) -> 4578 | Z59: 3165 | AB59: 252 | AC59: 858 | AD59: 1298 | AE59: 0 | AF59: 1933 | AG59: 683 | AI59: 664 | AP59: =SUM(AD59:AO59) -> 4578 | AQ59: =AP59/AP$15 -> 0.0056091049 | AR59: Trend
B60: Professional fees | C60: =QB!F106 -> 8793.32 | D60: =C60/C$15 -> 0.0068651212 | E60: =QB!K106 -> 14641.91 | F60: =E60/E$15 -> 0.0067497408 | G60: =QB!P106 -> 25989.68 | H60: =G60/G$15 -> 0.011803313 | I60: 19267 | J60: =I60/I$15 -> 0.0082995899 | K60: 12052 | L60: 9564 | M60: 9537 | N60: 12881 | O60: =SUM(K60:N60) -> 44034 | P60: =O60/O$15 -> 0.025094616 | R60: =SUM(AD60:AF60) -> 7487 | S60: =SUM(AG60:AI60) -> 17322 | T60: =SUM(AJ60:AL60) -> 12441 | U60: =SUM(AM60:AO60) -> 12402 | V60: =SUM(R60:U60) -> 49652 | W60: =V60/V$15 -> 0.060835142 | Z60: 9537 | AA60: 2194 | AB60: 1594 | AC60: 9094 | AD60: 5893 | AE60: 0 | AF60: 1594 | AG60: 9094 | AH60: 4094 | AI60: 4134 | AJ60: =AI60 -> 4134 | AK60: 4173 | AL60: 4134 | AM60: =AL60 -> 4134 | AN60: =AM60 -> 4134 | AO60: =AN60 -> 4134 | AP60: =SUM(AD60:AO60) -> 49652 | AQ60: =AP60/AP$15 -> 0.060835142 | AR60: $1594/mo bookies, $2500/mo Mark
B61: Repairs & maintenance | C61: =QB!F115 -> 5276.76 | D61: =C61/C$15 -> 0.0041196723 | E61: =QB!K115 -> 3200.57 | F61: =E61/E$15 -> 0.0014754235 | G61: =QB!P115 -> 8234.48 | H61: =G61/G$15 -> 0.0037397208 | I61: 11020 | J61: =I61/I$15 -> 0.0047470536 | K61: 1010 | L61: 2214 | M61: 1118 | N61: 738 | O61: =SUM(K61:N61) -> 5080 | P61: =O61/O$15 -> 0.0028950504 | R61: =SUM(AD61:AF61) -> 361 | S61: =SUM(AG61:AI61) -> 777 | T61: =SUM(AJ61:AL61) -> 200 | U61: =SUM(AM61:AO61) -> 600 | V61: =SUM(R61:U61) -> 1938 | W61: =V61/V$15 -> 0.0023744966 | Z61: 1118 | AA61: 534 | AC61: 204 | AD61: 0 | AE61: 0 | AF61: 361 | AG61: 259 | AH61: 354 | AI61: 164 | AJ61: 0 | AK61: 0 | AL61: 200 | AM61: 200 | AN61: 200 | AO61: 200 | AP61: =SUM(AD61:AO61) -> 1938 | AQ61: =AP61/AP$15 -> 0.0023744966 | AR61: Average
B62: Taxes & licenses | C62: =QB!F107 -> 2966.05 | D62: =C62/C$15 -> 0.0023156547 | E62: =QB!K107 -> 3042.38 | F62: =E62/E$15 -> 0.0014024998 | G62: =QB!P107 -> 22007.56 | H62: =G62/G$15 -> 0.0099948181 | I62: 9262 | J62: =I62/I$15 -> 0.003989765 | K62: 849 | L62: 7574 | M62: 150 | N62: 0 | O62: =SUM(K62:N62) -> 8573 | P62: =O62/O$15 -> 0.0048856826 | R62: =SUM(AD62:AF62) -> 0 | S62: =SUM(AG62:AI62) -> 0 | T62: =SUM(AJ62:AL62) -> 1 | U62: =SUM(AM62:AO62) -> 0 | V62: =SUM(R62:U62) -> 1 | W62: =V62/V$15 -> 1.2252304e-06 | Z62: 150 | AB62: 0 | AC62: 0 | AD62: 0 | AE62: 0 | AF62: 0 | AG62: 0 | AH62: 0 | AI62: 0 | AJ62: 0 | AK62: 1 | AL62: 0 | AM62: 0 | AN62: 0 | AO62: 0 | AP62: =SUM(AD62:AO62) -> 1 | AQ62: =AP62/AP$15 -> 1.2252304e-06 | AR62: Franchise tax in April
B63: Reimbursements | C63: =QB!F114 -> 0 | D63: =C63/C$15 -> 0 | E63: =QB!K114 -> 0 | F63: =E63/E$15 -> 0 | G63: =QB!P114 -> 32.44 | H63: =G63/G$15 -> 1.4732751e-05 | I63: 3653 | J63: =I63/I$15 -> 0.0015735923 | K63: 1267 | L63: 917 | M63: 794 | N63: 1092 | O63: =SUM(K63:N63) -> 4070 | P63: =O63/O$15 -> 0.0023194597 | R63: =SUM(AD63:AF63) -> 423 | S63: =SUM(AG63:AI63) -> 55 | T63: =SUM(AJ63:AL63) -> 100 | U63: =SUM(AM63:AO63) -> 300 | V63: =SUM(R63:U63) -> 878 | W63: =V63/V$15 -> 0.0010757523 | Z63: 794 | AA63: 650 | AC63: 442 | AD63: 79 | AE63: 240 | AF63: 104 | AH63: 55 | AJ63: 0 | AK63: 0 | AL63: 100 | AM63: 100 | AN63: 100 | AO63: 100 | AP63: =SUM(AD63:AO63) -> 878 | AQ63: =AP63/AP$15 -> 0.0010757523 | AR63: Average
B64: Bank/Faire/CC charges | O64: =SUM(K64:N64) -> 0 | AP64: =SUM(AD64:AO64) -> 0
B65: - Bank/cc | C65: 4055 | D65: =C65/C$15 -> 0.0031658198 | E65: 1905 | F65: =E65/E$15 -> 0.00087818162 | G65: 4660 | H65: =G65/G$15 -> 0.0021163569 | I65: 11808 | J65: =I65/I$15 -> 0.005086498 | K65: 5812 | L65: 6586 | M65: 3830 | N65: 1598 | O65: =SUM(K65:N65) -> 17826 | R65: =SUM(AD65:AF65) -> 4247 | S65: =SUM(AG65:AI65) -> 7292 | T65: =SUM(AJ65:AL65) -> 5696 | U65: =SUM(AM65:AO65) -> 3000 | V65: =SUM(R65:U65) -> 20235 | Z65: 3831 | AA65: 252 | AB65: 533 | AC65: 813 | AD65: 1441 | AE65: 640 | AF65: 2166 | AG65: 3759 | AH65: 2176 | AI65: 1357 | AJ65: 1514 | AK65: =770+2412 -> 3182 | AL65: 1000 | AM65: 1000 | AN65: 1000 | AO65: 1000 | AP65: =SUM(AD65:AO65) -> 20235
B66: - Faire | O66: =SUM(K66:N66) -> 0 | R66: =SUM(AD66:AF66) -> 616 | S66: =SUM(AG66:AI66) -> 446 | T66: =SUM(AJ66:AL66) -> 712 | U66: =SUM(AM66:AO66) -> 525 | V66: =SUM(R66:U66) -> 2299 | AD66: 366 | AE66: 102 | AF66: 148 | AG66: 76 | AH66: 172 | AI66: 198 | AJ66: 354 | AK66: 183 | AL66: 175 | AM66: 175 | AN66: 175 | AO66: 175 | AP66: =SUM(AD66:AO66) -> 2299
B67: - Interest | C67: 6092 | D67: =C67/C$15 -> 0.0047561465 | E67: 577 | F67: =E67/E$15 -> 0.00026598992 | G67: 3496 | H67: =G67/G$15 -> 0.0015877219 | I67: 21775 | J67: =I67/I$15 -> 0.0093799538 | K67: 16981 | L67: 23222 | M67: 15052 | N67: 9081 | O67: =SUM(K67:N67) -> 64336 | R67: =SUM(AD67:AF67) -> 10080 | S67: =SUM(AG67:AI67) -> 8271 | T67: =SUM(AJ67:AL67) -> 6815 | U67: =SUM(AM67:AO67) -> 3500 | V67: =SUM(R67:U67) -> 28666 | AA67: 5025 | AB67: 6435 | AC67: -2378 | AD67: 3799 | AE67: 3609 | AF67: 2672 | AG67: 5113 | AH67: 2317 | AI67: 841 | AJ67: 1310 | AK67: 3505 | AL67: 2000 | AM67: 1500 | AN67: 1000 | AO67: 1000 | AP67: =SUM(AD67:AO67) -> 28666 | AR67: Approx $1200/mo CC/misc, see below
B68: Bad debts | C68: =QB!F112 -> 652.42 | D68: =C68/C$15 -> 0.00050935737 | E68: =QB!K112 -> 6737.83 | F68: =E68/E$15 -> 0.0031060569 | G68: =QB!P112 -> 0 | H68: =G68/G$15 -> 0 | I68: 12743 | J68: =I68/I$15 -> 0.0054892653 | K68: -144 | L68: 0 | M68: 477 | N68: 0 | O68: =SUM(K68:N68) -> 333 | P68: =O68/O$15 -> 0.00018977398 | R68: =SUM(AD68:AF68) -> 0 | S68: =SUM(AG68:AI68) -> 0 | T68: =SUM(AJ68:AL68) -> 0 | U68: =SUM(AM68:AO68) -> 0 | V68: =SUM(R68:U68) -> 0 | W68: =V68/V$15 -> 0 | Z68: 477 | AB68: 0 | AC68: 0 | AD68: 0 | AE68: 0 | AF68: 0 | AG68: 0 | AH68: 0 | AI68: 0 | AJ68: 0 | AK68: 0 | AL68: 0 | AM68: 0 | AN68: 0 | AO68: 0 | AP68: =SUM(AD68:AO68) -> 0 | AQ68: =AP68/AP$15 -> 0
B69: Miscellaneous | C69: -8262 | D69: =C69/C$15 -> -0.006450309 | E69: =QB!K132+QB!K116+QB!K117+QB!K118+QB!K119+QB!K120+QB!K121 -> 4773.89 | F69: =E69/E$15 -> 0.0022007047 | G69: 1625 | H69: =G69/G$15 -> 0.000738 | I69: 1085 | J69: =I69/I$15 -> 0.00046738231 | K69: 87 | L69: -101 | M69: 1156 | N69: -335 | O69: =SUM(K69:N69) -> 807 | P69: =O69/O$15 -> 0.0004599027 | R69: =SUM(AD69:AF69) -> 166 | S69: =SUM(AG69:AI69) -> -23830 | T69: =SUM(AJ69:AL69) -> 2135 | U69: =SUM(AM69:AO69) -> 750 | V69: =SUM(R69:U69) -> -20779 | W69: =V69/V$15 -> -0.025459063 | Z69: -16379 | AA69: 21 | AB69: =-319+83 -> -236 | AC69: 31 | AD69: 7 | AF69: 159 | AG69: -15 | AH69: -596 | AI69: -23219 | AJ69: -2167 | AK69: =1885+2167 -> 4052 | AL69: 250 | AM69: 250 | AN69: 250 | AO69: 250 | AP69: =SUM(AD69:AO69) -> -20779 | AQ69: =AP69/AP$15 -> -0.025459063 | AR69: Cushion
B70: Total SG&A | C70: =SUM(C43:C69) -> 378874.33 | D70: =C70/C$15 -> 0.29579478 | E70: =SUM(E43:E69) -> 556127.56 | F70: =E70/E$15 -> 0.25636798 | G70: =SUM(G43:G69) -> 865735.86 | H70: =G70/G$15 -> 0.39317727 | I70: =SUM(I43:I69) -> 1066212 | J70: =I70/I$15 -> 0.45928906 | K70: =SUM(K43:K69) -> 327051 | L70: =SUM(L43:L69) -> 299570 | M70: =SUM(M43:M69) -> 239653 | N70: =SUM(N43:N69) -> 231812 | O70: =SUM(O43:O69) -> 1098086 | P70: =O70/O$15 -> 0.62579023 | R70: =SUM(R43:R69) -> 170571 | S70: =SUM(S43:S69) -> 118688 | T70: =SUM(T43:T69) -> 101915.92 | U70: =SUM(U43:U69) -> 113708.76 | V70: =SUM(V43:V69) -> 504883.68 | W70: =V70/V$15 -> 0.61859885 | Z70: =SUM(Z43:Z69) -> 208105 | AA70: =SUM(AA43:AA69) -> 68473 | AB70: =SUM(AB43:AB69)-AB45-AB47-AB48-AB49-AB50-AB51 -> 94830 | AC70: =SUM(AC43:AC69)-AC45-AC47-AC48-AC49-AC50-AC51 -> 68591 | AD70: =SUM(AD43:AD69)-AD45-AD46-AD47-AD48-AD49-AD50-AD51 -> 68679 | AE70: =SUM(AE52:AE69)+AE44+AE43 -> 55822 | AF70: =SUM(AF52:AF69)+AF44+AF43 -> 46070 | AG70: =SUM(AG52:AG69)+AG44+AG43 -> 57576 | AH70: =SUM(AH52:AH69)+AH44+AH43 -> 49039 | AI70: =SUM(AI52:AI69)+AI44+AI43 -> 12073 | AJ70: =SUM(AJ52:AJ69)+AJ44+AJ43 -> 31545 | AK70: =SUM(AK52:AK69)+AK44+AK43 -> 32438 | AL70: =SUM(AL52:AL69)+AL44+AL43 -> 37932.92 | ... AP70: =SUM(AP52:AP69)+AP44+AP43 -> 504883.68 | AQ70: =AP70/AP$15 -> 0.61859885
A71: Cash from Operations | C71: =C25-C70 -> 135070.69 | D71: =C71/C$15 -> 0.10545239 | E71: =E25-E70 -> 399091.56 | F71: =E71/E$15 -> 0.18397631 | G71: =G25-G70 -> -131891.56 | H71: =G71/G$15 -> -0.059899059 | I71: =I25-I70 -> -56343 | J71: =I71/I$15 -> -0.024270711 | K71: =K25-K70 -> -172616 | L71: =L25-L70 -> -158034 | M71: =M25-M70 -> -201759 | N71: =N25-N70 -> -49760 | O71: =O25-O70 -> -582169 | P71: =O71/O$15 -> -0.33177335 | R71: =R25-R70 -> -115253 | S71: =S25-S70 -> -61271 | T71: =T25-T70 -> -42894.92 | U71: =U25-U70 -> -31808.76 | V71: =V25-V70 -> -251227.68 | W71: =V71/V$15 -> -0.3078118 | Z71: =Z25-Z70 -> -170207 | AA71: =AA25-AA70 -> -3109 | AB71: =AB25-AB70 -> -34009 | AC71: =AC25-AC70 -> -13348 | AD71: =AD25-AD70 -> -48421 | AE71: =AE25-AE70 -> -35555 | AF71: =AF25-AF70 -> -31277 | AG71: =AG25-AG70 -> -63199 | ... AP71: =AP25-AP70 -> -251227.68 | AQ71: =AP71/AP$15 -> -0.3078118
A72: Debt Service
B73: CC payments, net of charges | N73: 18747 | R73: =SUM(AD73:AF73) -> 28470 | S73: =SUM(AG73:AI73) -> 24341 | T73: =SUM(AJ73:AL73) -> 16994 | U73: =SUM(AM73:AO73) -> 19995 | V73: =SUM(R73:U73) -> 89800 | AA73: =Z128-AA128 -> 15451 | AB73: =AA128-AB128 -> 1827.3 | AC73: =AB128-AC128 -> 1468.7 | AD73: =AC128-AD128 -> 27408 | AE73: =AD128-AE128 -> -1419 | AF73: =AE128-AF128 -> 2481 | AG73: =AF128-AG128 -> 1009 | AH73: =AG128-AH128 -> -168 | ... AJ73: =AI128-AJ128 -> 3664 | AK73: 6665 | AL73: 6665 | AM73: 6665 | AN73: 6665 | AO73: 6665 | AP73: =SUM(AD73:AO73) -> 89800
B74: Anthony Tallerine | R74: =SUM(AD74:AF74) -> 0 | S74: =SUM(AG74:AI74) -> 0 | T74: =SUM(AJ74:AL74) -> 0 | U74: =SUM(AM74:AO74) -> 0 | V74: =SUM(R74:U74) -> 0 | AP74: =SUM(AD74:AO74) -> 0
B75: Bluevine | N75: 69541 | R75: =SUM(AD75:AF75) -> 29552 | S75: =SUM(AG75:AI75) -> 9448 | T75: =SUM(AJ75:AL75) -> 0 | U75: =SUM(AM75:AO75) -> 0 | V75: =SUM(R75:U75) -> 39000 | AA75: 28007 | AB75: 23286 | AC75: 18248 | AD75: 15342 | AE75: 10668 | AF75: 3542 | AG75: =1181*4 -> 4724 | AH75: =1181*4 -> 4724 | AP75: =SUM(AD75:AO75) -> 39000
B76: Jeremiah reimbursements | N76: 25252 | R76: =SUM(AD76:AF76) -> 11131 | S76: =SUM(AG76:AI76) -> -27192 | T76: =SUM(AJ76:AL76) -> 6626 | U76: =SUM(AM76:AO76) -> 0 | V76: =SUM(R76:U76) -> -9435 | AA76: 2834 | AC76: 22418 | AD76: 14150 | AE76: =AD130-AE130 -> -261 | AF76: =AE130-AF130 -> -2758 | AG76: =AF130-AG130 -> -19492 | AH76: =AG130-AH130 -> -8100 | AI76: =AH130-AI130 -> 400 | AJ76: =AI130-AJ130 -> 6626 | AP76: =SUM(AD76:AO76) -> -9435
B77: Forward Financing | R77: =SUM(AD77:AF77) -> 1512 | S77: =SUM(AG77:AI77) -> 23436 | T77: =SUM(AJ77:AL77) -> 22193 | U77: =SUM(AM77:AO77) -> 13238 | V77: =SUM(R77:U77) -> 60379 | AE77: =AD131-AE131 -> 0 | AF77: 1512 | AG77: 8316 | AH77: 7938 | AI77: 7182 | AJ77: 5939 | AK77: 8316 | AL77: 7938 | AM77: 7938 | AN77: 5300 | AP77: =SUM(AD77:AO77) -> 60379
B78: Everest | AJ78: 4713 | AK78: 4956 | AL78: 4956 | AM78: 4956 | AN78: 4956
B79: Fundbox | N79: 6921 | R79: =SUM(AD79:AF79) -> 13228 | S79: =SUM(AG79:AI79) -> 7605 | T79: =SUM(AJ79:AL79) -> 0 | U79: =SUM(AM79:AO79) -> 0 | V79: =SUM(R79:U79) -> 20833 | AB79: 2273 | AC79: 4648 | AD79: 5689 | AE79: 5783 | AF79: 1756 | AG79: =585*4 -> 2340 | AH79: 2925 | AI79: =585*4 -> 2340 | AP79: =SUM(AD79:AO79) -> 20833
B80: Funding Circle | N80: 8924 | R80: =SUM(AD80:AF80) -> 9262 | S80: =SUM(AG80:AI80) -> 10261 | T80: =SUM(AJ80:AL80) -> 10424 | U80: =SUM(AM80:AO80) -> 11439 | V80: =SUM(R80:U80) -> 41386 | AA80: 2938 | AB80: 2974 | AC80: 3012 | AD80: 3049 | AE80: 6213 | AF80: 0 | AG80: 3813 | AH80: 3204 | AI80: 3244 | AJ80: 3285 | AK80: 3326 | AL80: 3813 | AM80: 3813 | AN80: 3813 | AO80: 3813 | AP80: =SUM(AD80:AO80) -> 41386
B81: Parafin | N81: 11388 | R81: =SUM(AD81:AF81) -> 8608 | S81: =SUM(AG81:AI81) -> 4806 | T81: =SUM(AJ81:AL81) -> 2823 | U81: =SUM(AM81:AO81) -> 1000 | V81: =SUM(R81:U81) -> 17237 | AA81: 5486 | AB81: 3617 | AC81: 2285 | AD81: 3580 | AE81: 1973 | AF81: 3055 | AG81: 3000 | AH81: 896 | AI81: 910 | AJ81: 968 | AK81: 855 | AL81: 1000 | AM81: 1000 | AP81: =SUM(AD81:AO81) -> 17237
B82: QB | N82: 11585 | R82: =SUM(AD82:AF82) -> 1680 | S82: =SUM(AG82:AI82) -> 3830 | T82: =SUM(AJ82:AL82) -> 2150 | U82: =SUM(AM82:AO82) -> 1075 | V82: =SUM(R82:U82) -> 8735 | AA82: 3853 | AB82: 3888 | AC82: 3844 | AE82: 1680 | AF82: 0 | AG82: 1680 | AH82: 1075 | AI82: 1075 | AJ82: 0 | AK82: 1075 | AL82: 1075 | AM82: 1075 | AP82: =SUM(AD82:AO82) -> 8735
B83: Shopify | N83: 5624 | R83: =SUM(AD83:AF83) -> 1704 | S83: =SUM(AG83:AI83) -> 1357 | T83: =SUM(AJ83:AL83) -> 3229 | U83: =SUM(AM83:AO83) -> 1500 | V83: =SUM(R83:U83) -> 7790 | AA83: 954 | AB83: 2558 | AC83: 2112 | AD83: 639 | AE83: 611 | AF83: 454 | AG83: 400 | AH83: 554 | AI83: 403 | AJ83: 1668 | AK83: 1061 | AL83: 500 | AM83: 500 | AN83: 500 | AO83: 500 | AP83: =SUM(AD83:AO83) -> 7790
B84: Amazon | N84: 17603 | R84: =SUM(AD84:AF84) -> 17142 | S84: =SUM(AG84:AI84) -> 17388 | T84: =SUM(AJ84:AL84) -> 6481 | U84: =SUM(AM84:AO84) -> 0 | V84: =SUM(R84:U84) -> 41011 | AA84: 5984 | AB84: 3433 | AC84: 8186 | AD84: 3164 | AE84: 6111 | AF84: 7867 | AG84: 5635 | AH84: 4866 | AI84: 6887 | AJ84: 3310 | AK84: 3171 | AP84: =SUM(AD84:AO84) -> 41011
R85: =SUM(AD85:AF85) -> 0 | S85: =SUM(AG85:AI85) -> 0 | T85: =SUM(AJ85:AL85) -> 0 | U85: =SUM(AM85:AO85) -> 0 | V85: =SUM(R85:U85) -> 0 | AP85: =SUM(AD85:AO85) -> 0
B86: Interest | C86: =QB!F99 -> 10146.97 | D86: =C86/C$15 -> 0.0079219429 | E86: =QB!K99 -> 2481.65 | F86: =E86/E$15 -> 0.0011440102 | G86: =QB!P99 -> 8155.74 | H86: =G86/G$15 -> 0.0037039607 | I86: =SUM(#REF!) -> #REF! | J86: =I86/I$15 -> #REF! | K86: =I86*0.9/4 -> #REF! | L86: =K86 -> #REF! | M86: =L86 -> #REF! | R86: =SUM(AD86:AF86) -> -6480 | S86: =SUM(AG86:AI86) -> -5871 | T86: =SUM(AJ86:AL86) -> -4415 | U86: =SUM(AM86:AO86) -> 100 | V86: =SUM(R86:U86) -> -16666 | Z86: 15052 | AD86: =1200-AD67 -> -2599 | AE86: =1200-AE67 -> -2409 | AF86: =1200-AF67 -> -1472 | AG86: =1200-AG67 -> -3913 | AH86: =1200-AH67 -> -1117 | AI86: =-AI67 -> -841 | AJ86: =-AJ67 -> -1310 | AK86: =1200-AK67 -> -2305 | AL86: =1200-AL67 -> -800 | AM86: =1200-AM67 -> -300 | AN86: =1200-AN67 -> 200 | AO86: =1200-AO67 -> 200 | AP86: =SUM(AD86:AO86) -> -16666 | AR86: Included above
B87: Total debt service | N87: =SUM(N73:N86) -> 175585 | R87: =SUM(R73:R86) -> 115809 | S87: =SUM(S73:S86) -> 69409 | T87: =SUM(T73:T86) -> 66505 | U87: =SUM(U73:U86) -> 48347 | V87: =SUM(V73:V86) -> 300070 | Z87: =SUM(Z73:Z86) -> 15052 | AA87: =SUM(AA73:AA86) -> 65507 | AB87: =SUM(AB73:AB86) -> 43856.3 | AC87: =SUM(AC73:AC86) -> 66221.7 | AD87: =SUM(AD73:AD86) -> 70422 | AE87: =SUM(AE73:AE86) -> 28950 | AF87: =SUM(AF73:AF86) -> 16437 | AG87: =SUM(AG73:AG86) -> 7512 | ... AP87: =SUM(AP73:AP86) -> 300070
A88: Cash Flow after Debt Service | N88: =N71-N87 -> -225345 | R88: =R71-R87 -> -231062 | S88: =S71-S87 -> -130680 | T88: =T71-T87 -> -109399.92 | U88: =U71-U87 -> -80155.76 | V88: =V71-V87 -> -551297.68 | AA88: =AA71-AA87 -> -68616 | AB88: =AB71-AB87 -> -77865.3 | AC88: =AC71-AC87 -> -79569.7 | AD88: =AD71-AD87 -> -118843 | AE88: =AE71-AE87 -> -64505 | AF88: =AF71-AF87 -> -47714 | AG88: =AG71-AG87 -> -70711 | AH88: =AH71-AH87 -> -44807 | ... AP88: =AP71-AP87 -> -551297.68
A89: Working Capital Fluctuation | N89: 83009 | R89: =SUM(AD89:AF89) -> 40288 | S89: =SUM(AG89:AI89) -> 113133 | T89: =SUM(AJ89:AL89) -> 16726 | U89: =SUM(AM89:AO89) -> 0 | V89: =SUM(R89:U89) -> 170147 | AA89: 12964 | AB89: 22340 | AC89: 48625 | AD89: -51185 | AE89: 65201 | AF89: 26272 | AG89: 52504 | AH89: 46489 | AI89: 14140 | AJ89: 16726 | AP89: =SUM(AD89:AO89) -> 170147
A90: Investment/Borrowing | N90: 296440 | R90: =SUM(AD90:AF90) -> 40950 | S90: =SUM(AG90:AI90) -> 0 | T90: =SUM(AJ90:AL90) -> 22275 | U90: =SUM(AM90:AO90) -> 0 | V90: =SUM(R90:U90) -> 63225 | AA90: 48000 | AB90: =14000+25000 -> 39000 | AC90: 209440 | AF90: 40950 | AJ90: 17275 | AL90: 5000 | AP90: =SUM(AD90:AO90) -> 63225
A91: Net Cash Flow | C91: =C71-#REF!-C86-C90 -> #REF! | D91: =C91/C$15 -> #REF! | E91: =E71-#REF!-E86-E90 -> #REF! | F91: =E91/E$15 -> #REF! | G91: =G71-#REF!-G86-G90 -> #REF! | H91: =G91/G$15 -> #REF! | I91: =I71-#REF!-I86-I90 -> #REF! | J91: =I91/I$15 -> #REF! | K91: =K71-#REF!-K86-K90 -> #REF! | L91: =L71-#REF!-L86-L90 -> #REF! | M91: =M71-#REF!-M86-M90 -> #REF! | N91: =SUM(N88:N90) -> 154104 | R91: =SUM(R88:R90) -> -149824 | S91: =SUM(S88:S90) -> -17547 | T91: =SUM(T88:T90) -> -70398.92 | U91: =SUM(U88:U90) -> -80155.76 | V91: =SUM(V88:V90) -> -317925.68 | Z91: =Z71-Z87-Z90 -> -185259 | AA91: =SUM(AA88:AA90) -> -7652 | AB91: =SUM(AB88:AB90) -> -16525.3 | AC91: =SUM(AC88:AC90) -> 178495.3 | AD91: =SUM(AD88:AD90) -> -170028 | AE91: =SUM(AE88:AE90) -> 696 | AF91: =SUM(AF88:AF90) -> 19508 | AG91: =SUM(AG88:AG90) -> -18207 | AH91: =SUM(AH88:AH90) -> 1682 | ... AP91: =SUM(AP88:AP90) -> -317925.68
A92: Cash, Beginning of Month | N92: 12057 | R92: =AD92 -> 166376 | S92: =R119 -> 16552 | T92: =S119 -> -995 | U92: =T119 -> -71393.92 | V92: =R92 -> 166376 | AA92: 12057 | AB92: 4406 | AC92: =AB119 -> -12119.3 | AD92: 166376 | AE92: =AD119 -> -3652 | AF92: =AE119 -> -2956 | AG92: =AF119 -> 16552 | AH92: =AG119 -> -1655 | AI92: =AH119 -> 27 | AJ92: =AI119 -> -995 | AK92: =AJ119 -> -590 | AL92: =AK119 -> -55239 | ... AO92: =AN119 -> -153695.76 | AP92: =AD92 -> 166376
A93: ASSUMPTIONS
B94: Growth
B95: Retail
B96: Online
B97: Distributor
B98: Franchise
B99: Marg/spices
B100: Cost of co-packer/ingredients
B101: Retail | K101: 0.38 | L101: 0.38 | M101: 0.38 | N101: 0.38 | O101: 0.38 | R101: 0.38 | S101: 0.38 | T101: 0.38 | V101: 0.38 | Z101: 0.38 | AP101: 0.38
B102: Online | K102: 0.38 | L102: 0.38 | M102: 0.38 | N102: 0.38 | O102: 0.38 | R102: 0.38 | S102: 0.38 | T102: 0.38 | V102: 0.38 | Z102: 0.38 | AP102: 0.38
...

Sheet 2024 Monthly
A1: Bravado Spice
A2: Budget Worksheet | AE2: Actual
I3: 2022 | P3: 2023 Forecast (Original) | X3: 2024 (Updated 3/11/24)
C4: 2019 | E4: 2020 | G4: 2021 | I4: Q1 | J4: Q2 | K4: Q3 | L4: Q4 Proj | M4: 2022 | O4: Qtr Run Rate | P4: Q1 | Q4: Q2 | R4: Q3 | S4: Q4 | T4: 2023 | V4: Notes | X4: Q1 Actual | Y4: Q2 Actual | Z4: Q3 Actual | AA4: Oct | AB4: Nov | AC4: Dec | AE4: Jan | AF4: Feb | AG4: Mar | AH4: Apr | AI4: May | AJ4: June | AK4: July | AL4: Aug | AM4: Sept | AN4: Oct | AO4: Nov | AP4: Dec | AQ4: 2024 Total | AS4: Assumptions | AT4: Original Notes
A5: Sales
B6: Retail | I6: ='Sales by Segment'!C38 -> 67876.69 | J6: ='Sales by Segment'!E38 -> 65982 | K6: ='Sales by Segment'!G38 -> 55994 | L6: ='Sales by Segment'!K38 -> 40887.67 | M6: =SUM(I6:L6) -> 230740.36 | N6: =M6/M$14 -> 0.099200782 | P6: ='Sales by Segment'!O38 -> 48455.476 | Q6: ='Sales by Segment'!P38 -> 53301.023 | R6: ='Sales by Segment'!Q38 -> 55723.797 | S6: ='Sales by Segment'!R38 -> 84797.082 | T6: ='Sales by Segment'!S38 -> 242277.38 | U6: =T6/T$14 -> 0.077380649 | X6: ='Sales by Segment'!T38 -> 38264 | Y6: 55790 | AQ6: =SUM(AE6:AP6) -> 0 | AR6: =AQ6/AQ$14 -> 0
B7: Online/Amazon | I7: ='Sales by Segment'!C40 -> 108870 | J7: ='Sales by Segment'!E40 -> 94874 | K7: ='Sales by Segment'!G40 -> 100895 | L7: ='Sales by Segment'!K40 -> 132530 | M7: =SUM(I7:L7) -> 437169 | N7: =M7/M$14 -> 0.18794938 | P7: ='Sales by Segment'!O40 -> 120000 | Q7: ='Sales by Segment'!P40 -> 100000 | R7: ='Sales by Segment'!Q40 -> 154000 | S7: ='Sales by Segment'!R40 -> 242000 | T7: ='Sales by Segment'!S40 -> 600000 | U7: =T7/T$14 -> 0.1916332 | X7: ='Sales by Segment'!T40 -> 89837 | Y7: ='Sales by Segment'!U40 -> 78100 | AQ7: =SUM(AE7:AP7) -> 0 | AR7: =AQ7/AQ$14 -> 0
B8: Less Amazon netting | AQ8: =SUM(AE8:AP8) -> 0 | AR8: =AQ8/AQ$14 -> 0
B9: Distributor | I9: ='Sales by Segment'!C22 -> 115641 | J9: ='Sales by Segment'!E22 -> 109617 | K9: ='Sales by Segment'!G22 -> 76149 | L9: ='Sales by Segment'!K22 -> 136365 | M9: =SUM(I9:L9) -> 437772 | N9: =M9/M$14 -> 0.18820862 | P9: ='Sales by Segment'!O22 -> 106256.68 | Q9: ='Sales by Segment'!P22 -> 182882.35 | R9: ='Sales by Segment'!Q22 -> 182445.18 | S9: ='Sales by Segment'!R22 -> 269699.19 | T9: ='Sales by Segment'!S22 -> 741283.4 | U9: =T9/T$14 -> 0.23675752 | X9: ='Sales by Segment'!T22 -> 164797 | Y9: ='Sales by Segment'!U22 -> 124694 | AQ9: =SUM(AE9:AP9) -> 0 | AR9: =AQ9/AQ$14 -> 0
B10: Franchise | I10: ='Sales by Segment'!C35 -> 308016 | J10: ='Sales by Segment'!E35 -> 156713 | K10: ='Sales by Segment'!G35 -> 304392 | L10: ='Sales by Segment'!K35 -> 451191 | M10: =SUM(I10:L10) -> 1220312 | N10: =M10/M$14 -> 0.52464122 | P10: ='Sales by Segment'!O35 -> 332584.14 | Q10: ='Sales by Segment'!P35 -> 293142.55 | R10: ='Sales by Segment'!Q35 -> 388171.76 | S10: ='Sales by Segment'!R35 -> 533522.24 | T10: ='Sales by Segment'!S35 -> 1547420.7 | U10: =T10/T$14 -> 0.49422863 | X10: ='Sales by Segment'!T35 -> 277143 | Y10: ='Sales by Segment'!U35 -> 146688 | AQ10: =SUM(AE10:AP10) -> 0 | AR10: =AQ10/AQ$14 -> 0
B11: Total hot sauce | C11: =QB!F20+QB!F30+QB!F33+QB!F34+QB!F40 -> 1176162.1 | E11: =QB!K20+QB!K30+QB!K33+QB!K34+QB!K40 -> 1985300.7 | G11: =QB!P20+QB!P30+QB!P33+QB!P34+QB!P40 -> 1946199.2
B12: Mixers & seasonings | C12: =QB!F24+QB!F29 -> 98761.52 | E12: =QB!K24+QB!K29 -> 182871.54 | G12: =QB!P24+QB!P29 -> 249354.5
B13: Other | C13: =QB!F42+QB!F43+QB!F44 -> 5945.28 | E13: =QB!K42+QB!K43+QB!K44 -> 1082.89 | G13: =QB!P42+QB!P43+QB!P44 -> 6343.26
B14: Total sales | C14: =SUM(C11:C13) -> 1280868.9 | D14: =C14/C$14 -> 1 | E14: =SUM(E11:E13) -> 2169255.1 | F14: =E14/E$14 -> 1 | G14: =SUM(G11:G13) -> 2201897 | H14: =G14/G$14 -> 1 | I14: =SUM(I6:I10) -> 600403.69 | J14: =SUM(J6:J10) -> 427186 | K14: =SUM(K6:K10) -> 537430 | L14: =SUM(L6:L10) -> 760973.67 | M14: =SUM(M6:M10) -> 2325993.4 | N14: =M14/M$14 -> 1 | O14: =K14 -> 537430 | P14: =SUM(P6:P10) -> 607296.3 | Q14: =SUM(Q6:Q10) -> 629325.93 | R14: =SUM(R6:R10) -> 780340.74 | S14: =SUM(S6:S10) -> 1130018.5 | T14: =SUM(T6:T10) -> 3130981.5 | U14: =T14/T$14 -> 1 | X14: =SUM(X6:X10) -> 570041 | Y14: 405174 | Z14: 347143 | AA14: 155912 | AB14: 147384 | AC14: 129065 | AE14: 104120 | AF14: 82917 | AG14: 100000 | AH14: 200000 | AI14: 200000 | AJ14: 200000 | AK14: 230000 | AL14: 230000 | AM14: 240000 | AN14: 225000 | AO14: 230000 | AP14: 230000 | AQ14: =SUM(AE14:AP14) -> 2272037 | AR14: =AQ14/AQ$14 -> 1 | AS14: TBD
A15: Cost of Sales
B16: Co-Packer & ingredients | C16: =QB!F47+QB!F48+QB!F50+QB!F51 -> 497738.93 | D16: =C16/C$14 -> 0.38859476 | E16: =QB!K47+QB!K48+QB!K50+QB!K51 -> 668009.87 | F16: =E16/E$14 -> 0.30794435 | G16: =QB!P47+QB!P48+QB!P50+QB!P51 -> 943998.9 | H16: =G16/G$14 -> 0.42872073 | I16: =QB!Q47+QB!Q48+QB!Q50+QB!Q51 -> 296571.87 | J16: =QB!R47+QB!R48+QB!R50+QB!R51 -> 170635.73 | K16: =QB!S47+QB!S48+QB!S50+QB!S51 -> 195667.65 | L16: =QB!T47+QB!T48+QB!T50+QB!T51 -> 349942.37 | M16: =SUM(I16:L16) -> 1012817.6 | N16: =M16/M$14 -> 0.43543444 | P16: =(P6*P97)+(P7*P98)+(P9*P99)+(P10*P100) -> 259090.03 | Q16: =(Q6*Q97)+(Q7*Q98)+(Q9*Q99)+(Q10*Q100) -> 273918.04 | R16: =(R6*R97)+(R7*R98)+(R9*R99)+(R10*R100) -> 336007.04 | S16: =(S6*S97)+(S7*S98)+(S9*S99)+(S10*S100) -> 485750.06 | T16: =SUM(P16:S16) -> 1354765.2 | U16: =T16/T$14 -> 0.43269664 | V16: margin assumptions below | X16: 342783 | Y16: 182623 | Z16: 199547 | AA16: 51354 | AB16: 56556 | AC16: 54070 | AE16: 35127 | AF16: 27875 | AG16: =AG14*0.4 -> 40000 | AH16: =AH14*0.4 -> 80000 | AI16: =AI14*0.4 -> 80000 | AJ16: =AJ14*0.4 -> 80000 | AK16: =AK14*0.4 -> 92000 | AL16: =AL14*0.4 -> 92000 | AM16: =AM14*0.4 -> 96000 | AN16: =AN14*0.4 -> 90000 | ... AP16: =AP14*0.4 -> 92000 | AQ16: =SUM(AE16:AP16) -> 897002 | AR16: =AQ16/AQ$14 -> 0.39480079 | AS16: 40% of sales
B17: Shipping & delivery | C17: =QB!F49 -> 115308.88 | D17: =C17/C$14 -> 0.090023954 | E17: =QB!K49 -> 198278.67 | F17: =E17/E$14 -> 0.091404034 | G17: =QB!P49 -> 268052.97 | H17: =G17/G$14 -> 0.12173729 | I17: =QB!Q49 -> 51915.66 | J17: =QB!R49 -> 50350.69 | K17: =QB!S49 -> 44278.39 | L17: =QB!T49 -> 68459.79 | M17: =SUM(I17:L17) -> 215004.53 | N17: =M17/M$14 -> 0.092435573 | P17: =P14*0.09 -> 54656.667 | Q17: =Q14*0.09 -> 56639.333 | R17: =R14*0.09 -> 70230.667 | S17: =S14*0.09 -> 101701.67 | T17: =SUM(P17:S17) -> 283228.33 | U17: =T17/T$14 -> 0.09045992 | V17: 9% of sales | X17: 46962 | Y17: 32407 | Z17: 27976 | AA17: 8573 | AB17: 10446 | AC17: 8139 | AE17: 8646 | AF17: 5159 | AG17: =0.07*AG14 -> 7000 | AH17: =0.07*AH14 -> 14000 | AI17: =0.07*AI14 -> 14000 | AJ17: =0.07*AJ14 -> 14000 | AK17: =0.07*AK14 -> 16100 | AL17: =0.07*AL14 -> 16100 | AM17: =0.07*AM14 -> 16800 | AN17: =0.07*AN14 -> 15750 | ... AP17: =0.07*AP14 -> 16100 | AQ17: =SUM(AE17:AP17) -> 159755 | AR17: =AQ17/AQ$14 -> 0.070313556 | AS17: 7% of sales
B18: Inventory adjustment | AE18: 6900 | AF18: -2315 | AQ18: =SUM(AE18:AP18) -> 4585
B19: Materials | C19: =QB!F52 -> 128054.04 | D19: =C19/C$14 -> 0.099974356 | E19: =QB!K52 -> 194413.35 | F19: =E19/E$14 -> 0.089622169 | G19: =QB!P52 -> 179567.31 | H19: =G19/G$14 -> 0.081551185 | I19: =QB!Q52 -> 0 | J19: =QB!R52 -> 0 | K19: =QB!S52 -> 0 | L19: =QB!T52 -> 0 | M19: =SUM(I19:L19) -> 0 | N19: =M19/M$14 -> 0 | P19: =SUM(L19:O19) -> 0 | Q19: =SUM(M19:P19) -> 0 | R19: =SUM(N19:Q19) -> 0 | S19: =SUM(O19:R19) -> 0 | T19: =SUM(P19:S19) -> 0 | U19: =T19/T$14 -> 0 | X19: =SUM(T19:V19) -> 0 | AQ19: =SUM(AE19:AP19) -> 0 | AR19: =AQ19/AQ$14 -> 0
B20: KeHe slotting fees | AQ20: =SUM(AE20:AP20) -> 0
A21: ? | B21: Swell/other discounts | X21: 25860 | Y21: 17408 | Z21: 52288 | AA21: 20454 | AB21: 12986 | AC21: 2493 | AE21: 17155 | AF21: 16557 | AG21: =AG14*0.08 -> 8000 | AH21: =AH14*0.08 -> 16000 | AI21: =AI14*0.08 -> 16000 | AJ21: =AJ14*0.08 -> 16000 | AK21: =AK14*0.08 -> 18400 | AL21: =AL14*0.08 -> 18400 | AM21: =AM14*0.08 -> 19200 | AN21: =AN14*0.08 -> 18000 | ... AP21: =AP14*0.08 -> 18400 | AQ21: =SUM(AE21:AP21) -> 200512 | AS21: 8% of sales
A22: ? | B22: Other | C22: =QB!F53+QB!F54+QB!F55+QB!F56+QB!F57+QB!F58+QB!F59+QB!F60+QB!F61+QB!F62+QB!F64 -> 25822.27 | D22: =C22/C$14 -> 0.020159964 | E22: =QB!K53+QB!K54+QB!K55+QB!K56+QB!K57+QB!K58+QB!K59+QB!K60+QB!K61+QB!K62+QB!K64 -> 154060.7 | F22: =E22/E$14 -> 0.071020092 | G22: =QB!P53+QB!P54+QB!P55+QB!P56+QB!P57+QB!P58+QB!P59+QB!P60+QB!P61+QB!P62+QB!P64 -> 76433.53 | H22: =G22/G$14 -> 0.034712582 | I22: =QB!Q53+QB!Q54+QB!Q55+QB!Q56+QB!Q57+QB!Q58+QB!Q59+QB!Q60+QB!Q61+QB!Q62+QB!Q64 -> 15108.43 | J22: =QB!R53+QB!R54+QB!R55+QB!R56+QB!R57+QB!R58+QB!R59+QB!R60+QB!R61+QB!R62+QB!R64 -> 25808.14 | K22: =QB!S53+QB!S54+QB!S55+QB!S56+QB!S57+QB!S58+QB!S59+QB!S60+QB!S61+QB!S62+QB!S64 -> 15454.42 | L22: =QB!T53+QB!T54+QB!T55+QB!T56+QB!T57+QB!T58+QB!T59+QB!T60+QB!T61+QB!T62+QB!T64 -> 27571.25 | M22: =SUM(I22:L22) -> 83942.24 | N22: =M22/M$14 -> 0.03608877 | P22: =P14*0.03 -> 18218.889 | Q22: =Q14*0.03 -> 18879.778 | R22: =R14*0.03 -> 23410.222 | S22: =S14*0.03 -> 33900.556 | T22: =SUM(P22:S22) -> 94409.444 | U22: =T22/T$14 -> 0.030153307 | V22: 3% of sales | Y22: 31200 | Z22: 29434 | AA22: 10167 | AB22: 6575 | AC22: 9120 | AE22: 1408 | AF22: 281 | AG22: =AG14*0.02 -> 2000 | AH22: =AH14*0.02 -> 4000 | AI22: =AI14*0.02 -> 4000 | AJ22: =AJ14*0.02 -> 4000 | AK22: =AK14*0.02 -> 4600 | AL22: =AL14*0.02 -> 4600 | AM22: =AM14*0.02 -> 4800 | AN22: =AN14*0.02 -> 4500 | ... AP22: =AP14*0.02 -> 4600 | AQ22: =SUM(AE22:AP22) -> 43389 | AR22: =AQ22/AQ$14 -> 0.01909696 | AS22: 2% of sales
B23: Total CGS | C23: =SUM(C16:C22) -> 766924.12 | D23: =C23/C$14 -> 0.59875303 | E23: =SUM(E16:E22) -> 1214762.6 | F23: =E23/E$14 -> 0.55999065 | G23: =SUM(G16:G22) -> 1468052.7 | H23: =G23/G$14 -> 0.66672179 | I23: =SUM(I16:I22) -> 363595.96 | J23: =SUM(J16:J22) -> 246794.56 | K23: =SUM(K16:K22) -> 255400.46 | L23: =SUM(L16:L22) -> 445973.41 | M23: =SUM(M16:M22) -> 1311764.4 | N23: =M23/M$14 -> 0.56395879 | O23: =K23 -> 255400.46 | P23: =SUM(P16:P22) -> 331965.59 | Q23: =SUM(Q16:Q22) -> 349437.15 | R23: =SUM(R16:R22) -> 429647.93 | S23: =SUM(S16:S22) -> 621352.28 | T23: =SUM(T16:T22) -> 1732402.9 | U23: =T23/T$14 -> 0.55330987 | X23: =SUM(X16:X22) -> 415605 | Y23: =SUM(Y16:Y22) -> 263638 | Z23: =SUM(Z16:Z22) -> 309245 | AA23: =SUM(AA16:AA22) -> 90548 | AB23: =SUM(AB16:AB22) -> 86563 | AC23: =SUM(AC16:AC22) -> 73822 | AE23: =SUM(AE16:AE22) -> 69236 | AF23: =SUM(AF16:AF22) -> 47557 | AG23: =SUM(AG16:AG22) -> 57000 | AH23: =SUM(AH16:AH22) -> 114000 | AI23: =SUM(AI16:AI22) -> 114000 | AJ23: =SUM(AJ16:AJ22) -> 114000 | AK23: =SUM(AK16:AK22) -> 131100 | AL23: =SUM(AL16:AL22) -> 131100 | ... AQ23: =SUM(AQ16:AQ22) -> 1305243 | AR23: =AQ23/AQ$14 -> 0.5744814
A24: Gross Margin | C24: =C14-C23 -> 513944.75 | D24: =C24/C$14 -> 0.40124697 | E24: =E14-E23 -> 954492.55 | F24: =E24/E$14 -> 0.44000935 | G24: =G14-G23 -> 733844.3 | H24: =G24/G$14 -> 0.33327821 | I24: =I14-I23 -> 236807.73 | J24: =J14-J23 -> 180391.44 | K24: =K14-K23 -> 282029.54 | L24: =L14-L23 -> 315000.26 | M24: =M14-M23 -> 1014229 | N24: =M24/M$14 -> 0.43604121 | O24: =O14*0.41 -> 220346.3 | P24: =P14-P23 -> 275330.71 | Q24: =Q14-Q23 -> 279888.78 | R24: =R14-R23 -> 350692.81 | S24: =S14-S23 -> 508666.24 | T24: =T14-T23 -> 1398578.5 | U24: =T24/T$14 -> 0.44669013 | X24: =X14-X23 -> 154436 | Y24: =Y14-Y23 -> 141536 | Z24: =Z14-Z23 -> 37898 | AA24: =AA14-AA23 -> 65364 | AB24: =AB14-AB23 -> 60821 | AC24: =AC14-AC23 -> 55243 | AE24: =AE14-AE23 -> 34884 | AF24: =AF14-AF23 -> 35360 | AG24: =AG14-AG23 -> 43000 | AH24: =AH14-AH23 -> 86000 | AI24: =AI14-AI23 -> 86000 | AJ24: =AJ14-AJ23 -> 86000 | AK24: =AK14-AK23 -> 98900 | AL24: =AL14-AL23 -> 98900 | ... AQ24: =AQ14-AQ23 -> 966794 | AR24: =AQ24/AQ$14 -> 0.4255186
X25: =X24/X14 -> 0.27092086 | Y25: =Y24/Y14 -> 0.34932153 | Z25: =Z24/Z14 -> 0.10917115 | AA25: =AA24/AA14 -> 0.41923649 | AB25: =AB24/AB14 -> 0.4126703 | AC25: =AC24/AC14 -> 0.42802464 | AE25: =AE24/AE14 -> 0.3350365 | AF25: =AF24/AF14 -> 0.42645055
A26: Selling, General & Administrative
B27: Compensation | AU27: starting Feb
B28: Salaries & wages | C28: =QB!F110 -> 0 | D28: =C28/C$14 -> 0 | E28: =QB!K110 -> 216764.24 | F28: =E28/E$14 -> 0.099925655 | G28: =QB!P110 -> 391277.16 | H28: =G28/G$14 -> 0.17770003 | I28: =QB!Q110 -> 91276.55 | J28: =QB!R110 -> 84874.36 | K28: =QB!S110 -> 114609.99 | L28: =QB!T110 -> 119543.86 | M28: =SUM(I28:L28) -> 410304.76 | N28: =M28/M$14 -> 0.1763998 | O28: =Payroll!F17*6 -> 126618 | P28: =Payroll!P17 -> 126618 | Q28: =Payroll!Q17 -> 126618 | R28: =Payroll!R17 -> 135718 | S28: =Payroll!S17 -> 135718 | T28: =SUM(P28:S28) -> 524672 | U28: =T28/T$14 -> 0.16757429 | V28: payroll sheet | X28: 113695 | Y28: 113361 | Z28: 88012 | AA28: 32685 | AB28: 24892 | AC28: 22267 | AE28: =SUM(AE29:AE34) -> 26285 | AF28: =SUM(AF29:AF34) -> 19282 | AG28: =SUM(AG29:AG34) -> 18974 | AH28: =SUM(AH29:AH34) -> 18974 | AI28: =SUM(AI29:AI34) -> 18974 | AJ28: =SUM(AJ29:AJ34) -> 18974 | AK28: =SUM(AK29:AK34) -> 18974 | AL28: =SUM(AL29:AL34) -> 18974 | ... AP28: =SUM(AP29:AP34) -> 18974 | AQ28: =SUM(AE28:AP28) -> 235307 | AR28: =AQ28/AQ$14 -> 0.10356654
B29: Spencer | AB29: =$AS29*2 -> 4744 | AC29: =$AS29*2 -> 4744 | AE29: =$AS29*2 -> 4744 | AF29: 1313 | AS29: 2372
B30: Ryan (Kristopher) | AB30: =$AS30*2 -> 5000 | AC30: =$AS30*2 -> 5000 | AE30: =$AS30*2 -> 5000 | AF30: =$AS30*2 -> 5000 | AS30: 2500
B31: Levi | AB31: =$AS31*2 -> 4574 | AC31: =$AS31*2 -> 4574 | AE31: 4416 | AF31: 4468 | AG31: =$AS31*2 -> 4574 | AH31: =$AS31*2 -> 4574 | AI31: =$AS31*2 -> 4574 | AJ31: =$AS31*2 -> 4574 | AK31: =$AS31*2 -> 4574 | AL31: =$AS31*2 -> 4574 | AM31: =$AS31*2 -> 4574 | AN31: =$AS31*2 -> 4574 | ... AP31: =$AS31*2 -> 4574 | AS31: 2287
B32: McKenna | AB32: =$AS32*2 -> 1834 | AC32: =$AS32*2 -> 1834 | AE32: 1834 | AF32: 1834 | AG32: =$AU32*2 -> 2400 | AH32: =$AU32*2 -> 2400 | AI32: =$AU32*2 -> 2400 | AJ32: =$AU32*2 -> 2400 | AK32: =$AU32*2 -> 2400 | AL32: =$AU32*2 -> 2400 | AM32: =$AU32*2 -> 2400 | AN32: =$AU32*2 -> 2400 | ... AP32: =$AU32*2 -> 2400 | AS32: 917 | AU32: 1200
B33: Marisa | AB33: =$AS33*2 -> 2490 | AC33: =$AS33*AC$138 -> 2490 | AE33: 6666 | AF33: 6667 | AG33: =$AU33*2 -> 5000 | AH33: 5000 | AI33: 5000 | AJ33: 5000 | AK33: 5000 | AL33: 5000 | AM33: 5000 | AN33: 5000 | AO33: 5000 | AP33: 5000 | AS33: 1245 | AU33: 2500
B34: Jeremiah | AB34: =$AS34*2 -> 7000 | AC34: =$AS34*2 -> 7000 | AE34: 3625 | AF34: 0 | AG34: =$AS34*2 -> 7000 | AH34: =$AS34*2 -> 7000 | AI34: =$AS34*2 -> 7000 | AJ34: =$AS34*2 -> 7000 | AK34: =$AS34*2 -> 7000 | AL34: =$AS34*2 -> 7000 | AM34: =$AS34*2 -> 7000 | AN34: =$AS34*2 -> 7000 | ... AP34: =$AS34*2 -> 7000 | AS34: 3500
B35: Contract labor | C35: =QB!F108 -> 142452.45 | D35: =C35/C$14 -> 0.11121548 | E35: =QB!K108 -> 57528.86 | F35: =E35/E$14 -> 0.026520099 | G35: =QB!P108 -> 18232.21 | H35: =G35/G$14 -> 0.0082802283 | I35: =QB!Q108 -> 17026.35 | J35: =QB!R108 -> 19560.25 | K35: =QB!S108 -> 20833.55 | L35: =QB!T108 -> 34645.85 | M35: =SUM(I35:L35) -> 92066 | N35: =M35/M$14 -> 0.039581368 | O35: =Payroll!G31*3 -> 19131 | P35: =Payroll!P34 -> 18381 | Q35: =Payroll!Q34 -> 18881 | R35: =Payroll!R34 -> 12614 | S35: =Payroll!S34 -> 17864 | T35: =SUM(P35:S35) -> 67740 | U35: =T35/T$14 -> 0.021635388 | V35: payroll sheet | X35: 30320 | Y35: 9581 | Z35: 9030 | AA35: 4939 | AB35: 6242 | AC35: 5138 | AE35: =SUM(AE36:AE39) -> 7721 | AF35: =SUM(AF36:AF39) -> 3588 | AG35: =SUM(AG36:AG39) -> 5720 | AH35: =SUM(AH36:AH39) -> 5720 | AI35: =SUM(AI36:AI39) -> 5720 | AJ35: =SUM(AJ36:AJ39) -> 5720 | AK35: =SUM(AK36:AK39) -> 5720 | AL35: =SUM(AL36:AL39) -> 5720 | ... AP35: =SUM(AP36:AP39) -> 5720 | AQ35: =SUM(AE35:AP35) -> 68509 | AR35: =AQ35/AQ$14 -> 0.030153118
B36: Miguel | AB36: 2860 | AC36: 2860 | AE36: 4767 | AF36: 1428 | AG36: 2860 | AH36: 2860 | AI36: 2860 | AJ36: 2860 | AK36: 2860 | AL36: 2860 | AM36: 2860 | AN36: 2860 | AO36: 2860 | AP36: 2860 | AS36: 1430 fulfillment
B37: Robert | AB37: 2860 | AC37: 2860 | AE37: 2954 | AF37: 2160 | AG37: 2860 | AH37: 2860 | AI37: 2860 | AJ37: 2860 | AK37: 2860 | AL37: 2860 | AM37: 2860 | AN37: 2860 | AO37: 2860 | AP37: 2860 | AS37: 1430 sales admin | AU37: 1666
B40: Payroll taxes | C40: =QB!F109 -> 0 | D40: =C40/C$14 -> 0 | E40: =QB!K109 -> 18516.46 | F40: =E40/E$14 -> 0.0085358608 | G40: =QB!P109 -> 32796.35 | H40: =G40/G$14 -> 0.014894589 | I40: =QB!Q109 -> 7854.57 | J40: =QB!R109 -> 5685.44 | K40: =QB!S109 -> 8563.9 | L40: =QB!T109 -> 8924.05 | M40: =SUM(I40:L40) -> 31027.96 | N40: =M40/M$14 -> 0.01333966 | O40: =Payroll!F18*6 -> 9450 | P40: =Payroll!P18 -> 10129.44 | Q40: =Payroll!Q18 -> 10129.44 | R40: =Payroll!R18 -> 10857.44 | S40: =Payroll!S18 -> 10857.44 | T40: =SUM(P40:S40) -> 41973.76 | U40: =T40/T$14 -> 0.013405943 | V40: payroll sheet | X40: 7707 | Y40: 6925 | Z40: 5184 | AA40: 1439 | AB40: 1363 | AC40: 1670 | AE40: 2184 | AF40: 1545 | AG40: =AG28*0.08 -> 1517.92 | AH40: =AH28*0.08 -> 1517.92 | AI40: =AI28*0.08 -> 1517.92 | AJ40: =AJ28*0.08 -> 1517.92 | AK40: =AK28*0.08 -> 1517.92 | AL40: =AL28*0.08 -> 1517.92 | AM40: =AM28*0.08 -> 1517.92 | AN40: =AN28*0.08 -> 1517.92 | ... AP40: =AP28*0.08 -> 1517.92 | AQ40: =SUM(AE40:AP40) -> 18908.2 | AR40: =AQ40/AQ$14 -> 0.0083221356 | AS40: 8% of payroll
B41: Employee benefits | C41: =QB!F104 -> 6974.56 | D41: =C41/C$14 -> 0.0054451788 | E41: =QB!K104 -> 10175.58 | F41: =E41/E$14 -> 0.0046908175 | G41: =QB!P104 -> 2511.54 | H41: =G41/G$14 -> 0.0011406256 | I41: =QB!Q104 -> 4626.48 | J41: =QB!R104 -> 4626.48 | K41: =QB!S104 -> 4626.48 | L41: =QB!T104 -> 3084.32 | M41: =SUM(I41:L41) -> 16963.76 | N41: =M41/M$14 -> 0.0072931249 | O41: =Payroll!F19*6 -> 4626 | P41: =Payroll!P19 -> 4626 | Q41: =Payroll!Q19 -> 4626 | R41: =Payroll!R19 -> 5226 | S41: =Payroll!S19 -> 4626 | T41: =SUM(P41:S41) -> 19104 | U41: =T41/T$14 -> 0.0061016011 | V41: payroll sheet | X41: 3191 | Y41: 3417 | Z41: 3692 | AC41: 4817 | AE41: 270 | AF41: 0 | AG41: 1230 | AH41: 1230 | AI41: 1230 | AJ41: 1230 | AK41: 1230 | AL41: 1230 | AM41: 1230 | AN41: 1230 | AO41: 1230 | AP41: 1230 | AQ41: =SUM(AE41:AP41) -> 12570 | AR41: =AQ41/AQ$14 -> 0.0055324803 | AS41: Trend
B42: Total compensation | C42: =SUM(C28:C41) -> 149427.01 | D42: =C42/C$14 -> 0.11666066 | E42: =SUM(E28:E41) -> 302985.14 | F42: =E42/E$14 -> 0.13967243 | G42: =SUM(G28:G41) -> 444817.26 | H42: =G42/G$14 -> 0.20201547 | I42: =SUM(I28:I41) -> 120783.95 | J42: =SUM(J28:J41) -> 114746.53 | K42: =SUM(K28:K41) -> 148633.92 | L42: =SUM(L28:L41) -> 166198.08 | M42: =SUM(M28:M41) -> 550362.48 | N42: =M42/M$14 -> 0.23661395 | O42: =SUM(O28:O41) -> 159825 | P42: =SUM(P28:P41) -> 159754.44 | Q42: =SUM(Q28:Q41) -> 160254.44 | R42: =SUM(R28:R41) -> 164415.44 | S42: =SUM(S28:S41) -> 169065.44 | T42: =SUM(T28:T41) -> 653489.76 | U42: =T42/T$14 -> 0.20871722 | X42: =SUM(X28:X41) -> 154913 | Y42: =SUM(Y28:Y41) -> 133284 | Z42: =SUM(Z28:Z41) -> 105918 | AA42: =SUM(AA28:AA41) -> 39063 | AB42: =AB28+AB35+AB40+AB41 -> 32497 | AC42: =AC28+AC35+AC40+AC41 -> 33892 | AE42: =AE28+AE35+AE40+AE41 -> 36460 | AF42: =AF28+AF35+AF40+AF41 -> 24415 | AG42: =AG28+AG35+AG40+AG41 -> 27441.92 | AH42: =AH28+AH35+AH40+AH41 -> 27441.92 | AI42: =AI28+AI35+AI40+AI41 -> 27441.92 | AJ42: =AJ28+AJ35+AJ40+AJ41 -> 27441.92 | AK42: =AK28+AK35+AK40+AK41 -> 27441.92 | AL42: =AL28+AL35+AL40+AL41 -> 27441.92 | ... AP42: =AP28+AP35+AP40+AP41 -> 27441.92 | AQ42: =SUM(AQ28:AQ41) -> 335294.2 | AR42: =AQ42/AQ$14 -> 0.14757427
B43: Marketing & advertising | C43: =QB!F80 -> 120088.93 | D43: =C43/C$14 -> 0.093755835 | E43: =QB!K80 -> 126166.54 | F43: =E43/E$14 -> 0.058161227 | G43: =QB!P80 -> 153428.37 | H43: =G43/G$14 -> 0.069680085 | I43: =QB!Q80 -> 30869.34 | J43: =QB!R80 -> 46372.21 | K43: =QB!S80 -> 45966.52 | L43: =QB!T80 -> 59769.5 | M43: =SUM(I43:L43) -> 182977.57 | N43: =M43/M$14 -> 0.07866642 | O43: =(J43+K43)/2 -> 46169.365 | P43: =(7700+6100+8400+3600+11200)+33000 -> 70000 | Q43: =(5600+8700+6100+7900)+33000 -> 61300 | R43: =(10000+8400)+33000 -> 51400 | S43: 33000 | T43: =SUM(P43:S43) -> 215700 | U43: =T43/T$14 -> 0.068892135 | V43: see show schedule + 10% increase in other | X43: 47825 | Y43: 43028 | Z43: 35371 | AA43: -277 | AB43: =SUM(AB44:AB50) -> 37351 | AC43: =SUM(AC44:AC50) -> 11703 | AE43: =SUM(AE44:AE50) -> 3596 | AF43: =SUM(AF44:AF50) -> 5681 | AG43: =SUM(AG44:AG50) -> 3600 | AH43: =SUM(AH44:AH50) -> 2000 | AI43: =SUM(AI44:AI50) -> 2000 | AJ43: =SUM(AJ44:AJ50) -> 2000 | AK43: =SUM(AK44:AK50) -> 5000 | AL43: =SUM(AL44:AL50) -> 5000 | ... AP43: =SUM(AP44:AP50) -> 2000 | AQ43: =SUM(AE43:AP43) -> 39877 | AR43: =AQ43/AQ$14 -> 0.017551211 | AS43: Per Jer
B44: Events & shows | AB44: 5091 | AE44: 15 | AF44: 3991 | AK44: 3000 | AL44: 3000 | AM44: 3000
B45: Travel | AE45: 2152
B46: Social Media | AE46: 741 | AF46: 6 | AG46: 300 | AH46: 300 | AI46: 300 | AJ46: 300 | AK46: 300 | AL46: 300 | AM46: 300 | AN46: 300 | AO46: 300 | AP46: 300
B47: In store | AE47: 192 | AF47: 30 | AG47: 300 | AH47: 300 | AI47: 300 | AJ47: 300 | AK47: 300 | AL47: 300 | AM47: 300 | AN47: 300 | AO47: 300 | AP47: 300
B48: Website
A49: a | B49: Slotting fees | AB49: 30280 | AC49: 5130
B50: Other | AB50: 1980 | AC50: 6573 | AE50: 496 | AF50: 1654 | AG50: 3000 | AH50: 1400 | AI50: 1400 | AJ50: 1400 | AK50: 1400 | AL50: 1400 | AM50: 1400 | AN50: 1400 | AO50: 1400 | AP50: 1400
B51: Rent | C51: =QB!F85 -> 38000.7 | D51: =C51/C$14 -> 0.029667908 | E51: =QB!K85 -> 32084.48 | F51: =E51/E$14 -> 0.014790552 | G51: =QB!P85 -> 84207.42 | H51: =G51/G$14 -> 0.038243124 | I51: =QB!Q85 -> 26379.88 | J51: =QB!R85+QB!R81 -> 35720.62 | K51: =QB!S85 -> 18292.42 | L51: =QB!T85 -> 29012.51 | M51: =SUM(I51:L51) -> 109405.43 | N51: =M51/M$14 -> 0.047036003 | O51: =(8442+760)*3 -> 27606 | P51: =9500*3 -> 28500 | Q51: =9500*3 -> 28500 | R51: =9500*3 -> 28500 | S51: =9500*3 -> 28500 | T51: =SUM(P51:S51) -> 114000 | U51: =T51/T$14 -> 0.036410308 | V51: $9500/month | X51: 37316 | Y51: 28264 | Z51: 29360 | AA51: 9440 | AB51: 9372 | AC51: 10026 | AE51: =9560-4500 -> 5060 | AF51: 9560 | AG51: 5000 | AH51: =AG51 -> 5000 | AI51: =AH51 -> 5000 | AJ51: =AI51 -> 5000 | AK51: =AJ51 -> 5000 | AL51: =AK51 -> 5000 | AM51: =AL51 -> 5000 | AN51: =AM51 -> 5000 | AO51: =AN51 -> 5000 | AP51: =AO51 -> 5000 | AQ51: =SUM(AE51:AP51) -> 64620 | AR51: =AQ51/AQ$14 -> 0.028441438 | AS51: $9500/mo, reduce to $5000 in Jan
B52: Office/food expenses | C52: =QB!F89 -> 20912.08 | D52: =C52/C$14 -> 0.01632648 | E52: =QB!K89 -> 28881.79 | F52: =E52/E$14 -> 0.013314151 | G52: =QB!P89 -> 62978.55 | H52: =G52/G$14 -> 0.028601951 | I52: =QB!Q89 -> 8729.68 | J52: =QB!R89 -> 14622.97 | K52: =QB!S89 -> 18106.66 | L52: =QB!T89 -> 23639.13 | M52: =SUM(I52:L52) -> 65098.44 | N52: =M52/M$14 -> 0.027987371 | O52: =(J52+K52)/2 -> 16364.815 | P52: 15000 | Q52: 15000 | R52: 15000 | S52: 15000 | T52: =SUM(P52:S52) -> 60000 | U52: =T52/T$14 -> 0.01916332 | V52: $5000/month | X52: 11546 | Y52: 6569 | Z52: 1644 | AA52: 1798 | AB52: 1032 | AC52: 564 | AE52: 251 | AF52: 893 | AG52: 600 | AH52: =AG52 -> 600 | AI52: =AH52 -> 600 | AJ52: =AI52 -> 600 | AK52: =AJ52 -> 600 | AL52: =AK52 -> 600 | AM52: =AL52 -> 600 | AN52: =AM52 -> 600 | AO52: =AN52 -> 600 | AP52: =AO52 -> 600 | AQ52: =SUM(AE52:AP52) -> 7144 | AR52: =AQ52/AQ$14 -> 0.003144315 | AS52: Per discussion 11/20
B53: Travel | C53: =QB!F113 -> 10191.39 | D53: =C53/C$14 -> 0.0079566224 | E53: =QB!K113 -> 6913.83 | F53: =E53/E$14 -> 0.0031871908 | G53: =QB!P113 -> 9268.26 | H53: =G53/G$14 -> 0.0042092159 | I53: =QB!Q113 -> 5660.65 | J53: =QB!R113 -> 10099.85 | K53: =QB!S113 -> 5022 | L53: =QB!T113 -> 3101.44 | M53: =SUM(I53:L53) -> 23883.94 | N53: =M53/M$14 -> 0.010268275 | O53: =(J53+K53)/2 -> 7560.925 | P53: =M53/4 -> 5970.985 | Q53: =P53 -> 5970.985 | R53: =Q53 -> 5970.985 | S53: =R53 -> 5970.985 | T53: =SUM(P53:S53) -> 23883.94 | U53: =T53/T$14 -> 0.0076282598 | V53: mostly gas, PY average | X53: 10230 | Y53: 17117 | Z53: 9398 | AA53: 1514 | AB53: 571 | AC53: 192 | AF53: 177 | AG53: 500 | AH53: 500 | AI53: 500 | AJ53: 500 | AK53: 500 | AL53: 500 | AM53: 500 | AN53: 500 | AO53: 500 | AP53: 500 | AQ53: =SUM(AE53:AP53) -> 5177 | AR53: =AQ53/AQ$14 -> 0.002278572 | AS53: Per Jer | AT53: mostly gas, PY average
B54: Dues & subscriptions | C54: =QB!F100 -> 9066.62 | D54: =C54/C$14 -> 0.007078492 | E54: =QB!K100 -> 9832.89 | F54: =E54/E$14 -> 0.0045328416 | G54: =QB!P100 -> 13230.97 | H54: =G54/G$14 -> 0.0060088959 | I54: =QB!Q100 -> 4003.7 | J54: =QB!R100 -> 4951.06 | K54: =QB!S100 -> 5337.94 | L54: =QB!T100 -> 6193 | M54: =SUM(I54:L54) -> 20485.7 | N54: =M54/M$14 -> 0.0088072908 | O54: =(J54+K54)/2 -> 5144.5 | P54: =M54/4 -> 5121.425 | Q54: =P54 -> 5121.425 | R54: =Q54 -> 5121.425 | S54: =R54 -> 5121.425 | T54: =SUM(P54:S54) -> 20485.7 | U54: =T54/T$14 -> 0.0065429004 | V54: software, PY average | X54: 12949 | Y54: 10819 | Z54: 17922 | AA54: 3465 | AB54: 5065 | AC54: 2125 | AE54: 4075 | AF54: 2467 | AG54: 3000 | AH54: 2000 | AI54: 2000 | AJ54: 2000 | AK54: 2000 | AL54: 2000 | AM54: 2000 | AN54: 2000 | AO54: 2000 | AP54: 2000 | AQ54: =SUM(AE54:AP54) -> 27542 | AR54: =AQ54/AQ$14 -> 0.012122162 | AS54: Per analysis | AT54: software, PY average
B55: Insurance | C55: =QB!F101+QB!F102+QB!F103 -> 7786.98 | D55: =C55/C$14 -> 0.0060794514 | E55: =QB!K101+QB!K102+QB!K103 -> 9618.2 | F55: =E55/E$14 -> 0.0044338722 | G55: =QB!P101+QB!P102+QB!P103 -> 19428.15 | H55: =G55/G$14 -> 0.0088233691 | I55: =QB!Q101+QB!Q102+QB!Q103 -> 5429.34 | J55: =QB!R101+QB!R102+QB!R103 -> 5207.41 | K55: =QB!S101+QB!S102+QB!S103 -> 1824.37 | L55: =QB!T101+QB!T102+QB!T103 -> 3851.4 | M55: =SUM(I55:L55) -> 16312.52 | N55: =M55/M$14 -> 0.0070131413 | O55: 1400 | P55: =(M55*1.05)/4 -> 4282.0365 | Q55: =P55 -> 4282.0365 | R55: =Q55 -> 4282.0365 | S55: =R55 -> 4282.0365 | T55: =SUM(P55:S55) -> 17128.146 | U55: =T55/T$14 -> 0.0054705357 | V55: 5% increase | X55: 8122 | Y55: 4876 | Z55: 3610 | AA55: 1394 | AB55: 364 | AC55: 375 | AE55: 3015 | AF55: =201+94+1809 -> 2104 | AG55: =201+94+982 -> 1277 | AH55: =201+94+982 -> 1277 | AI55: =201+94+982 -> 1277 | AJ55: =201+94+982 -> 1277 | AK55: =201+94+982 -> 1277 | AL55: =201+94 -> 295 | AM55: =201+94 -> 295 | AN55: =201+94 -> 295 | AO55: =201+94 -> 295 | AP55: =201+94 -> 295 | AQ55: =SUM(AE55:AP55) -> 12979 | AR55: =AQ55/AQ$14 -> 0.005712495 | AS55: Beam(dental), SF(auto), Hartford(liab/WC)
B56: Utilities | C56: =QB!F90 -> 3827.54 | D56: =C56/C$14 -> 0.0029882372 | E56: =QB!K90 -> 4766.11 | F56: =E56/E$14 -> 0.0021971182 | G56: =QB!P90 -> 12331.72 | H56: =G56/G$14 -> 0.0056004981 | I56: =QB!Q90 -> 2861.71 | J56: =QB!R90 -> 5028.17 | K56: =QB!S90 -> 2859.4 | L56: =QB!T90 -> 2800.93 | M56: =SUM(I56:L56) -> 13550.21 | N56: =M56/M$14 -> 0.0058255583 | O56: =(170+810+180)*3 -> 3480 | P56: =M56/4 -> 3387.5525 | Q56: =P56 -> 3387.5525 | R56: =Q56 -> 3387.5525 | S56: =R56 -> 3387.5525 | T56: =SUM(P56:S56) -> 13550.21 | U56: =T56/T$14 -> 0.0043277835 | V56: PY average | AA56: 3400 | AT56: PY average
B57: - Phone | X57: 3992 | Y57: 3647 | Z57: 2189 | AC57: 650 | AE57: 792 | AF57: 782 | AG57: =612+183 -> 795 | AH57: =612+183-220 -> 575 | AI57: =612+183-220 -> 575 | AJ57: =612+183-220 -> 575 | AK57: =612+183-220 -> 575 | AL57: =612+183-220 -> 575 | AM57: =612+183-220 -> 575 | AN57: =612+183-220 -> 575 | AO57: =612+183-220 -> 575 | AP57: =612+183-220 -> 575 | AQ57: =SUM(AE57:AP57) -> 7544 | AR57: =AQ57/AQ$14 -> 0.0033203685 | AS57: Verizon(phone), AT&T (internet)
B58: - Electric | X58: 2243 | Y58: 1989 | Z58: 3165 | AB58: 252 | AC58: 858 | AE58: 0 | AF58: 0 | AG58: 820 | AH58: 820 | AI58: 820 | AJ58: 820 | AK58: 820 | AL58: 820 | AM58: 820 | AN58: 820 | AO58: 820 | AP58: 820 | AQ58: =SUM(AE58:AP58) -> 8200 | AR58: =AQ58/AQ$14 -> 0.0036090962 | AS58: Trend
B59: Professional fees | C59: =QB!F106 -> 8793.32 | D59: =C59/C$14 -> 0.0068651212 | E59: =QB!K106 -> 14641.91 | F59: =E59/E$14 -> 0.0067497408 | G59: =QB!P106 -> 25989.68 | H59: =G59/G$14 -> 0.011803313 | I59: =QB!Q106 -> 1557 | J59: =QB!R106 -> 1232 | K59: =QB!S106 -> 4093 | L59: =QB!T106 -> 12384.98 | M59: =SUM(I59:L59) -> 19266.98 | N59: =M59/M$14 -> 0.0082833341 | O59: 10500 | P59: =I59+7500 -> 9057 | Q59: =J59+7500 -> 8732 | R59: =K59+7500 -> 11593 | S59: =L59 -> 12384.98 | T59: =SUM(P59:S59) -> 41766.98 | U59: =T59/T$14 -> 0.0133399 | V59: PY + contract CFO | X59: 12052 | Y59: 9564 | Z59: 9537 | AA59: 2194 | AB59: 1594 | AC59: 9094 | AE59: 5893 | AF59: 0 | AG59: 5500 | AH59: =AG59 -> 5500 | AI59: =AH59 -> 5500 | AJ59: =AI59 -> 5500 | AK59: =AJ59 -> 5500 | AL59: =AK59 -> 5500 | AM59: =AL59 -> 5500 | AN59: =AM59 -> 5500 | AO59: =AN59 -> 5500 | AP59: =AO59 -> 5500 | AQ59: =SUM(AE59:AP59) -> 60893 | AR59: =AQ59/AQ$14 -> 0.02680106 | AS59: $3000/mo bookies, $2500/mo Mark | AT59: PY + contract CFO
B60: Repairs & maintenance | C60: =QB!F115 -> 5276.76 | D60: =C60/C$14 -> 0.0041196723 | E60: =QB!K115 -> 3200.57 | F60: =E60/E$14 -> 0.0014754235 | G60: =QB!P115 -> 8234.48 | H60: =G60/G$14 -> 0.0037397208 | I60: =QB!Q115 -> 3372.88 | J60: =QB!R115 -> 3634.97 | K60: =QB!S115 -> 1907.57 | L60: =QB!T115 -> 2104.5 | M60: =SUM(I60:L60) -> 11019.92 | N60: =M60/M$14 -> 0.0047377263 | O60: 3500 | P60: =M60/4 -> 2754.98 | Q60: =P60 -> 2754.98 | R60: =Q60 -> 2754.98 | S60: =R60 -> 2754.98 | T60: =SUM(P60:S60) -> 11019.92 | U60: =T60/T$14 -> 0.0035196376 | V60: PY average | X60: 1010 | Y60: 2214 | Z60: 1118 | AA60: 534 | AC60: 204 | AE60: 0 | AF60: 0 | AG60: 300 | AH60: 300 | AI60: 300 | AJ60: 300 | AK60: 300 | AL60: 300 | AM60: 300 | AN60: 300 | AO60: 300 | AP60: 300 | AQ60: =SUM(AE60:AP60) -> 3000 | AR60: =AQ60/AQ$14 -> 0.001320401 | AS60: Average | AT60: PY average
B61: Taxes & licenses | C61: =QB!F107 -> 2966.05 | D61: =C61/C$14 -> 0.0023156547 | E61: =QB!K107 -> 3042.38 | F61: =E61/E$14 -> 0.0014024998 | G61: =QB!P107 -> 22007.56 | H61: =G61/G$14 -> 0.0099948181 | I61: =QB!Q107 -> 2319.65 | J61: =QB!R107 -> 540.23 | K61: =QB!S107 -> 6401.74 | L61: =QB!T107 -> 0 | M61: =SUM(I61:L61) -> 9261.62 | N61: =M61/M$14 -> 0.0039817912 | O61: =(SUM(I61:K61))/3 -> 3087.2067 | P61: =I61 -> 2319.65 | Q61: =J61 -> 540.23 | R61: =K61*1.1 -> 7041.914 | S61: =L61 -> 0 | T61: =SUM(P61:S61) -> 9901.794 | U61: =T61/T$14 -> 0.0031625208 | V61: PY average + 10% franchise tax (3Q?) | X61: 849 | Y61: 7574 | Z61: 150 | AB61: 0 | AC61: 0 | AE61: 0 | AF61: 0 | AG61: 0 | AH61: 4000 | AI61: 0 | AJ61: 0 | AK61: 0 | AL61: 0 | AM61: 0 | AN61: 0 | AO61: 0 | AP61: 0 | AQ61: =SUM(AE61:AP61) -> 4000 | AR61: =AQ61/AQ$14 -> 0.0017605347 | AS61: Franchise tax in April
B62: Reimbursements | C62: =QB!F114 -> 0 | D62: =C62/C$14 -> 0 | E62: =QB!K114 -> 0 | F62: =E62/E$14 -> 0 | G62: =QB!P114 -> 32.44 | H62: =G62/G$14 -> 1.4732751e-05 | I62: =QB!Q114 -> 916.78 | J62: =QB!R114 -> 1260.64 | K62: =QB!S114 -> 907.58 | L62: =QB!T114 -> 568.13 | M62: =SUM(I62:L62) -> 3653.13 | N62: =M62/M$14 -> 0.0015705677 | O62: 1000 | P62: =M62/4 -> 913.2825 | Q62: =P62 -> 913.2825 | R62: =Q62 -> 913.2825 | S62: =R62 -> 913.2825 | T62: =SUM(P62:S62) -> 3653.13 | U62: =T62/T$14 -> 0.0011667683 | V62: PY average | X62: 1267 | Y62: 917 | Z62: 794 | AA62: 650 | AC62: 442 | AE62: 79 | AF62: 240 | AG62: 100 | AH62: 100 | AI62: 100 | AJ62: 100 | AK62: 100 | AL62: 100 | AM62: 100 | AN62: 100 | AO62: 100 | AP62: 100 | AQ62: =SUM(AE62:AP62) -> 1319 | AR62: =AQ62/AQ$14 -> 0.00058053632 | AS62: Average | AT62: PY average
B63: Bank/Faire/CC charges | AQ63: =SUM(AE63:AP63) -> 0
B64: - Bank/cc | X64: 5811 | Y64: 6586 | Z64: 3831 | AA64: 252 | AB64: 533 | AC64: 813 | AE64: 1441 | AF64: 640 | AG64: 100 | AH64: 100 | AI64: 100 | AJ64: 100 | AK64: 100 | AL64: 100 | AM64: 100 | AN64: 100 | AO64: 100 | AP64: 100 | AQ64: =SUM(AE64:AP64) -> 3081
B65: - Faire | AE65: 366 | AF65: 102 | AG65: 250 | AH65: 250 | AI65: 250 | AJ65: 250 | AK65: 250 | AL65: 250 | AM65: 250 | AN65: 250 | AO65: 250 | AP65: 250 | AQ65: =SUM(AE65:AP65) -> 2968
B66: - Interest | AA66: 5025 | AB66: 6435 | AC66: -2378 | AE66: 4234 | AF66: 3609 | AG66: 50 | AH66: 50 | AI66: 50 | AJ66: 50 | AK66: 50 | AL66: 50 | AM66: 50 | AN66: 50 | AO66: 50 | AP66: 50 | AQ66: =SUM(AE66:AP66) -> 8343
B67: Bad debts | C67: =QB!F112 -> 652.42 | D67: =C67/C$14 -> 0.00050935737 | E67: =QB!K112 -> 6737.83 | F67: =E67/E$14 -> 0.0031060569 | G67: =QB!P112 -> 0 | H67: =G67/G$14 -> 0 | I67: =QB!Q112 -> 0 | J67: =QB!R112 -> 0 | K67: =QB!S112 -> 0 | L67: =QB!T112 -> 0 | M67: =SUM(I67:L67) -> 0 | N67: =M67/M$14 -> 0 | O67: 500 | P67: 500 | Q67: 500 | R67: 500 | S67: 500 | T67: =SUM(P67:S67) -> 2000 | U67: =T67/T$14 -> 0.00063877733 | V67: guess | X67: -143 | Y67: 0 | Z67: 477 | AB67: 0 | AC67: 0 | AE67: 0 | AF67: 0 | AG67: 0 | AH67: 0 | AI67: 0 | AJ67: 0 | AK67: 0 | AL67: 0 | AM67: 0 | AN67: 0 | AO67: 0 | AP67: 0 | AQ67: =SUM(AE67:AP67) -> 0 | AR67: =AQ67/AQ$14 -> 0
B68: Miscellaneous | C68: =QB!F132 -> -8839 | D68: =C68/C$14 -> -0.0069007845 | E68: =QB!K132+QB!K116+QB!K117+QB!K118+QB!K119+QB!K120+QB!K121 -> 4773.89 | F68: =E68/E$14 -> 0.0022007047 | G68: =QB!P132+QB!P116+QB!P117+QB!P118+QB!P119+QB!P120+QB!P121 -> 1597.54 | H68: =G68/G$14 -> 0.00072552894 | I68: =QB!Q132+QB!Q116+QB!Q117+QB!Q118+QB!Q119+QB!Q120+QB!Q121 -> 181.43 | J68: =QB!R132+QB!R116+QB!R117+QB!R118+QB!R119+QB!R120+QB!R121 -> 577.36 | K68: =QB!S132+QB!S116+QB!S117+QB!S118+QB!S119+QB!S120+QB!S121 -> 61.87 | L68: =QB!T132+QB!T116+QB!T117+QB!T118+QB!T119+QB!T120+QB!T121 -> 264.6 | M68: =SUM(I68:L68) -> 1085.26 | N68: =M68/M$14 -> 0.00046657915 | O68: 1000 | P68: 2500 | Q68: 2500 | R68: 2500 | S68: 2500 | T68: =SUM(P68:S68) -> 10000 | U68: =T68/T$14 -> 0.0031938867 | V68: $2500/month | X68: 87 | Y68: -100 | Z68: -16379 | AA68: 21 | AB68: =-319+83 -> -236 | AC68: 31 | AE68: 5 | AF68: 500 | AG68: 250 | AH68: 250 | AI68: 250 | AJ68: 250 | AK68: 250 | AL68: 250 | AM68: 250 | AN68: 250 | AO68: 250 | AP68: 250 | AQ68: =SUM(AE68:AP68) -> 3005 | AR68: =AQ68/AQ$14 -> 0.0013226017 | AS68: Cushion
B69: Total SG&A | C69: =SUM(C42:C68) -> 368150.8 | D69: =C69/C$14 -> 0.28742271 | E69: =SUM(E42:E68) -> 553645.56 | F69: =E69/E$14 -> 0.25522381 | G69: =SUM(G42:G68) -> 857552.4 | H69: =G69/G$14 -> 0.38946072 | I69: =SUM(I42:I68) -> 213065.99 | J69: =SUM(J42:J68) -> 243994.02 | K69: =SUM(K42:K68) -> 259414.99 | L69: =SUM(L42:L68) -> 309888.2 | M69: =SUM(M42:M68) -> 1026363.2 | N69: =M69/M$14 -> 0.44125801 | O69: =SUM(O42:O68) -> 287137.81 | P69: =SUM(P42:P68) -> 310061.35 | Q69: =SUM(Q42:Q68) -> 299756.93 | R69: =SUM(R42:R68) -> 303380.62 | S69: =SUM(S42:S68) -> 283380.68 | T69: =SUM(T42:T68) -> 1196579.6 | U69: =T69/T$14 -> 0.38217396 | X69: =SUM(X42:X68) -> 310069 | Y69: =SUM(Y42:Y68) -> 276348 | Z69: =SUM(Z42:Z68) -> 208105 | AA69: =SUM(AA42:AA68) -> 68473 | AB69: =SUM(AB42:AB68)-AB44-AB46-AB47-AB48-AB49-AB50 -> 94830 | AC69: =SUM(AC42:AC68)-AC44-AC46-AC47-AC48-AC49-AC50 -> 68591 | AE69: =SUM(AE42:AE68)-AE44-AE45-AE46-AE47-AE48-AE49-AE50 -> 65267 | AF69: =SUM(AF51:AF68)+AF43+AF42 -> 51170 | AG69: =SUM(AG51:AG68)+AG43+AG42 -> 49583.92 | AH69: =SUM(AH51:AH68)+AH43+AH42 -> 50763.92 | AI69: =SUM(AI51:AI68)+AI43+AI42 -> 46763.92 | AJ69: =SUM(AJ51:AJ68)+AJ43+AJ42 -> 46763.92 | AK69: =SUM(AK51:AK68)+AK43+AK42 -> 49763.92 | AL69: =SUM(AL51:AL68)+AL43+AL42 -> 48781.92 | AM69: =SUM(AM51:AM68)+AM43+AM42 -> 48781.92 | ... AQ69: =SUM(AQ51:AQ68)+AQ43+AQ42 -> 594986.2 | AR69: =AQ69/AQ$14 -> 0.26187346
A70: Cash from Operations | C70: =C24-C69 -> 145793.95 | D70: =C70/C$14 -> 0.11382426 | E70: =E24-E69 -> 400846.99 | F70: =E70/E$14 -> 0.18478554 | G70: =G24-G69 -> -123708.1 | H70: =G70/G$14 -> -0.05618251 | I70: =I24-I69 -> 23741.74 | J70: =J24-J69 -> -63602.58 | K70: =K24-K69 -> 22614.55 | L70: =L24-L69 -> 5112.06 | M70: =M24-M69 -> -12134.23 | N70: =M70/M$14 -> -0.0052167948 | O70: =O24-O69 -> -66791.512 | P70: =P24-P69 -> -34730.645 | Q70: =Q24-Q69 -> -19868.155 | R70: =R24-R69 -> 47312.196 | S70: =S24-S69 -> 225285.55 | T70: =T24-T69 -> 201998.95 | U70: =T70/T$14 -> 0.064516175 | X70: =X24-X69 -> -155633 | Y70: =Y24-Y69 -> -134812 | Z70: =Z24-Z69 -> -170207 | AA70: =AA24-AA69 -> -3109 | AB70: =AB24-AB69 -> -34009 | AC70: =AC24-AC69 -> -13348 | AE70: =AE24-AE69 -> -30383 | AF70: =AF24-AF69 -> -15810 | AG70: =AG24-AG69 -> -6583.92 | AH70: =AH24-AH69 -> 35236.08 | AI70: =AI24-AI69 -> 39236.08 | AJ70: =AJ24-AJ69 -> 39236.08 | AK70: =AK24-AK69 -> 49136.08 | AL70: =AL24-AL69 -> 50118.08 | ... AQ70: =AQ24-AQ69 -> 371807.8 | AR70: =AQ70/AQ$14 -> 0.16364513
A71: Debt Service | D71: =C71/C$14 -> 0 | F71: =E71/E$14 -> 0 | H71: =G71/G$14 -> 0
B72: CC payments, net of charges | AA72: =Z124-AA124 -> 15451 | AB72: =AA124-AB124 -> 1827.3 | AC72: =AB124-AC124 -> 1468.7 | AE72: =AC124-AE124 -> 27408 | AF72: -1446 | AG72: =5400+200+1732+50+1000 -> 8382 | AH72: =5400+200+1732+50+1000 -> 8382 | AI72: =5400+200+1732+50+1000 -> 8382 | AJ72: =5400+200+1732+50+1000 -> 8382 | AK72: =5400+200+1732+50+1000 -> 8382 | AL72: =5400+200+1732+50+1000 -> 8382 | AM72: =200+1732+50+1000 -> 2982 | AN72: =200+1732+50+1000 -> 2982 | AO72: =200+1732+50+1000 -> 2982 | AP72: =200+1732+50+1000 -> 2982 | AQ72: =SUM(AE72:AP72) -> 88182
B73: Anthony Tallerine | AQ73: =SUM(AE73:AP73) -> 0
B74: Bluevine | AA74: 28007 | AB74: 23286 | AC74: 18248 | AE74: 15342 | AF74: 10668 | AG74: =1181*4 -> 4724 | AH74: =1181*4 -> 4724 | AI74: =1181*4 -> 4724 | AJ74: =1181*4 -> 4724 | AQ74: =SUM(AE74:AP74) -> 44906
B75: Jeremiah reimbursements | AA75: 2834 | AC75: 22418 | AE75: 14150 | AF75: -35 | AQ75: =SUM(AE75:AP75) -> 14115
B76: Fundbox | AB76: 2273 | AC76: 4648 | AE76: 5155 | AF76: 5458 | AG76: =585*4 -> 2340 | AH76: =585*4 -> 2340 | AI76: =585*4 -> 2340 | AJ76: =585*4 -> 2340 | AQ76: =SUM(AE76:AP76) -> 19973
B77: Funding Circle | AA77: 2938 | AB77: 2974 | AC77: 3012 | AE77: 3049 | AF77: 6213 | AG77: 3813 | AH77: 3813 | AI77: 3813 | AJ77: 3813 | AQ77: =SUM(AE77:AP77) -> 24514
B78: Parafin | AA78: 5486 | AB78: 3617 | AC78: 2285 | AE78: 3580 | AF78: 1973 | AG78: 3000 | AH78: 3000 | AI78: 3000 | AJ78: 3000 | AQ78: =SUM(AE78:AP78) -> 17553
B79: QB | AA79: 3853 | AB79: 3888 | AC79: 3844 | AF79: 1680 | AG79: 1680 | AH79: 1680 | AI79: 1680 | AJ79: 1680 | AK79: 1680 | AL79: 1680 | AM79: 1680 | AN79: 1680 | AQ79: =SUM(AE79:AP79) -> 15120
B80: Shopify | AA80: 954 | AB80: 2558 | AC80: 2112 | AE80: 639 | AF80: 611 | AG80: 400 | AH80: 400 | AI80: 400 | AJ80: 400 | AQ80: =SUM(AE80:AP80) -> 2850
B81: Amazon | AA81: 5984 | AB81: 3433 | AC81: 8186 | AE81: 3164 | AF81: 6111 | AG81: 5635 | AH81: 5635 | AI81: 5635 | AJ81: 5635 | AQ81: =SUM(AE81:AP81) -> 31815
B82: Interest | C82: =QB!F99 -> 10146.97 | D82: =C82/C$14 -> 0.0079219429 | E82: =QB!K99 -> 2481.65 | F82: =E82/E$14 -> 0.0011440102 | G82: =QB!P99 -> 8155.74 | H82: =G82/G$14 -> 0.0037039607 | I82: =QB!Q99 -> 4509.94 | J82: =QB!R99 -> 8061.97 | K82: =QB!S99 -> 7285.06 | L82: =QB!T99 -> 13926.07 | M82: =SUM(I82:L82) -> 33783.04 | N82: =M82/M$14 -> 0.014524134 | P82: =M82*0.9/4 -> 7601.184 | Q82: =P82 -> 7601.184 | R82: =Q82 -> 7601.184 | S82: =R82 -> 7601.184 | T82: =SUM(P82:S82) -> 30404.736 | U82: =T82/T$14 -> 0.0097109281 | V82: TBD | X82: 16981 | Y82: 23222 | Z82: 15052 | AQ82: =SUM(AE82:AP82) -> 0 | AR82: =AQ82/AQ$14 -> 0 | AT82: TBD
B83: Total debt service | X83: =SUM(X72:X82) -> 16981 | Y83: =SUM(Y72:Y82) -> 23222 | Z83: =SUM(Z72:Z82) -> 15052 | AA83: =SUM(AA72:AA82) -> 65507 | AB83: =SUM(AB72:AB82) -> 43856.3 | AC83: =SUM(AC72:AC82) -> 66221.7 | AE83: =SUM(AE72:AE82) -> 72487 | AF83: =SUM(AF72:AF82) -> 31233 | AG83: =SUM(AG72:AG82) -> 29974 | AH83: =SUM(AH72:AH82) -> 29974 | AI83: =SUM(AI72:AI82) -> 29974 | AJ83: =SUM(AJ72:AJ82) -> 29974 | AK83: =SUM(AK72:AK82) -> 10062 | AL83: =SUM(AL72:AL82) -> 10062 | ... AQ83: =SUM(AQ72:AQ82) -> 259028
A84: Cash Flow after Debt Service | AA84: =AA70-AA83 -> -68616 | AB84: =AB70-AB83 -> -77865.3 | AC84: =AC70-AC83 -> -79569.7 | AE84: =AE70-AE83 -> -102870 | AF84: =AF70-AF83 -> -47043 | AG84: =AG70-AG83 -> -36557.92 | AH84: =AH70-AH83 -> 5262.08 | AI84: =AI70-AI83 -> 9262.08 | AJ84: =AJ70-AJ83 -> 9262.08 | AK84: =AK70-AK83 -> 39074.08 | AL84: =AL70-AL83 -> 40056.08 | ... AP84: =AP70-AP83 -> 50136.08
A85: Working Capital Fluctuation | AA85: 12964 | AB85: 22340 | AC85: 48625 | AE85: -67158 | AF85: 47727
A86: Investment/Borrowing | AA86: 48000 | AB86: =14000+25000 -> 39000 | AC86: 209440
A87: Net Cash Flow | C87: =C70-#REF!-C82-C86 -> #REF! | D87: =C87/C$14 -> #REF! | E87: =E70-#REF!-E82-E86 -> #REF! | F87: =E87/E$14 -> #REF! | G87: =G70-#REF!-G82-G86 -> #REF! | H87: =G87/G$14 -> #REF! | I87: =I70-#REF!-I82-I86 -> #REF! | J87: =J70-#REF!-J82-J86 -> #REF! | K87: =K70-#REF!-K82-K86 -> #REF! | L87: =L70-#REF!-L82-L86 -> #REF! | M87: =M70-#REF!-M82-M86 -> #REF! | N87: =M87/M$14 -> #REF! | P87: =P70-#REF!-P82-P86 -> #REF! | Q87: =Q70-#REF!-Q82-Q86 -> #REF! | R87: =R70-#REF!-R82-R86 -> #REF! | S87: =S70-#REF!-S82-S86 -> #REF! | T87: =T70-#REF!-T82-T86 -> #REF! | U87: =T87/T$14 -> #REF! | X87: =X70-X83-X86 -> -172614 | Y87: =Y70-Y83-Y86 -> -158034 | Z87: =Z70-Z83-Z86 -> -185259 | AA87: =SUM(AA84:AA86) -> -7652 | AB87: =SUM(AB84:AB86) -> -16525.3 | AC87: =SUM(AC84:AC86) -> 178495.3 | AE87: =SUM(AE84:AE86) -> -170028 | AF87: =SUM(AF84:AF86) -> 684 | AG87: =SUM(AG84:AG86) -> -36557.92 | AH87: =SUM(AH84:AH86) -> 5262.08 | AI87: =SUM(AI84:AI86) -> 9262.08 | AJ87: =SUM(AJ84:AJ86) -> 9262.08 | AK87: =SUM(AK84:AK86) -> 39074.08 | AL87: =SUM(AL84:AL86) -> 40056.08 | ... AP87: =SUM(AP84:AP86) -> 50136.08 | AQ87: =AQ70+#REF!-AQ83+AQ86 -> #REF! | AR87: =AQ87/AQ$14 -> #REF!
A88: Cash, Beginning of Month | AA88: 12057 | AB88: 4406 | AC88: =AB115 -> -12119.3 | AE88: 166376 | AF88: =AE115 -> -3652 | AG88: =AF115 -> -2968 | AH88: =AG115 -> -39525.92 | AI88: =AH115 -> -34263.84 | AJ88: =AI115 -> -25001.76 | AK88: =AJ115 -> -15739.68 | AL88: =AK115 -> 23334.4 | AM88: =AL115 -> 63390.48 | ... AP88: =AO115 -> 209588.72
A89: ASSUMPTIONS
B90: Growth
B91: Retail
B92: Online
B93: Distributor
B94: Franchise
B95: Marg/spices
B96: Cost of co-packer/ingredients
B97: Retail | P97: 0.38 | Q97: 0.38 | R97: 0.38 | S97: 0.38 | T97: 0.38 | X97: 0.38 | Y97: 0.38 | Z97: 0.38 | AQ97: 0.38
B98: Online | P98: 0.38 | Q98: 0.38 | R98: 0.38 | S98: 0.38 | T98: 0.38 | X98: 0.38 | Y98: 0.38 | Z98: 0.38 | AQ98: 0.38
B99: Distributor | P99: 0.49 | Q99: 0.49 | R99: 0.49 | S99: 0.49 | T99: 0.49 | X99: 0.49 | Y99: 0.49 | Z99: 0.49 | AQ99: 0.49
B100: Franchise | P100: 0.43 | Q100: 0.43 | R100: 0.43 | S100: 0.43 | T100: 0.43 | X100: 0.43 | Y100: 0.43 | Z100: 0.43 | AQ100: 0.43
B101: Revenue split by qtr | I101: =I14/$M14 -> 0.25812786 | J101: =J14/$M14 -> 0.18365745 | K101: =K14/$M14 -> 0.23105397 | L101: =L14/$M14 -> 0.32716072 | P101: 0.2 | Q101: 0.22 | R101: 0.23 | S101: 0.35 | T101: =SUM(P101:S101) -> 1 | X101: 0.2 | Y101: 0.22 | Z101: 0.23 | AQ101: =SUM(X101:AP101) -> 0.65
A104: PRICING/COST GRID
...

Sheet Sales Detail
A1: Bravado Spice
A2: Sales by Segment
L3: 2022 | X3: 2023 Forecast | AE3: Revised Based on Meeting 6/20/23
C4: Nov | D4: Dec | E4: Jan | F4: Feb | G4: Mar | H4: Apr | I4: May | J4: June | L4: Q1 | N4: Q2 | P4: Q3 | R4: Q4 To Date | S4: Adjust | T4: Q4 Proj | V4: Total | X4: Q1 | Y4: Q2 | Z4: Q3 | AA4: Q4 | AB4: 2023 | AC4: Q1 Actual | AD4: Q2 Actual | AE4: Q3 | AF4: Q4 | AG4: Year | AH4: Notes 3/27 | AJ4: 2Q Est 6/20 | AL4: YTD 2022 | AM4: YTD 2023 | AN4: Forecast 2023
A5: Distributor
B6: UNFI | L6: 48044 | N6: 36502 | P6: 16487 | R6: 32732 | T6: =SUM(R6:S6) -> 32732 | V6: =L6+N6+P6+T6 -> 133765 | X6: =0.2*$AB6 -> 29428.3 | Y6: =0.22*$AB6 -> 32371.13 | Z6: =0.23*$AB6 -> 33842.545 | AA6: =0.35*$AB6 -> 51499.525 | AB6: =V6*1.1 -> 147141.5 | AC6: 45561 | AD6: 34704 | AE6: 25000 | AF6: 40000 | AG6: =SUM(AC6:AF6) -> 145265 | AH6: On target | AJ6: 30816 | AL6: =L6+N6 -> 84546 | AM6: =AC6+AD6 -> 80265 | AN6: =X6+Y6 -> 61799.43
B7: Total Wine | X7: 5000 | Y7: 7500 | Z7: 7500 | AA7: 10000 | AB7: =SUM(X7:AA7) -> 30000 | AE7: 2500 | AF7: 5000 | AG7: =SUM(AC7:AF7) -> 7500 | AH7: On target | AJ7: 2500 | AL7: =L7+N7 -> 0 | AM7: =AC7+AD7 -> 0 | AN7: =X7+Y7 -> 12500
B8: KeHe | L8: 54013 | N8: 46386 | P8: 29570 | R8: 46297 | T8: =SUM(R8:S8) -> 46297 | V8: =L8+N8+P8+T8 -> 176266 | X8: =0.2*$AB8 -> 38778.52 | Y8: =0.22*$AB8 -> 42656.372 | Z8: =0.23*$AB8 -> 44595.298 | AA8: =0.35*$AB8 -> 67862.41 | AB8: =V8*1.1 -> 193892.6 | AC8: 85717 | AD8: 60107 | AE8: 50000 | AF8: 75000 | AG8: =SUM(AC8:AF8) -> 270824 | AH8: Includes $45 to Meijer 1Q, on target | AJ8: 62491 | AL8: =L8+N8 -> 100399 | AM8: =AC8+AD8 -> 145824 | AN8: =X8+Y8 -> 81434.892
B9: Meijer | Y9: 20000 | Z9: 15000 | AA9: 20000 | AB9: =SUM(X9:AA9) -> 55000 | AE9: 30000 | AF9: 30000 | AG9: =SUM(AC9:AF9) -> 60000 | AH9: Includes $45 to Meijer 1Q, on target | AJ9: =AE9 -> 30000 | AL9: =L9+N9 -> 0 | AM9: =AC9+AD9 -> 0 | AN9: =X9+Y9 -> 20000
B10: Walmart | AF10: 122000 | AG10: =SUM(AC10:AF10) -> 122000 | AL10: =L10+N10 -> 0 | AM10: =AC10+AD10 -> 0 | AN10: =X10+Y10 -> 0
B11: Albertsons | AF11: 85000 | AG11: =SUM(AC11:AF11) -> 85000 | AL11: =L11+N11 -> 0 | AM11: =AC11+AD11 -> 0 | AN11: =X11+Y11 -> 0
B12: Target | Y12: 20000 | Z12: 15000 | AA12: 20000 | AB12: =SUM(X12:AA12) -> 55000 | AG12: =SUM(AC12:AF12) -> 0 | AL12: =L12+N12 -> 0 | AM12: =AC12+AD12 -> 0 | AN12: =X12+Y12 -> 20000
B13: DPI | P13: 1315 | R13: 5404 | T13: =SUM(R13:S13) -> 5404 | V13: =L13+N13+P13+T13 -> 6719 | X13: =0.2*$AB13 -> 1478.18 | Y13: =0.22*$AB13 -> 1625.998 | Z13: =0.23*$AB13 -> 1699.907 | AA13: =0.35*$AB13 -> 2586.815 | AB13: =V13*1.1 -> 7390.9 | AC13: 15798 | AD13: 0 | AE13: 7500 | AF13: 10000 | AG13: =SUM(AC13:AF13) -> 33298 | AJ13: 7500 | AL13: =L13+N13 -> 0 | AM13: =AC13+AD13 -> 15798 | AN13: =X13+Y13 -> 3104.178
B14: Kroger | Y14: 20000 | Z14: 25000 | AA14: 40000 | AB14: =SUM(X14:AA14) -> 85000 | AD14: 0 | AE14: =Z14 -> 25000 | AF14: =AA14 -> 40000 | AG14: =SUM(AC14:AF14) -> 65000 | AH14: Will know more after 5/18, uncertain at present | AJ14: =AE14 -> 25000 | AL14: =L14+N14 -> 0 | AM14: =AC14+AD14 -> 0 | AN14: =X14+Y14 -> 20000
B15: Hot Shots | L15: 13584 | N15: 26729 | P15: 13489 | R15: 36080 | T15: =SUM(R15:S15) -> 36080 | V15: =L15+N15+P15+T15 -> 89882 | X15: =0.2*$AB15 -> 21571.68 | Y15: =0.22*$AB15 -> 23728.848 | Z15: =0.23*$AB15 -> 24807.432 | AA15: =0.35*$AB15 -> 37750.44 | AB15: =V15*1.2 -> 107858.4 | AC15: 12261 | AD15: 0 | AE15: 15000 | AF15: 30000 | AG15: =SUM(AC15:AF15) -> 57261 | AH15: On target | AJ15: 10000 | AL15: =L15+N15 -> 40313 | AM15: =AC15+AD15 -> 12261 | AN15: =X15+Y15 -> 45300.528
B16: Heatsupply | P16: 15288 | R16: 15852 | T16: =SUM(R16:S16) -> 15852 | V16: =L16+N16+P16+T16 -> 31140 | X16: 10000 | Y16: 15000 | Z16: 15000 | AA16: 20000 | AB16: =SUM(X16:AA16) -> 60000 | AC16: 0 | AE16: 15000 | AF16: 30000 | AG16: =SUM(AC16:AF16) -> 45000 | AH16: On target | AL16: =L16+N16 -> 0 | AM16: =AC16+AD16 -> 0 | AN16: =X16+Y16 -> 25000
B17: Heatonist | AC17: 5460 | AD17: 6510 | AE17: 4000 | AF17: 6000 | AG17: =SUM(AC17:AF17) -> 21970 | AJ17: 5585 | AL17: =L17+N17 -> 0 | AM17: =AC17+AD17 -> 11970 | AN17: =X17+Y17 -> 0
B18: Peppers.com | AD18: 3517 | AE18: 3500 | AF18: 7000 | AG18: =SUM(AC18:AF18) -> 14017 | AL18: =L18+N18 -> 0 | AM18: =AC18+AD18 -> 3517 | AN18: =X18+Y18 -> 0
B19: Food Movers | AD19: 16730 | AE19: 15000 | AF19: 15000 | AG19: =SUM(AC19:AF19) -> 46730 | AL19: =L19+N19 -> 0 | AM19: =AC19+AD19 -> 16730 | AN19: =X19+Y19 -> 0
B20: American Heritage | AD20: 3126 | AE20: 3000 | AF20: 6000 | AG20: =SUM(AC20:AF20) -> 12126 | AJ20: 2700 | AL20: =L20+N20 -> 0 | AM20: =AC20+AD20 -> 3126 | AN20: =X20+Y20 -> 0
B21: Hotheads (intl) | T21: =SUM(R21:S21) -> 0 | AC21: 0 | AG21: =SUM(AC21:AF21) -> 0 | AL21: =L21+N21 -> 0 | AM21: =AC21+AD21 -> 0 | AN21: =X21+Y21 -> 0
B22: Total distributor | C22: =SUM(C6:C21) -> 0 | D22: =SUM(D6:D21) -> 0 | E22: =SUM(E6:E21) -> 0 | F22: =SUM(F6:F21) -> 0 | G22: =SUM(G6:G21) -> 0 | H22: =SUM(H6:H21) -> 0 | I22: =SUM(I6:I21) -> 0 | J22: =SUM(J6:J21) -> 0 | L22: =SUM(L6:L21) -> 115641 | M22: =L22/L42 -> 0.19260541 | N22: =SUM(N6:N21) -> 109617 | O22: =N22/N42 -> 0.25660251 | P22: =SUM(P6:P21) -> 76149 | Q22: =P22/P42 -> 0.14169101 | R22: =SUM(R6:R21) -> 136365 | S22: =SUM(S6:S21) -> 0 | T22: =SUM(T6:T21) -> 136365 | U22: =R22/R42 -> 0.17919805 | V22: =SUM(V6:V21) -> 437772 | W22: =T22/T42 -> 0.17919805 | X22: =SUM(X6:X21) -> 106256.68 | Y22: =SUM(Y6:Y21) -> 182882.35 | Z22: =SUM(Z6:Z21) -> 182445.18 | AA22: =SUM(AA6:AA21) -> 269699.19 | AB22: =SUM(AB6:AB21) -> 741283.4 | AC22: =SUM(AC6:AC21) -> 164797 | AD22: =SUM(AD6:AD21) -> 124694 | AE22: =SUM(AE6:AE21) -> 195500 | ... AG22: =SUM(AG6:AG21) -> 985991 | AJ22: =SUM(AJ6:AJ21) -> 176592 | AL22: =SUM(AL6:AL21) -> 225258 | AM22: =SUM(AM6:AM21) -> 289491 | AN22: =SUM(AN6:AN21) -> 289139.03
A23: Franchise
B24: Buc-ee's | L24: 55130 | N24: 82372 | P24: 61402 | R24: 73071 | T24: =SUM(R24:S24) -> 73071 | V24: =L24+N24+P24+T24 -> 271975 | X24: =0.2*$AB24 -> 65274 | Y24: =0.22*$AB24 -> 71801.4 | Z24: =0.23*$AB24 -> 75065.1 | AA24: =0.35*$AB24 -> 114229.5 | AB24: =V24*1.2 -> 326370 | AC24: 32461 | AD24: 23971 | AE24: 38000 | AF24: 57000 | AG24: =SUM(AC24:AF24) -> 151432 | AH24: TBD, send Spencer a summary | AJ24: 20201 | AL24: =L24+N24 -> 137502 | AM24: =AC24+AD24 -> 56432 | AN24: =X24+Y24 -> 137075.4
B25: Academy | L25: 132950 | N25: 17883 | P25: 48502 | R25: 98797 | T25: =SUM(R25:S25) -> 98797 | V25: =L25+N25+P25+T25 -> 298132 | X25: =0.2*$AB25 -> 59626.4 | Y25: =0.22*$AB25 -> 65589.04 | Z25: =0.23*$AB25 -> 68570.36 | AA25: =0.35*$AB25 -> 104346.2 | AB25: =V25 -> 298132 | AC25: 23173 | AD25: 2250 | AE25: 30000 | AF25: 50000 | AG25: =SUM(AC25:AF25) -> 105423 | AH25: Reduce rest of year by 10% | AJ25: 22250 | AL25: =L25+N25 -> 150833 | AM25: =AC25+AD25 -> 25423 | AN25: =X25+Y25 -> 125215.44
B26: Cost Plus/World Market | L26: 92563 | N26: 41760 | P26: 80636 | R26: 36420 | T26: =SUM(R26:S26) -> 36420 | V26: =L26+N26+P26+T26 -> 251379 | X26: =0.2*$AB26 -> 65358.54 | Y26: =0.22*$AB26 -> 71894.394 | Z26: =0.23*$AB26 -> 75162.321 | AA26: =0.35*$AB26 -> 114377.44 | AB26: =V26*1.3 -> 326792.7 | AC26: 15174 | AD26: 25453 | AE26: 25000 | AF26: 35000 | AG26: =SUM(AC26:AF26) -> 100627 | AH26: Reduce rest of year by 15% | AJ26: 16530 | AL26: =L26+N26 -> 134323 | AM26: =AC26+AD26 -> 40627 | AN26: =X26+Y26 -> 137252.93
B27: TJ Maxx | L27: 8568 | P27: 21449 | R27: 21609 | T27: =SUM(R27:S27) -> 21609 | V27: =L27+N27+P27+T27 -> 51626 | X27: =0.2*$AB27 -> 10325.2 | Y27: =0.22*$AB27 -> 11357.72 | Z27: =0.23*$AB27 -> 11873.98 | AA27: =0.35*$AB27 -> 18069.1 | AB27: =V27 -> 51626 | AC27: 21627 | AD27: 6772 | AE27: 2000 | AF27: 0 | AG27: =SUM(AC27:AF27) -> 30399 | AH27: Zero rest of year | AJ27: 6772 | AL27: =L27+N27 -> 8568 | AM27: =AC27+AD27 -> 28399 | AN27: =X27+Y27 -> 21682.92
B28: Uline | P28: 61975 | R28: 201600 | T28: =SUM(R28:S28) -> 201600 | V28: =L28+N28+P28+T28 -> 263575 | X28: 110000 | Y28: 50000 | Z28: 120000 | AA28: 120000 | AB28: =SUM(X28:AA28) -> 400000 | AC28: 117029 | AD28: 63806 | AE28: 60000 | AF28: 75000 | AG28: =SUM(AC28:AF28) -> 315835 | AH28: Check with Jeremiah | AJ28: 42538 | AL28: =L28+N28 -> 0 | AM28: =AC28+AD28 -> 180835 | AN28: =X28+Y28 -> 160000
B29: Marshalls | L29: 7140 | P29: 15365 | R29: 8640 | T29: =SUM(R29:S29) -> 8640 | V29: =L29+N29+P29+T29 -> 31145 | X29: 7000 | Y29: 5000 | Z29: 5000 | AA29: 10000 | AB29: =SUM(X29:AA29) -> 27000 | AC29: 14985 | AD29: 4879 | AE29: 0 | AF29: 0 | AG29: =SUM(AC29:AF29) -> 19864 | AH29: Zero rest of year | AJ29: 4879 | AL29: =L29+N29 -> 7140 | AM29: =AC29+AD29 -> 19864 | AN29: =X29+Y29 -> 12000
B30: Jungle Jim's | L30: 4161 | N30: 2540 | P30: 3046 | R30: 2506 | T30: =SUM(R30:S30) -> 2506 | V30: =L30+N30+P30+T30 -> 12253 | X30: 2500 | Y30: =X30 -> 2500 | Z30: =Y30 -> 2500 | AA30: =Z30 -> 2500 | AB30: =SUM(X30:AA30) -> 10000 | AC30: 1257 | AD30: 2718 | AE30: 5000 | AF30: 7000 | AG30: =SUM(AC30:AF30) -> 15975 | AH30: On target | AJ30: 2718 | AL30: =L30+N30 -> 6701 | AM30: =AC30+AD30 -> 3975 | AN30: =X30+Y30 -> 5000
B31: Door Dash | R31: 2236 | T31: =SUM(R31:S31) -> 2236 | X31: 5000 | Y31: 5000 | Z31: 10000 | AA31: 20000 | AB31: =SUM(X31:AA31) -> 40000 | AD31: 0 | AE31: 0 | AF31: 0 | AG31: =SUM(AC31:AF31) -> 0 | AH31: Zero rest of year | AJ31: 0 | AL31: =L31+N31 -> 0 | AM31: =AC31+AD31 -> 0 | AN31: =X31+Y31 -> 10000
B32: HomeGoods | AC32: 23233 | AD32: =Y32 -> 0 | AE32: =Z32 -> 0 | AF32: =AA32 -> 0 | AG32: =SUM(AC32:AF32) -> 23233 | AH32: Zero rest of year | AJ32: =AE32 -> 0 | AL32: =L32+N32 -> 0 | AM32: =AC32+AD32 -> 23233 | AN32: =X32+Y32 -> 0
B33: Sarl Sauce (France) | AC33: 11464 | AD33: =Y33 -> 0 | AE33: =Z33 -> 0 | AF33: =AA33 -> 0 | AG33: =SUM(AC33:AF33) -> 11464 | AJ33: =AE33 -> 0 | AL33: =L33+N33 -> 0 | AM33: =AC33+AD33 -> 11464 | AN33: =X33+Y33 -> 0
B34: Spec's | L34: 7504 | N34: 12158 | P34: 12017 | R34: 6312 | T34: =SUM(R34:S34) -> 6312 | V34: =L34+N34+P34+T34 -> 37991 | X34: 7500 | Y34: 10000 | Z34: 20000 | AA34: 30000 | AB34: =SUM(X34:AA34) -> 67500 | AC34: 16740 | AD34: 16839 | AE34: 80000 | AF34: 90000 | AG34: =SUM(AC34:AF34) -> 203579 | AH34: Major demos May 12-13 expected to drive growth | AJ34: 15318 | AL34: =L34+N34 -> 19662 | AM34: =AC34+AD34 -> 33579 | AN34: =X34+Y34 -> 17500
B35: Total franchise | C35: =SUM(C24:C34) -> 0 | D35: =SUM(D24:D34) -> 0 | E35: =SUM(E24:E34) -> 0 | F35: =SUM(F24:F34) -> 0 | G35: =SUM(G24:G34) -> 0 | H35: =SUM(H24:H34) -> 0 | I35: =SUM(I24:I34) -> 0 | J35: =SUM(J24:J34) -> 0 | L35: =SUM(L24:L34) -> 308016 | M35: =L35/L42 -> 0.51301484 | N35: =SUM(N24:N34) -> 156713 | O35: =N35/N42 -> 0.36684957 | P35: =SUM(P24:P34) -> 304392 | Q35: =P35/P42 -> 0.56638446 | R35: =SUM(R24:R34) -> 451191 | S35: =SUM(S24:S34) -> 0 | T35: =SUM(T24:T34) -> 451191 | U35: =R35/R42 -> 0.59291276 | V35: =SUM(V24:V34) -> 1218076 | W35: =T35/T42 -> 0.59291276 | X35: =SUM(X24:X34) -> 332584.14 | Y35: =SUM(Y24:Y34) -> 293142.55 | Z35: =SUM(Z24:Z34) -> 388171.76 | AA35: =SUM(AA24:AA34) -> 533522.24 | AB35: =SUM(AB24:AB34) -> 1547420.7 | AC35: =SUM(AC24:AC34) -> 277143 | AD35: =SUM(AD24:AD34) -> 146688 | AE35: =SUM(AE24:AE34) -> 240000 | ... AG35: =SUM(AG24:AG34) -> 977831 | AJ35: =SUM(AJ24:AJ34) -> 131206 | AL35: =SUM(AL24:AL34) -> 464729 | AM35: =SUM(AM24:AM34) -> 423831 | AN35: =SUM(AN24:AN34) -> 625726.69
A36: Retail | L36: =L42-L22-L35-L41 -> 67876.69 | M36: =L36/L42 -> 0.11305175 | N36: =N42-N22-N35-N41 -> 65982 | O36: =N36/N42 -> 0.15445731 | P36: =P42-P22-P35-P41 -> 55994 | Q36: =P36/P42 -> 0.10418845 | R36: =R42-R22-R35-R41 -> 40887.67 | T36: =SUM(R36:S36) -> 40887.67 | U36: =R36/R42 -> 0.053730729 | V36: =L36+N36+P36+T36 -> 230740.36 | W36: =T36/T42 -> 0.053730729 | X36: =0.2*$AB36 -> 48455.476 | Y36: =0.22*$AB36 -> 53301.023 | Z36: =0.23*$AB36 -> 55723.797 | AA36: =0.35*$AB36 -> 84797.082 | AB36: =V36*1.05 -> 242277.38 | AC36: 38264 | AD36: 56618 | AE36: 65000 | AF36: 95000 | AG36: =SUM(AC36:AF36) -> 254882 | AH36: Increase to $30K/month by 4Q for Faire plus small amount of other | AJ36: 82023 | AL36: =L36+N36 -> 133858.69 | AM36: =AC36+AD36 -> 94882 | AN36: =X36+Y36 -> 101756.5
B37: Faire
B38: Other
C39: =SUM(C37:C38) -> 0 | D39: =SUM(D37:D38) -> 0 | E39: =SUM(E37:E38) -> 0 | F39: =SUM(F37:F38) -> 0 | G39: =SUM(G37:G38) -> 0 | H39: =SUM(H37:H38) -> 0 | I39: =SUM(I37:I38) -> 0 | J39: =SUM(J37:J38) -> 0
A41: Online/Amazon | L41: =44514+64356 -> 108870 | M41: =L41/L42 -> 0.181328 | N41: =58581+36293 -> 94874 | O41: =N41/N42 -> 0.22209061 | P41: =54860+46035 -> 100895 | Q41: =P41/P42 -> 0.18773608 | R41: 132530 | T41: =SUM(R41:S41) -> 132530 | U41: =R41/R42 -> 0.17415846 | V41: =L41+N41+P41+T41 -> 437169 | W41: =T41/T42 -> 0.17415846 | X41: =0.2*$AB41 -> 120000 | Y41: 100000 | Z41: 154000 | AA41: 242000 | AB41: 600000 | AC41: 89837 | AD41: 78100 | AE41: 150000 | AF41: 200000 | AG41: =SUM(AC41:AF41) -> 517937 | AH41: On target | AJ41: 81613 | AL41: =L41+N41 -> 203744 | AM41: =AC41+AD41 -> 167937 | AN41: =X41+Y41 -> 220000
B42: Total | C42: =C22+C35+C39+C41 -> 0 | D42: =D22+D35+D39+D41 -> 0 | E42: =E22+E35+E39+E41 -> 0 | F42: =F22+F35+F39+F41 -> 0 | G42: =G22+G35+G39+G41 -> 0 | H42: =H22+H35+H39+H41 -> 0 | I42: =I22+I35+I39+I41 -> 0 | J42: =J22+J35+J39+J41 -> 0 | L42: =[1]QB!Q45 -> 600403.69 | N42: 427186 | P42: 537430 | R42: =[1]QB!T45 -> 760973.67 | S42: =S22+S35+S36+S41 -> 0 | T42: =T22+T35+T36+T41 -> 760973.67 | U42: =R42/R42 -> 1 | V42: =V22+V35+V36+V41 -> 2323757.4 | W42: =T42/T42 -> 1 | X42: =X22+X35+X36+X41 -> 607296.3 | Y42: =Y22+Y35+Y36+Y41 -> 629325.93 | Z42: =Z22+Z35+Z36+Z41 -> 780340.74 | AA42: =AA22+AA35+AA36+AA41 -> 1130018.5 | AB42: =AB22+AB35+AB36+AB41 -> 3130981.5 | AC42: =AC22+AC35+AC36+AC41 -> 570041 | AD42: =AD22+AD35+AD36+AD41 -> 406100 | AE42: =AE22+AE35+AE36+AE41 -> 650500 | ... AG42: =AG22+AG35+AG36+AG41 -> 2736641 | AJ42: =AJ22+AJ35+AJ36+AJ41 -> 471434 | AL42: =AL22+AL35+AL36+AL41 -> 1027589.7 | AM42: =AM22+AM35+AM36+AM41 -> 976141 | AN42: =AN22+AN35+AN36+AN41 -> 1236622.2
L43: =L22+L35+L36+L41 -> 600403.69 | N43: =[1]QB!R45 -> 427185.57 | P43: =[1]QB!S45 -> 537430.43 | R43: =[1]QB!T45 -> 760973.67 | X43: =X42/$AB42 -> 0.19396355 | Y43: =Y42/$AB42 -> 0.20099957 | Z43: =Z42/$AB42 -> 0.24923199 | AA43: =AA42/$AB42 -> 0.36091511 | AB43: =AB42/$AB42 -> 1 | AC43: =AC42/$AG42 -> 0.20829952 | AD43: =AD42/$AG42 -> 0.1483936 | AE43: =AE42/$AG42 -> 0.23770016 | AF43: =AF42/$AG42 -> 0.40560673 | AG43: =AG42/$AG42 -> 1 | AJ43: =AJ42/$AG42 -> 0.17226739
AC46: 5611
B48: Per QB sales by customer | L48: 476612 | N48: 310960 | P48: 426300 | R48: 623345
B49: Retail (implied via SbC report) | L49: =L48-L22-L35 -> 52955 | N49: =N48-N22-N35 -> 44630 | P49: =P48-P22-P35 -> 45759 | R49: =R48-R22-R35 -> 35789
AC55: 570041

Sheet Mktg.Advert
A1: Bravado Spice
A2: Transaction Report
A3: January - October, 2023
B5: Date | C5: Transaction Type | D5: Num | E5: Adj | F5: Name | G5: Memo/Description | H5: Account | I5: Split | J5: Amount | K5: Balance | M5: Google | N5: Events/Shows | O5: In Store | P5: Website | Q5: Other | R5: KeHe | S5: UNFI | T5: Advantage | U5: MailChimp | V5: MooPrint | W5: Apdat | X5: HEB | Y5: SpecFoods | Z5: Specs
A6: Marketing/Advertising
B7: 01/01/2023 | C7: Expense | E7: No | F7: Google | G7: GOOGLE *ADS9428905993 | H7: 72000 Marketing/Advertising | I7: Chase 0423 | J7: 144.74 | K7: 144.74 | M7: =J7 -> 144.74
B8: 01/09/2023 | C8: Expense | E8: No | F8: Cloud Chaserz | G8: CLOUD CHASERZ | H8: 72000 Marketing/Advertising | I8: Chase 2639 | J8: 46.93 | K8: 191.67 | Q8: =J8 -> 46.93
B9: 01/17/2023 | C9: Expense | E9: No | F9: Google | G9: GOOGLE *ADS9428905993 | H9: 72000 Marketing/Advertising | I9: Chase 0423 | J9: 500 | K9: 691.67 | M9: =J9 -> 500
B10: 01/23/2023 | C10: Expense | E10: No | G10: cost plus world | H10: 72000 Marketing/Advertising | I10: 11200 Chase Checking 5189 | J10: 40.01 | K10: 731.68 | Q10: =J10 -> 40.01
B11: 01/29/2023 | C11: Expense | E11: No | F11: Liquor Lounge | G11: TST* EZ' LIQUOR LOUNGE | H11: 72000 Marketing/Advertising | I11: Chase 2639 | J11: 8.98 | K11: 740.66 | Q11: =J11 -> 8.98
B12: 02/01/2023 | C12: Expense | E12: No | F12: Google | G12: GOOGLE *ADS9428905993 | H12: 72000 Marketing/Advertising | I12: Chase 0423 | J12: 533.02 | K12: 1273.68 | M12: =J12 -> 533.02
B13: 02/05/2023 | C13: Expense | E13: No | F13: Manready Mercantile | G13: SP MANREADY MERCANTI | H13: 72000 Marketing/Advertising | I13: Chase 2639 | J13: 25.33 | K13: 1299.01 | Q13: =J13 -> 25.33
B14: 02/11/2023 | C14: Expense | E14: No | F14: Google | G14: GOOGLE *ADS9428905993 | H14: 72000 Marketing/Advertising | I14: Chase 0423 | J14: 500 | K14: 1799.01 | M14: =J14 -> 500
B15: 02/25/2023 | C15: Expense | E15: No | F15: Google | G15: GOOGLE *ADS9428905993 | H15: 72000 Marketing/Advertising | I15: Chase 0423 | J15: 500 | K15: 2299.01 | M15: =J15 -> 500
B16: 02/26/2023 | C16: Expense | E16: No | F16: Tiktok | G16: TIKTOK ADS *TIKTOK | H16: 72000 Marketing/Advertising | I16: Chase 0423 | J16: 40 | K16: 2339.01 | Q16: =J16 -> 40
B17: 03/01/2023 | C17: Expense | E17: No | F17: Google | G17: GOOGLE *ADS9428905993 | H17: 72000 Marketing/Advertising | I17: Chase 0423 | J17: 102.5 | K17: 2441.51 | M17: =J17 -> 102.5
B18: 03/05/2023 | C18: Expense | E18: No | F18: Tiktok | G18: TIKTOK ADS | H18: 72000 Marketing/Advertising | I18: Chase 0423 | J18: 36.51 | K18: 2478.02 | Q18: =J18 -> 36.51
B19: 03/07/2023 | C19: Expense | E19: No | F19: Cloud Chaserz | G19: CLOUD CHASERZ | H19: 72000 Marketing/Advertising | I19: 32400 Spark Business Credit Card - 4964 | J19: 24.83 | K19: 2502.85 | Q19: =J19 -> 24.83
B20: 03/17/2023 | C20: Expense | E20: No | F20: ATM Withdrawal | G20: ATM WITHDRAWAL 006340 03/1712017 NOR | H20: 72000 Marketing/Advertising | I20: 11200 Chase Checking 5189 | J20: 100 | K20: 2602.85 | Q20: =J20 -> 100
B21: 03/18/2023 | C21: Expense | E21: No | F21: Google | G21: GOOGLE *ADS9428905993 | H21: 72000 Marketing/Advertising | I21: Chase 0423 | J21: 500 | K21: 3102.85 | M21: =J21 -> 500
B22: 03/22/2023 | C22: Expense | E22: No | F22: Cloud Chaserz | G22: CLOUD CHASERZ | H22: 72000 Marketing/Advertising | I22: Chase 2639 | J22: 58.42 | K22: 3161.27 | Q22: =J22 -> 58.42
B23: 04/01/2023 | C23: Expense | E23: No | F23: Google | G23: GOOGLE *ADS9428905993 | H23: 72000 Marketing/Advertising | I23: Chase 0423 | J23: 347.49 | K23: 3508.76 | M23: =J23 -> 347.49
B24: 04/02/2023 | C24: Expense | E24: No | F24: Valencia Exotic Cigars | G24: VALENCIA EXOTIC CIGARS . | H24: 72000 Marketing/Advertising | I24: Chase 2639 | J24: 16.79 | K24: 3525.55 | Q24: =J24 -> 16.79
B25: 04/02/2023 | C25: Expense | E25: No | F25: Zeitgeist | G25: SQ *ZEITGEIST | H25: 72000 Marketing/Advertising | I25: Chase 2639 | J25: 19.38 | K25: 3544.93 | Q25: =J25 -> 19.38
B26: 04/19/2023 | C26: Expense | E26: No | F26: Google | G26: GOOGLE *ADS9428905993 | H26: 72000 Marketing/Advertising | I26: Chase 0423 | J26: 500 | K26: 4044.93 | M26: =J26 -> 500
B27: 05/01/2023 | C27: Expense | E27: No | F27: Google | G27: GOOGLE *ADS9428905993 | H27: 72000 Marketing/Advertising | I27: Chase 0423 | J27: 255.18 | K27: 4300.11 | M27: =J27 -> 255.18
B28: 05/12/2023 | C28: Expense | E28: No | F28: Google | G28: GOOGLE *ADS9428905993 | H28: 72000 Marketing/Advertising | I28: Chase 0423 | J28: 500 | K28: 4800.11 | M28: =J28 -> 500
B29: 05/16/2023 | C29: Expense | E29: No | F29: Google | G29: GOOGLE *ADS9428905993 | H29: 72000 Marketing/Advertising | I29: Chase 0423 | J29: 500 | K29: 5300.11 | M29: =J29 -> 500
B30: 05/19/2023 | C30: Expense | E30: No | F30: Google | G30: GOOGLE *ADS9428905993 | H30: 72000 Marketing/Advertising | I30: Chase 0423 | J30: 500 | K30: 5800.11 | M30: =J30 -> 500
B31: 05/23/2023 | C31: Expense | E31: No | F31: Google | G31: & GOOGLE *ADS9428905993 cc@google.com CA | H31: 72000 Marketing/Advertising | I31: Chase 0423 | J31: 500 | K31: 6300.11 | M31: =J31 -> 500
B32: 05/24/2023 | C32: Expense | E32: No | F32: KeHE Distributors LLC | G32: MSF83618 Promotion | H32: 72000 Marketing/Advertising | I32: 11200 Chase Checking 5189 | J32: 4742.97 | K32: 11043.08 | R32: =J32 -> 4742.97
B33: 05/27/2023 | C33: Expense | E33: No | F33: Google | G33: & GOOGLE *ADS9428905993 cc@google.com CA | H33: 72000 Marketing/Advertising | I33: Chase 0423 | J33: 500 | K33: 11543.08 | M33: =J33 -> 500
B34: 06/01/2023 | C34: Expense | E34: No | F34: Google | G34: & GOOGLE *ADS9428905993 cc@google.com CA | H34: 72000 Marketing/Advertising | I34: Chase 0423 | J34: 462.65 | K34: 12005.73 | M34: =J34 -> 462.65
B35: 06/05/2023 | C35: Expense | E35: No | F35: Google | G35: & GOOGLE *ADS9428905993 cc@google.com CA | H35: 72000 Marketing/Advertising | I35: Chase 0423 | J35: 500 | K35: 12505.73 | M35: =J35 -> 500
B36: 06/11/2023 | C36: Expense | E36: No | F36: Google | G36: & GOOGLE *ADS9428905993 cc@google.com CA | H36: 72000 Marketing/Advertising | I36: Chase 0423 | J36: 500 | K36: 13005.73 | M36: =J36 -> 500
B37: 06/14/2023 | C37: Expense | E37: No | F37: Google | G37: & GOOGLE *ADS9428905993 cc@google.com CA | H37: 72000 Marketing/Advertising | I37: Chase 0423 | J37: 500 | K37: 13505.73 | M37: =J37 -> 500
B38: 07/19/2023 | C38: Expense | E38: No | F38: KeHE Distributors LLC | G38: Advertising | H38: 72000 Marketing/Advertising | I38: 11200 Chase Checking 5189 | J38: 2272.29 | K38: 15778.02 | R38: =J38 -> 2272.29
B39: 07/28/2023 | C39: Expense | E39: No | F39: Google | G39: GOOGLE *ADSXXXXXXXXX cc@google.com CA 07/28 | H39: 72000 Marketing/Advertising | I39: 11200 Chase Checking 5189 | J39: 16.31 | K39: 15794.33 | M39: =J39 -> 16.31
B40: 07/28/2023 | C40: Expense | E40: No | F40: Google | G40: GOOGLE *ADSXXXXXXXXX cc@google.com CA 07/28 | H40: 72000 Marketing/Advertising | I40: 11200 Chase Checking 5189 | J40: 698.51 | K40: 16492.84 | M40: =J40 -> 698.51
B41: 07/30/2023 | C41: Expense | E41: No | F41: Google | G41: GOOGLE *ADSXXXXXXXXX cc@google.com CA 07/30 | H41: 72000 Marketing/Advertising | I41: 11200 Chase Checking 5189 | J41: 500 | K41: 16992.84 | M41: =J41 -> 500
B42: 08/01/2023 | C42: Expense | E42: No | F42: Google | G42: GOOGLE *ADSXXXXXXXXX cc@google.com CA 08/01 | H42: 72000 Marketing/Advertising | I42: 11200 Chase Checking 5189 | J42: 288.12 | K42: 17280.96 | M42: =J42 -> 288.12
B43: 08/04/2023 | C43: Credit Memo | D43: 9181 | E43: No | F43: KeHE Distributors LLC | G43: Promotion / Meijer Promo/ Chargeback | H43: 72000 Marketing/Advertising | I43: 12000 Accounts Receivable | J43: 1088.08 | K43: 18369.04 | R43: =J43 -> 1088.08
B44: 08/04/2023 | C44: Expense | E44: No | F44: UNFI | G44: WRDC0723A042034 - Quarterly Ad agrement West Region Basic - July, Aug, Sept 2023 | H44: 72000 Marketing/Advertising | I44: 11200 Chase Checking 5189 | J44: 480 | K44: 18849.04 | S44: =J44 -> 480
B45: 08/04/2023 | C45: Expense | E45: No | F45: Google | G45: GOOGLE *ADSXXXXXXXXX cc@google.com CA 08/04 | H45: 72000 Marketing/Advertising | I45: 11200 Chase Checking 5189 | J45: 500 | K45: 19349.04 | M45: =J45 -> 500
B46: 08/07/2023 | C46: Bill | D46: SINV10-006757167 | E46: No | F46: Advantage Sales & Marketing | G46: COLLATERAL 1.00 $950.24 950.24 | H46: 72000 Marketing/Advertising | I46: 31000 Accounts Payable | J46: 950.24 | K46: 20299.28 | T46: =J46 -> 950.24
B47: 08/07/2023 | C47: Bill | D47: SINV10-006757167 | E47: No | F47: Advantage Sales & Marketing | G47: Product Cost 1.00 $122.98 122.98 | H47: 72000 Marketing/Advertising | I47: 31000 Accounts Payable | J47: 122.98 | K47: 20422.26 | T47: =J47 -> 122.98
B48: 08/07/2023 | C48: Bill | D48: SINV10-006757167 | E48: No | F48: Advantage Sales & Marketing | G48: MEIJER EXPLORE MORE 2023 7/1/2023 P6 W2 FD - Bravado Spice JOB # 29707 6 STORES EXECUTED Buyer# 15 BRAVADO CREAMY HERB & JALAPENO SAUCE 5 OZ L5-000059 UPC 85077100520 PROGRAM COST 6.00 $199.00 1,194.00 | H48: 72000 Marketing/Advertising | I48: 31000 Accounts Payable | J48: 1194 | K48: 21616.26 | T48: =J48 -> 1194
B49: 08/07/2023 | C49: Expense | E49: No | F49: Google | G49: GOOGLE *ADSXXXXXXXXX cc@google.com CA 08/07 | H49: 72000 Marketing/Advertising | I49: 11200 Chase Checking 5189 | J49: 500 | K49: 22116.26 | M49: =J49 -> 500
B50: 08/10/2023 | C50: Expense | E50: No | F50: Google | G50: GOOGLE *ADSXXXXXXXXX cc@google.com CA 08/10 | H50: 72000 Marketing/Advertising | I50: 11200 Chase Checking 5189 | J50: 500 | K50: 22616.26 | M50: =J50 -> 500
B51: 08/13/2023 | C51: Expense | E51: No | F51: Google | G51: GOOGLE *ADSXXXXXXXXX cc@google.com CA 08/13 | H51: 72000 Marketing/Advertising | I51: 11200 Chase Checking 5189 | J51: 500 | K51: 23116.26 | M51: =J51 -> 500
B52: 08/16/2023 | C52: Credit Memo | D52: 9216 | E52: No | F52: KeHE Distributors LLC | G52: BGM82819_Scan / 97Advertising/ Brookshire Brothers MCB Invoice | H52: 72000 Marketing/Advertising | I52: 12000 Accounts Receivable | J52: 11.92 | K52: 23128.18 | R52: =J52 -> 11.92
B53: 08/21/2023 | C53: Expense | E53: No | F53: Google | G53: GOOGLE *ADSXXXXXXXXX cc@google.com CA 08/21 | H53: 72000 Marketing/Advertising | I53: 11200 Chase Checking 5189 | J53: 500 | K53: 23628.18 | M53: =J53 -> 500
B54: 08/29/2023 | C54: Expense | E54: No | F54: Google | G54: GOOGLE *ADSXXXXXXXXX cc@google.com CA 08/29 | H54: 72000 Marketing/Advertising | I54: 11200 Chase Checking 5189 | J54: 500 | K54: 24128.18 | M54: =J54 -> 500
B55: 08/31/2023 | C55: Expense | E55: No | G55: Invoice# ERDC0723A042034_Quarterly Ad Agreements East Region Basic - JULY, AUG, SEPT 2023_Annual Advertising ; EInvoice#RNACVTN0623B042034_June 2023 New Activation/ Reactivation SAR Item#162139 and #162141 | H55: 72000 Marketing/Advertising | I55: 11200 Chase Checking 5189 | J55: 1280 | K55: 25408.18 | Q55: =J55 -> 1280
B56: 09/01/2023 | C56: Credit Memo | D56: SUMSHOW2 | E56: No | F56: KeHE Distributors LLC | G56: SUMSHOW2/ | H56: 72000 Marketing/Advertising | I56: 12000 Accounts Receivable | J56: 7020 | K56: 32428.18 | R56: =J56 -> 7020
B57: 09/01/2023 | C57: Expense | E57: No | F57: Google | G57: GOOGLE *ADSXXXXXXXXX cc@google.com CA 09/01 | H57: 72000 Marketing/Advertising | I57: 11200 Chase Checking 5189 | J57: 120.57 | K57: 32548.75 | M57: =J57 -> 120.57
B58: 09/05/2023 | C58: Credit Memo | D58: MSF296018 | E58: No | F58: KeHE Distributors LLC | G58: MSF296018/ Promotion/ Meijer Promo | H58: 72000 Marketing/Advertising | I58: 12000 Accounts Receivable | J58: 396.8 | K58: 32945.55 | R58: =J58 -> 396.8
B59: 09/05/2023 | C59: Expense | E59: No | F59: Global Experience | G59: GLOBAL EXPERIENCE SPE XXX-XXX-XXXX NV 09/06 | H59: 72000 Marketing/Advertising | I59: 11200 Chase Checking 5189 | J59: 427.5 | K59: 33373.05 | Q59: =J59 -> 427.5
B60: 09/08/2023 | C60: Expense | E60: No | F60: Google | G60: GOOGLE *ADSXXXXXXXXX cc@google.com CA 09/08 | H60: 72000 Marketing/Advertising | I60: 11200 Chase Checking 5189 | J60: 500 | K60: 33873.05 | M60: =J60 -> 500
B61: 09/11/2023 | C61: Journal Entry | D61: AJE-42 | E61: No | G61: Invoice#RPSUMSHOW2 / bal due ck # 2366842 | H61: 72000 Marketing/Advertising | I61: -Split- | J61: -7020 | K61: 26853.05 | R61: =J61 -> -7020
B62: 09/12/2023 | C62: Deposit | E62: No | F62: Google | G62: Reversal: GOOGLE *ADSXXXXXXXXX cc@google.com CA XX/XX ClaimId: XXXXXXXXXXX0001 | H62: 72000 Marketing/Advertising | I62: 11200 Chase Checking 5189 | J62: -120.57 | K62: 26732.48 | M62: =J62 -> -120.57
B63: 09/12/2023 | C63: Deposit | E63: No | F63: Google | G63: Reversal: GOOGLE *ADSXXXXXXXXX cc@google.com CA XX/XX ClaimId: XXXXXXXXXXX0001 | H63: 72000 Marketing/Advertising | I63: 11200 Chase Checking 5189 | J63: -16.31 | K63: 26716.17 | M63: =J63 -> -16.31
B64: 09/12/2023 | C64: Deposit | E64: No | F64: Google | G64: Reversal: GOOGLE *ADSXXXXXXXXX cc@google.com CA XX/XX ClaimId: XXXXXXXXXXX0001 | H64: 72000 Marketing/Advertising | I64: 11200 Chase Checking 5189 | J64: -698.51 | K64: 26017.66 | M64: =J64 -> -698.51
B65: 09/12/2023 | C65: Deposit | E65: No | F65: Google | G65: Reversal: GOOGLE *ADSXXXXXXXXX cc@google.com CA XX/XX ClaimId: XXXXXXXXXXX0001 | H65: 72000 Marketing/Advertising | I65: 11200 Chase Checking 5189 | J65: -500 | K65: 25517.66 | M65: =J65 -> -500
B66: 09/12/2023 | C66: Deposit | E66: No | F66: Google | G66: Reversal: GOOGLE *ADSXXXXXXXXX cc@google.com CA XX/XX ClaimId: XXXXXXXXXXX0001 | H66: 72000 Marketing/Advertising | I66: 11200 Chase Checking 5189 | J66: -500 | K66: 25017.66 | M66: =J66 -> -500
B67: 09/12/2023 | C67: Deposit | E67: No | F67: Google | G67: Reversal: GOOGLE *ADSXXXXXXXXX cc@google.com CA XX/XX ClaimId: XXXXXXXXXXX0001 | H67: 72000 Marketing/Advertising | I67: 11200 Chase Checking 5189 | J67: -500 | K67: 24517.66 | M67: =J67 -> -500
B68: 09/12/2023 | C68: Deposit | E68: No | F68: Google | G68: Reversal: GOOGLE *ADSXXXXXXXXX cc@google.com CA XX/XX ClaimId: XXXXXXXXXXX0001 | H68: 72000 Marketing/Advertising | I68: 11200 Chase Checking 5189 | J68: -500 | K68: 24017.66 | M68: =J68 -> -500
B69: 09/12/2023 | C69: Deposit | E69: No | F69: Google | G69: Reversal: GOOGLE *ADSXXXXXXXXX cc@google.com CA XX/XX ClaimId: XXXXXXXXXXX0001 | H69: 72000 Marketing/Advertising | I69: 11200 Chase Checking 5189 | J69: -500 | K69: 23517.66 | M69: =J69 -> -500
B70: 09/12/2023 | C70: Deposit | E70: No | F70: Google | G70: Reversal: GOOGLE *ADSXXXXXXXXX cc@google.com CA XX/XX ClaimId: XXXXXXXXXXX0001 | H70: 72000 Marketing/Advertising | I70: 11200 Chase Checking 5189 | J70: -500 | K70: 23017.66 | M70: =J70 -> -500
B71: 09/12/2023 | C71: Deposit | E71: No | F71: Google | G71: Reversal: GOOGLE *ADSXXXXXXXXX cc@google.com CA XX/XX ClaimId: XXXXXXXXXXX0001 | H71: 72000 Marketing/Advertising | I71: 11200 Chase Checking 5189 | J71: -500 | K71: 22517.66 | M71: =J71 -> -500
B72: 09/12/2023 | C72: Deposit | E72: No | F72: Google | G72: Reversal: GOOGLE *ADSXXXXXXXXX cc@google.com CA XX/XX ClaimId: XXXXXXXXXXX0001 | H72: 72000 Marketing/Advertising | I72: 11200 Chase Checking 5189 | J72: -288.12 | K72: 22229.54 | M72: =J72 -> -288.12
B73: 09/14/2023 | C73: Deposit | E73: No | F73: Google | G73: ORIG CO NAME:GOOGLE ORIG ID:FXXXXXXXXX DESC DATE: CO ENTRY DESCR:ACCTVERIFYSEC:PPD TRACE#:XXXXXXXXXXXXXXX EED:XXXXXX IND ID: IND NAME:Chase TRN: XXXXXX6092TC | H73: 72000 Marketing/Advertising | I73: 11200 Chase Checking 5189 | J73: -0.23 | K73: 22229.31 | M73: =J73 -> -0.23
B74: 09/17/2023 | C74: Expense | E74: No | F74: Global Experience | G74: GLOBAL EXPERIENCE SPE XXX-XXX-XXXX NV 09/18 | H74: 72000 Marketing/Advertising | I74: 11200 Chase Checking 5189 | J74: 153.9 | K74: 22383.21 | Q74: =J74 -> 153.9
B75: 09/18/2023 | C75: Credit Memo | D75: 9358 | E75: No | F75: KeHE Distributors LLC | G75: I2220341 NewItem Setup FeeSEP 23 | H75: 72000 Marketing/Advertising | I75: 12000 Accounts Receivable | J75: 100 | K75: 22483.21 | R75: =J75 -> 100
B76: 09/20/2023 | C76: Expense | E76: No | F76: Global Experience | G76: GLOBAL EXPERIENCE SPE XXX-XXX-XXXX NV 09/21 | H76: 72000 Marketing/Advertising | I76: 11200 Chase Checking 5189 | J76: 319.68 | K76: 22802.89 | Q76: =J76 -> 319.68
B77: 09/26/2023 | C77: Credit Memo | D77: H0267801725 | E77: No | F77: KeHE Distributors LLC | G77: DOT25 | H77: 72000 Marketing/Advertising | I77: 12000 Accounts Receivable | J77: 135 | K77: 22937.89 | R77: =J77 -> 135
B78: 09/26/2023 | C78: Credit Memo | D78: MSF376218 | E78: No | F78: KeHE Distributors LLC | G78: Promotion | H78: 72000 Marketing/Advertising | I78: 12000 Accounts Receivable | J78: 471.2 | K78: 23409.09 | R78: =J78 -> 471.2
B79: 09/26/2023 | C79: Credit Memo | D79: MSF376218 | E79: No | F79: KeHE Distributors LLC | G79: 904435 | H79: 72000 Marketing/Advertising | I79: 12000 Accounts Receivable | J79: 471.2 | K79: 23880.29 | R79: =J79 -> 471.2
B80: 10/12/2023 | C80: Invoice | D80: 9402 | E80: No | F80: Wonders & Worries, Inc. | G80: Donation | H80: 72000 Marketing/Advertising | I80: 12000 Accounts Receivable | J80: 432 | K80: 24312.29 | Q80: =J80 -> 432
B81: 10/31/2023 | C81: Bill | D81: 0017180-IN | E81: No | F81: Mustard Seed Health Food Market, Inc. | G81: October 2023 CO-OP Mailer Advertising | H81: 72000 Marketing/Advertising | I81: 31000 Accounts Payable | J81: 300 | K81: 24612.29 | Q81: =J81 -> 300
B82: 10/31/2023 | C82: Bill | D82: 0017176-IN | E82: No | F82: Mustard Seed Health Food Market, Inc. | G82: October 2023 CO-OP Mailer Advertising | H82: 72000 Marketing/Advertising | I82: 31000 Accounts Payable | J82: 350 | K82: 24962.29 | Q82: =J82 -> 350
A83: Total for Marketing/Advertising | J83: 24962.29
A84: Freight & Delivery - Marketing
B85: 02/23/2023 | C85: Expense | E85: No | F85: America Tent Rentals | G85: AMERICA TENT RENTALS | H85: 72100 Marketing/Advertising:Freight & Delivery - Marketing | I85: Chase 0423 | J85: 439.23 | K85: 439.23 | Q85: =J85 -> 439.23
B86: 04/08/2023 | C86: Expense | E86: No | F86: Xposolutions Transportation LLC | G86: XPOSOLUTIONS TRANSPORTAT | H86: 72100 Marketing/Advertising:Freight & Delivery - Marketing | I86: 32400 Spark Business Credit Card - 4964 | J86: 897.95 | K86: 1337.18 | Q86: =J86 -> 897.95
B87: 05/31/2023 | C87: Expense | E87: No | F87: Xposolutions Transportation LLC | G87: & XPOSOLUTIONS TRANSPORTAT 866-371-0007 IL | H87: 72100 Marketing/Advertising:Freight & Delivery - Marketing | I87: Chase 0423 | J87: 474.4 | K87: 1811.58 | Q87: =J87 -> 474.4
B88: 06/01/2023 | C88: Check | D88: 1035 | E88: No | F88: Vashon Burcell | G88: 20 Pallets | H88: 72100 Marketing/Advertising:Freight & Delivery - Marketing | I88: 11200 Chase Checking 5189 | J88: 80 | K88: 1891.58 | Q88: =J88 -> 80
B89: 06/05/2023 | C89: Expense | E89: No | F89: Xposolutions Transportation LLC | G89: & XPOSOLUTIONS TRANSPORTAT 866-371-0007 IL | H89: 72100 Marketing/Advertising:Freight & Delivery - Marketing | I89: Chase 0423 | J89: 389.33 | K89: 2280.91 | Q89: =J89 -> 389.33
A90: Total for Freight & Delivery - Marketing | J90: 2280.91
A91: Social Media Marketing
B92: 01/19/2023 | C92: Expense | E92: No | F92: Kroger | G92: KROGER 312 HOUSTON TX | H92: 72200 Marketing/Advertising:Social Media Marketing | I92: Chase 0423 | J92: 30.72 | K92: 30.72 | Q92: =J92 -> 30.72
B93: 01/23/2023 | C93: Expense | E93: No | G93: paper source | H93: 72200 Marketing/Advertising:Social Media Marketing | I93: 11200 Chase Checking 5189 | J93: 20.23 | K93: 50.95 | Q93: =J93 -> 20.23
B94: 01/23/2023 | C94: Expense | E94: No | G94: arne's | H94: 72200 Marketing/Advertising:Social Media Marketing | I94: 11200 Chase Checking 5189 | J94: 25.36 | K94: 76.31 | Q94: =J94 -> 25.36
B95: 01/23/2023 | C95: Expense | E95: No | G95: any occasion tents events | H95: 72200 Marketing/Advertising:Social Media Marketing | I95: 11200 Chase Checking 5189 | J95: 122.01 | K95: 198.32 | Q95: =J95 -> 122.01
B96: 01/30/2023 | C96: Expense | E96: No | F96: Kroger | G96: KROGER 312 HOUSTON TX | H96: 72200 Marketing/Advertising:Social Media Marketing | I96: Chase 0423 | J96: 95.37 | K96: 293.69 | Q96: =J96 -> 95.37
B97: 01/31/2023 | C97: Expense | E97: No | F97: Kroger | G97: KROGER 309 HOUSTON TX | H97: 72200 Marketing/Advertising:Social Media Marketing | I97: Chase 0423 | J97: 37.32 | K97: 331.01 | Q97: =J97 -> 37.32
B98: 02/19/2023 | C98: Expense | E98: No | F98: Kroger | G98: KROGER 740 | H98: 72200 Marketing/Advertising:Social Media Marketing | I98: Chase 2639 | J98: 2.49 | K98: 333.5 | Q98: =J98 -> 2.49
B99: 03/08/2023 | C99: Expense | E99: No | F99: Facebook | G99: FACEBK HFZRLK3Z72 | H99: 72200 Marketing/Advertising:Social Media Marketing | I99: Chase 0423 | J99: 45.54 | K99: 379.04 | Q99: =J99 -> 45.54
B100: 03/17/2023 | C100: Expense | E100: No | F100: Kroger | G100: KROGER #600 | H100: 72200 Marketing/Advertising:Social Media Marketing | I100: 32400 Spark Business Credit Card - 4964 | J100: 24.84 | K100: 403.88 | Q100: =J100 -> 24.84
B101: 04/11/2023 | C101: Expense | E101: No | F101: Amazon | G101: " ULTNICE 4pcs Artificial Pepper Bouquet Durable Fake Chili Bouquet Simulation Fruits Pepper Bunch Plastic Fake Plant for Home Party Office Decor Sold by: Panyuan001 Return window closed on May 12, 2023 $16.49"//Uncat//props for marketing | H101: 72200 Marketing/Advertising:Social Media Marketing | I101: Business AMEX Card | J101: 17.85 | K101: 421.73 | Q101: =J101 -> 17.85
...

Sheet Travel
A1: Bravado Spice
A2: Transaction Report
A3: January - October, 2023
B5: Date | C5: Transaction Type | D5: Num | E5: Adj | F5: Name | G5: Memo/Description | H5: Account | I5: Split | J5: Amount | K5: Balance
A6: Travel
B7: 01/01/2023 | C7: Expense | E7: No | F7: Lyft | G7: LYFT *2 RIDES 12-29 | H7: 75000 Travel | I7: Chase 2639 | J7: 22.91 | K7: 22.91
B8: 01/01/2023 | C8: Expense | E8: No | F8: Exxon | G8: EXXONMOBIL 47942933 | H8: 75000 Travel | I8: Chase 2639 | J8: 16 | K8: 38.91
B9: 01/02/2023 | C9: Expense | E9: No | F9: Exxon | G9: EXXONMOBIL 47938998 | H9: 75000 Travel | I9: Chase 2639 | J9: 1.99 | K9: 40.9
B10: 01/02/2023 | C10: Expense | E10: No | F10: Exxon | G10: EXXONMOBIL 47942933 | H10: 75000 Travel | I10: 32400 Spark Business Credit Card - 4964 | J10: 26.59 | K10: 67.49
B11: 01/02/2023 | C11: Expense | E11: No | F11: Exxon | G11: EXXONMOBIL 47938998 | H11: 75000 Travel | I11: Chase 2639 | J11: 29.55 | K11: 97.04
B12: 01/04/2023 | C12: Expense | E12: No | F12: Ekko Fuels | G12: EKKO FUELS | H12: 75000 Travel | I12: Chase 2639 | J12: 18.47 | K12: 115.51
B13: 01/04/2023 | C13: Expense | E13: No | F13: Ekko Fuels | G13: EKKO FUELS | H13: 75000 Travel | I13: Chase 2639 | J13: 27.99 | K13: 143.5
B14: 01/05/2023 | C14: Expense | E14: No | F14: Lyft | G14: LYFT *RIDE TUE 7AM | H14: 75000 Travel | I14: Chase 2639 | J14: 12.76 | K14: 156.26
B15: 01/08/2023 | C15: Expense | E15: No | F15: Exxon | G15: EXXONMOBIL 48295521 | H15: 75000 Travel | I15: Chase 2639 | J15: 10.06 | K15: 166.32
B16: 01/08/2023 | C16: Expense | E16: No | F16: Lyft | G16: LYFT *1 RIDE 01-06 | H16: 75000 Travel | I16: Chase 2639 | J16: 11.99 | K16: 178.31
B17: 01/08/2023 | C17: Expense | E17: No | F17: Lyft | G17: LYFT *1 RIDE 01-05 | H17: 75000 Travel | I17: Chase 2639 | J17: 12.78 | K17: 191.09
B18: 01/09/2023 | C18: Expense | E18: No | F18: Exxon | G18: EXXONMOBIL 47939723 | H18: 75000 Travel | I18: 32400 Spark Business Credit Card - 4964 | J18: 44.92 | K18: 236.01
... B39: 01/21/2023 | C39: Expense | E39: No | F39: Westgate | G39: WESTGATE LV RESORTCASINO | H39: 75000 Travel | I39: 32400 Spark Business Credit Card - 4964 | J39: 902.48 | K39: 3268.95
B40: 01/23/2023 | C40: Expense | E40: No | G40: exxon | H40: 75000 Travel | I40: 11200 Chase Checking 5189 | J40: 36.37 | K40: 3305.32
B41: 01/23/2023 | C41: Expense | E41: No | F41: Lyft | G41: LYFT *2 RIDES 01-18 855-865-95 53 CA 01/21 | H41: 75000 Travel | I41: 11200 Chase Checking 5189 | J41: 67.5 | K41: 3372.82
B42: 01/23/2023 | C42: Expense | E42: No | F42: Lyft | G42: LYFT *2 RIDES 01-21 | H42: 75000 Travel | I42: Chase 0423 | J42: 45.9 | K42: 3418.72
B43: 01/24/2023 | C43: Expense | E43: No | F43: Lyft | G43: LYFT *1 RIDE 01-22 | H43: 75000 Travel | I43: Chase 0423 | J43: 20.73 | K43: 3439.45
B44: 01/25/2023 | C44: Expense | E44: No | F44: Exxon | G44: EXXONMOBIL 47942933 | H44: 75000 Travel | I44: Chase 2639 | J44: 49.03 | K44: 3488.48
B45: 01/26/2023 | C45: Expense | E45: No | F45: Lyft | G45: LYFT *RIDE WED 4PM | H45: 75000 Travel | I45: Chase 0423 | J45: 12.99 | K45: 3501.47
B46: 01/26/2023 | C46: Expense | E46: No | F46: Lyft | G46: LYFT *2 RIDES 01-24 | H46: 75000 Travel | I46: Chase 0423 | J46: 29.39 | K46: 3530.86
B47: 01/27/2023 | C47: Expense | E47: No | F47: Lyft | G47: LYFT *1 RIDE 01-25 | H47: 75000 Travel | I47: Chase 0423 | J47: 14.99 | K47: 3545.85
B48: 01/29/2023 | C48: Expense | E48: No | F48: Chevron | G48: CHEVRON 0108129 HOUSTON TX | H48: 75000 Travel | I48: Chase 0423 | J48: 20 | K48: 3565.85
B49: 01/29/2023 | C49: Expense | E49: No | F49: Shell | G49: SHELL OIL12979923013 SPRING TX | H49: 75000 Travel | I49: Credit card (9532) | J49: 16.57 | K49: 3582.42
B50: 01/29/2023 | C50: Expense | E50: No | F50: Exxon | G50: EXXONMOBIL 47942933 | H50: 75000 Travel | I50: Chase 2639 | J50: 24.66 | K50: 3607.08
